Workbook

Sheet Executive Summary
B2: SITE SELECTION · COVINGTON, KENTON COUNTY KY | I2: Prepared for the Board of Directors
B3: PUPS PUB COVINGTON | I3: Data as of 2 August 2026
B4: The Tail Chase List — every commercial parcel in the city, scored and ranked | I4: Kenton County PVA · LINK-GIS · LoopNet
B7: HOW THE FIELD WAS NARROWED
B9: 16,103 | D9: 384 | F9: 337 | H9: 328 | J9: 25
B10: Parcels in Covington | D10: Pass use & size screen | F10: Privately held | H10: Fully scored | J10: Drive-by shortlist
B13: TOP 15 TAIL CHASE TARGETS | I13: Score = factor points x scoped multipliers (v8) — see Scoring Method
A15: # | B15: Address | C15: Owner of record | D15: Current use | E15: Lot AC | F15: Bldg SF | G15: Yard SF | H15: Mi | I15: Neighborhood | J15: Est. rent | K15: Score
A16: 1 | B16: 209 JOHNSON ST | C16: RICHMOND RODNEY C TRUSTEE | D16: SMALL SHOP | E16: 0.3 | F16: 3000 | G16: 9900 | H16: 0.13 | I16: Botany Hills / Riverfront West | J16: $2,750/mo | K16: 82.3
A17: 2 | B17: 401-419 GREENUP ST | C17: RP PROP OZ LLC | D17: OTHER RETAIL | E17: 0.46 | F17: 1325 | G17: 10650 | H17: 0.26 | I17: Central Business District | J17: $1,215/mo | K17: 78.8
A18: 3 | B18: 409 MAIN ST | C18: SMITH HOLDING CO INC | D18: AUTO SERVICE/REPAIR | E18: 1.01 | F18: 14720 | G18: 27500 | H18: 0.1 | I18: MainStrasse | J18: $13,493/mo | K18: 78.6
A19: 4 | B19: 805 RUSSELL ST | C19: SEMINARY SQUARE II LLC | D19: GARAGE/PARKING SPACE | E19: 0.71 | G19: 30375 | H19: 0.22 | I19: MainStrasse | J19: — | K19: 78.5
A20: 5 | B20: 248 W PIKE ST | C20: CLAYPOOL PROPERTIES LLC | D20: WHSE DISTRIBUTION | E20: 0.87 | F20: 22064 | G20: 13300 | H20: 0.25 | I20: MainStrasse | J20: $20,225/mo | K20: 78.1
A21: 6 | B21: 409 W 4TH ST | C21: SMITH HOLDING CO INC | D21: AUTO SERVICE/REPAIR | E21: 0.48 | F21: 9000 | G21: 9650 | H21: 0.13 | I21: Botany Hills / Riverfront West | J21: $8,250/mo | K21: 77.5
A22: 7 | B22: 325 GREENUP ST | C22: BUTT LLC | D22: PAVED LOT | E22: 0.34 | F22: 2891 | G22: 14400 | H22: 0.22 | I22: Central Business District | J22: $2,650/mo | K22: 77.1
A23: 8 | B23: 620 W 5TH ST | C23: SKYLIGHT CINCINNATI HOLDING | D23: PAVED LOT | E23: 0.77 | G23: 33200 | H23: 0.18 | I23: MainStrasse | J23: — | K23: 75.5
A24: 9 | B24: 617 HINDE ST | C24: GABE HOLDINGS LLC | D24: SMALL SHOP | E24: 0.75 | G24: 30400 | H24: 0.72 | I24: Lewisburg | J24: — | K24: 74.7
A25: 10 | B25: 423 SCOTT ST | C25: DECASTRO MANAGEMENT LLC | D25: AUTO SERVICE/REPAIR | E25: 0.83 | F25: 17586 | G25: 17825 | H25: 0.18 | I25: Central Business District | J25: $16,120/mo | K25: 74.5
A26: 11 | B26: 101 W 6TH ST | C26: DIOCESE OF COVINGTON | D26: PAVED LOT | E26: 0.46 | G26: 19775 | H26: 0.06 | I26: Central Business District | J26: — | K26: 74.4
A27: 12 | B27: 102 8TH ST W | C27: PIKE PARTNERS LLC | D27: PAVED LOT | E27: 0.55 | G27: 23550 | H27: 0.17 | I27: Central Business District | J27: — | K27: 74.4
A28: 13 | B28: 601 SCOTT ST | C28: 608 MADISON LLC | D28: LAND/W MISCELLANEOUS IMPROVEMENT | E28: 0.52 | G28: 21625 | H28: 0.1 | I28: Central Business District | J28: — | K28: 74.4
A29: 14 | B29: 16 W 9TH ST | C29: BLUE BRIDGE LLC | D29: WHSE DISTRIBUTION | E29: 0.78 | F29: 31448 | G29: 12025 | H29: 0.18 | I29: Central Business District | J29: $28,827/mo | K29: 74
A30: 15 | B30: 305 W PIKE ST | C30: DUPONT VENTURES LLC | D30: RETAIL W/APARTMENTS | E30: 0.5 | F30: 4878 | G30: 7875 | H30: 0.35 | I30: MainStrasse | J30: $4,472/mo | K30: 72.7
B33: WHAT THE DATA SAYS
B35: ▸ Location and convertibility drive the ranking.
B36: The two strongest predictors of owner field ratings are distance to a walkable district (26 pts) and whether the shell can actually be opened up (20 pts). Both validated positively against 23 site visits.
B39: ▸ Chain-occupied pads look good on paper and are not obtainable.
B40: 46 parcels are held by a national brand or a net-lease investor. They score well physically and were rated 1–4 by the owner. An availability multiplier now pushes them out of contention.
B43: ▸ Usable yard is far smaller than lot arithmetic suggests.
B44: Measuring open space geometrically — and deleting any strip under 20 ft wide — cut apparent outdoor area by half or more on tight downtown parcels, and to zero on several.
B47: ▸ Oversized parcels are capped by design.
B48: Nothing above 1.25 acres reaches the top half of the list. The largest candidates remain visible but carry a 0.65 multiplier reflecting cost and complexity a single venue cannot absorb.
B51: WHAT THIS MODEL DOES NOT KNOW
B53: • Rent is assumed, not quoted — $11/SF gross against an $11,000/month target. No public Covington lease comps exist; every figure needs broker confirmation.
B56: • Crime is partly estimated — 5 of 14 neighbourhoods carry a NeighborhoodScout-sourced ranking; the remainder are judgment calls, flagged in the Scoring Method tab.
... B62: • Building size is mixed-source — LoopNet gross area where available, otherwise a single-storey footprint from GIS geometry, which understates multi-storey buildings.
A64: • Flood is now FEMA-sourced — NFHL zones joined 2 Aug 2026 for all 328 parcels (296 X · 22 levee-protected X · 7 shaded X · 3 AE). The 5/4/3.5/0 sub-band split is an owner-approved weighting decision, not a FEMA designation.
A65: • Zoning now scores — v7 multiplier (1.0/0.9/0.7/0.5/0.3 by NDC bar-status tier, owner-approved 2 Aug 2026) discounts Location and Convertibility only. 422 Russell falls #1→#45 (TUR: bars prohibited; restaurant/microbrewery alt-paths remain). New #1: 401-419 Greenup St (DTC). SU parcels provisional pending corner-lot check.
A66: • Model v8 (2 Aug 2026): multipliers are factor-scoped (availability -> location/building/convertibility; lot-size -> yard/building/convertibility; zoning -> location/convertibility). Crime/flood/environmental immune. 17 LoopNet building-SF corrections applied (157/328 verified). Compare ranks, not raw scores, across model versions. | B66: Model agreement with owner field ratings: r = +0.71 across 23 rated parcels.

Sheet Tail Chase List
A1: Rank | B1: Parcel ID | C1: Address | D1: Owner Name | E1: Mailing Address | F1: Mail City | G1: Mail ST | H1: Current Use | I1: Lot SF | J1: Lot Acres | K1: Perimeter FT | L1: Compactness | M1: Lot Band | N1: Structure Tier | O1: Compact Band | P1: Env Risk | Q1: Absentee Tier | R1: Owner Class | S1: Portfolio | T1: Site Fit | U1: Readiness | V1: Combined | W1: Building SF | X1: Flood Zone (FEMA NFHL) | Y1: Outdoor SF | Z1: Coverage % | AA1: Parking Est | AB1: Market Status | AC1: LoopNet Lot AC | AD1: Lot Variance | AE1: Bldg Fit Band | AF1: Verified Fit | AG1: Verified Combined | AH1: Data Source | AI1: Lat | AJ1: Lon | AK1: Mi to MainStrasse | AL1: Mi to Roebling Pt | AM1: Mi to Cincy CBD | AN1: Mi to Core | AO1: Location Band | AP1: Convertibility | AQ1: Outdoor Band | AR1: Crime Risk | AS1: Verified Fit v2 | AT1: Verified Combined v2 | AU1: Neighborhood | AV1: Crime Index | AW1: Crime Source | AX1: Crime Band | AY1: Fit v3 | AZ1: COMBINED v3 | BA1: Availability Class | BB1: Avail Multiplier | BC1: Lot Size Class | BD1: Lot Multiplier | BE1: Fit (raw factor sum) | BF1: CHASE SCORE v8 | BG1: Budget Fit @ $11k | BH1: NDC District | BI1: District Name | BJ1: HP Overlay | BK1: 12th St Corridor | BL1: NDC Bar Status | BM1: Zoning Mult
A2: 1 | B2: 054-22-40-001.01 | C2: 1206 CHESAPEAKE ST | D2: KIRN RONALD C & MELISSA | E2: 408 OLIVIA LN | F2: FT WRIGHT | G2: KY | H2: AUTO SERVICE/REPAIR | I2: 22126 | J2: =I2/43560 | K2: 595 | L2: =I2/(K2^2) | M2: Ideal 18-32k | N2: A | O2: Compact >=.055 | P2: Moderate | Q2: Out-of-city KY | R2: Individual | S2: 2 | T2: =INDEX('Scoring Method'!$B$6:$B$9,MATCH(M2,'Scoring Method'!$A$6:$A$9,0))+INDEX('Scoring Method'!$B$12:$B$16,MATCH(N2,'Scoring Method'!$A$12:$A$16,0))+INDEX('Scoring Method'!$B$19:$B$22,MATCH(O2,'Scoring Method'!$A$19:$A$22,0))+INDEX('Scoring Method'!$B$25:$B$27,MATCH(P2,'Scoring Method'!$A$25:$A$27,0)) | U2: =(INDEX('Scoring Method'!$B$30:$B$33,MATCH(Q2,'Scoring Method'!$A$30:$A$33,0))+INDEX('Scoring Method'!$B$36:$B$42,MATCH(R2,'Scoring Method'!$A$36:$A$42,0))+INDEX('Scoring Method'!$B$45:$B$47,MATCH(IF(S2=1,"1",IF(S2=2,"2","3+")),'Scoring Method'!$A$45:$A$47,0)))/90*100 | V2: =T2*U2/100 | W2: 5000 | X2: X (minimal hazard) | Y2: 15000 | Z2: =W2/I2 | AA2: =MAX(0,(Y2-5000)/300) | AC2: 0.51 | AD2: ok | AE2: Large 4-6k | AF2: =INDEX('Scoring Method'!$B$63:$B$71,MATCH(AE2,'Scoring Method'!$A$63:$A$71,0))+INDEX('Scoring Method'!$B$75:$B$79,MATCH("Ample >=15k",'Scoring Method'!$A$75:$A$79,0))+INDEX('Scoring Method'!$B$343:$B$347,MATCH(X2,'Scoring Method'!$A$343:$A$347,0))+INDEX('Scoring Method'!$B$25:$B$27,MATCH(P2,'Scoring Method'!$A$25:$A$27,0)) | AG2: =AF2*U2/100 | AH2: LINK-GIS + LoopNet | AI2: 39.07696 | AJ2: -84.51056 | AK2: 0.65 | AL2: 0.97 | AM2: 1.7 | AN2: 0.49 | AO2: Near 0.35-0.75mi | AP2: Open span | AQ2: Ample >=15k | AS2: =ROUND(INDEX('Scoring Method'!$B$63:$B$70,MATCH(AE2,'Scoring Method'!$A$63:$A$70,0))*0.625+INDEX('Scoring Method'!$B$105:$B$113,MATCH(AP2,'Scoring Method'!$A$105:$A$113,0))+INDEX('Scoring Method'!$B$74:$B$78,MATCH(AQ2,'Scoring Method'!$A$74:$A$78,0))*0.6667+INDEX('Scoring Method'!$B$96:$B$101,MATCH(AO2,'Scoring Method'!$A$96:$A$101,0))+INDEX('Scoring Method'!$B$343:$B$347,MATCH(X2,'Scoring Method'!$A$343:$A$347,0))*0.3333+INDEX('Scoring Method'!$B$25:$B$27,MATCH(P2,'Scoring Method'!$A$25:$A$27,0))*0.3333,1) | AT2: =AS2*U2/100 | AU2: Old Seminary Square | AV2: 35 | AW2: ESTIMATED | AX2: Elevated 35-44 | AY2: =ROUND(INDEX('Scoring Method'!$B$132:$B$140,MATCH(AE2,'Scoring Method'!$A$132:$A$140,0))+INDEX('Scoring Method'!$B$144:$B$152,MATCH(AP2,'Scoring Method'!$A$144:$A$152,0))+INDEX('Scoring Method'!$B$156:$B$160,MATCH(AQ2,'Scoring Method'!$A$156:$A$160,0))+INDEX('Scoring Method'!$B$164:$B$169,MATCH(AO2,'Scoring Method'!$A$164:$A$169,0))+INDEX('Scoring Method'!$B$173:$B$178,MATCH(AX2,'Scoring Method'!$A$173:$A$178,0))+INDEX('Scoring Method'!$B$349:$B$353,MATCH(X2,'Scoring Method'!$A$349:$A$353,0))+INDEX('Scoring Method'!$B$188:$B$190,MATCH(P2,'Scoring Method'!$A$188:$A$190,0)),1) | AZ2: =AY2*U2/100 | BA2: No chain signal | BB2: 1 | BC2: Right-sized 0.35-0.75 AC | BD2: 1 | BE2: =ROUND(INDEX('Scoring Method'!$B$268:$B$276,MATCH(AE2,'Scoring Method'!$A$268:$A$276,0))+INDEX('Scoring Method'!$B$280:$B$288,MATCH(AP2,'Scoring Method'!$A$280:$A$288,0))+INDEX('Scoring Method'!$B$292:$B$296,MATCH(AQ2,'Scoring Method'!$A$292:$A$296,0))+INDEX('Scoring Method'!$B$300:$B$305,MATCH(AO2,'Scoring Method'!$A$300:$A$305,0))+INDEX('Scoring Method'!$B$309:$B$314,MATCH(AX2,'Scoring Method'!$A$309:$A$314,0))+INDEX('Scoring Method'!$B$337:$B$341,MATCH(X2,'Scoring Method'!$A$337:$A$341,0))+INDEX('Scoring Method'!$B$324:$B$326,MATCH(P2,'Scoring Method'!$A$324:$A$326,0)),1) | BF2: =ROUND(INDEX('Scoring Method'!$B$268:$B$276,MATCH(AE2,'Scoring Method'!$A$268:$A$276,0))*BB2*BD2+INDEX('Scoring Method'!$B$280:$B$288,MATCH(AP2,'Scoring Method'!$A$280:$A$288,0))*BM2*BB2*BD2+INDEX('Scoring Method'!$B$292:$B$296,MATCH(AQ2,'Scoring Method'!$A$292:$A$296,0))*BD2+INDEX('Scoring Method'!$B$300:$B$305,MATCH(AO2,'Scoring Method'!$A$300:$A$305,0))*BM2*BB2+INDEX('Scoring Method'!$B$309:$B$314,MATCH(AX2,'Scoring Method'!$A$309:$A$314,0))+INDEX('Scoring Method'!$B$337:$B$341,MATCH(X2,'Scoring Method'!$A$337:$A$341,0))+INDEX('Scoring Method'!$B$324:$B$326,MATCH(P2,'Scoring Method'!$A$324:$A$326,0)),1) | BG2: Fits (~$4,583/mo) | BH2: LI (TS) | BI2: Limited Industrial | BK2: Yes | BL2: Bar prohibited, alt-path | BM2: =INDEX('Scoring Method'!$B$358:$B$363,MATCH(BL2,'Scoring Method'!$A$358:$A$363,0))
A3: 2 | B3: 055-14-12-003.00 | C3: 1901 MADISON AVE | D3: NEW HORIZON PROPERTIES LLC | E3: 3000 READING RD | F3: CINCINNATI | G3: OH | H3: AUTO SERVICE/REPAIR | I3: 18667 | J3: =I3/43560 | K3: 658.2 | L3: =I3/(K3^2) | M3: Ideal 18-32k | N3: A | O3: Elongated .035-.045 | P3: Moderate | Q3: Out-of-state | R3: Passive vehicle | S3: 2 | T3: =INDEX('Scoring Method'!$B$6:$B$9,MATCH(M3,'Scoring Method'!$A$6:$A$9,0))+INDEX('Scoring Method'!$B$12:$B$16,MATCH(N3,'Scoring Method'!$A$12:$A$16,0))+INDEX('Scoring Method'!$B$19:$B$22,MATCH(O3,'Scoring Method'!$A$19:$A$22,0))+INDEX('Scoring Method'!$B$25:$B$27,MATCH(P3,'Scoring Method'!$A$25:$A$27,0)) | U3: =(INDEX('Scoring Method'!$B$30:$B$33,MATCH(Q3,'Scoring Method'!$A$30:$A$33,0))+INDEX('Scoring Method'!$B$36:$B$42,MATCH(R3,'Scoring Method'!$A$36:$A$42,0))+INDEX('Scoring Method'!$B$45:$B$47,MATCH(IF(S3=1,"1",IF(S3=2,"2","3+")),'Scoring Method'!$A$45:$A$47,0)))/90*100 | V3: =T3*U3/100 | W3: 1260 | X3: X (minimal hazard) | Y3: 15475 | Z3: =W3/I3 | AA3: =MAX(0,(Y3-5000)/300) | AC3: 0.43 | AD3: ok | AE3: Below 1.2-1.5k | AF3: =INDEX('Scoring Method'!$B$63:$B$71,MATCH(AE3,'Scoring Method'!$A$63:$A$71,0))+INDEX('Scoring Method'!$B$75:$B$79,MATCH("Ample >=15k",'Scoring Method'!$A$75:$A$79,0))+INDEX('Scoring Method'!$B$343:$B$347,MATCH(X3,'Scoring Method'!$A$343:$A$347,0))+INDEX('Scoring Method'!$B$25:$B$27,MATCH(P3,'Scoring Method'!$A$25:$A$27,0)) | AG3: =AF3*U3/100 | AH3: LINK-GIS + LoopNet | AI3: 39.06755 | AJ3: -84.50646 | AK3: 1.32 | AL3: 1.61 | AM3: 2.37 | AN3: 1.16 | AO3: Fringe 0.75-1.25mi | AP3: Open span | AQ3: Ample >=15k | AS3: =ROUND(INDEX('Scoring Method'!$B$63:$B$70,MATCH(AE3,'Scoring Method'!$A$63:$A$70,0))*0.625+INDEX('Scoring Method'!$B$105:$B$113,MATCH(AP3,'Scoring Method'!$A$105:$A$113,0))+INDEX('Scoring Method'!$B$74:$B$78,MATCH(AQ3,'Scoring Method'!$A$74:$A$78,0))*0.6667+INDEX('Scoring Method'!$B$96:$B$101,MATCH(AO3,'Scoring Method'!$A$96:$A$101,0))+INDEX('Scoring Method'!$B$343:$B$347,MATCH(X3,'Scoring Method'!$A$343:$A$347,0))*0.3333+INDEX('Scoring Method'!$B$25:$B$27,MATCH(P3,'Scoring Method'!$A$25:$A$27,0))*0.3333,1) | AT3: =AS3*U3/100 | AU3: Levassor Park | AV3: 42 | AW3: ESTIMATED | AX3: Elevated 35-44 | AY3: =ROUND(INDEX('Scoring Method'!$B$132:$B$140,MATCH(AE3,'Scoring Method'!$A$132:$A$140,0))+INDEX('Scoring Method'!$B$144:$B$152,MATCH(AP3,'Scoring Method'!$A$144:$A$152,0))+INDEX('Scoring Method'!$B$156:$B$160,MATCH(AQ3,'Scoring Method'!$A$156:$A$160,0))+INDEX('Scoring Method'!$B$164:$B$169,MATCH(AO3,'Scoring Method'!$A$164:$A$169,0))+INDEX('Scoring Method'!$B$173:$B$178,MATCH(AX3,'Scoring Method'!$A$173:$A$178,0))+INDEX('Scoring Method'!$B$349:$B$353,MATCH(X3,'Scoring Method'!$A$349:$A$353,0))+INDEX('Scoring Method'!$B$188:$B$190,MATCH(P3,'Scoring Method'!$A$188:$A$190,0)),1) | AZ3: =AY3*U3/100 | BA3: No chain signal | BB3: 1 | BC3: Right-sized 0.35-0.75 AC | BD3: 1 | BE3: =ROUND(INDEX('Scoring Method'!$B$268:$B$276,MATCH(AE3,'Scoring Method'!$A$268:$A$276,0))+INDEX('Scoring Method'!$B$280:$B$288,MATCH(AP3,'Scoring Method'!$A$280:$A$288,0))+INDEX('Scoring Method'!$B$292:$B$296,MATCH(AQ3,'Scoring Method'!$A$292:$A$296,0))+INDEX('Scoring Method'!$B$300:$B$305,MATCH(AO3,'Scoring Method'!$A$300:$A$305,0))+INDEX('Scoring Method'!$B$309:$B$314,MATCH(AX3,'Scoring Method'!$A$309:$A$314,0))+INDEX('Scoring Method'!$B$337:$B$341,MATCH(X3,'Scoring Method'!$A$337:$A$341,0))+INDEX('Scoring Method'!$B$324:$B$326,MATCH(P3,'Scoring Method'!$A$324:$A$326,0)),1) | BF3: =ROUND(INDEX('Scoring Method'!$B$268:$B$276,MATCH(AE3,'Scoring Method'!$A$268:$A$276,0))*BB3*BD3+INDEX('Scoring Method'!$B$280:$B$288,MATCH(AP3,'Scoring Method'!$A$280:$A$288,0))*BM3*BB3*BD3+INDEX('Scoring Method'!$B$292:$B$296,MATCH(AQ3,'Scoring Method'!$A$292:$A$296,0))*BD3+INDEX('Scoring Method'!$B$300:$B$305,MATCH(AO3,'Scoring Method'!$A$300:$A$305,0))*BM3*BB3+INDEX('Scoring Method'!$B$309:$B$314,MATCH(AX3,'Scoring Method'!$A$309:$A$314,0))+INDEX('Scoring Method'!$B$337:$B$341,MATCH(X3,'Scoring Method'!$A$337:$A$341,0))+INDEX('Scoring Method'!$B$324:$B$326,MATCH(P3,'Scoring Method'!$A$324:$A$326,0)),1) | BG3: Fits (~$1,155/mo) | BH3: AUC | BI3: Auto-Urban Commercial | BL3: Bar permitted | BM3: =INDEX('Scoring Method'!$B$358:$B$363,MATCH(BL3,'Scoring Method'!$A$358:$A$363,0))
A4: 3 | B4: 040-43-07-001.01 | C4: 501 W 4TH ST | D4: DAYAN MICHELLE & CHEN | E4: 2424 RIDGE RD | F4: ROCKWALL | G4: TX | H4: FAST FOOD-DRIVE THRU REST | I4: 23325 | J4: =I4/43560 | K4: 645 | L4: =I4/(K4^2) | M4: Ideal 18-32k | N4: C | O4: Compact >=.055 | P4: Low | Q4: Out-of-state | R4: Individual | S4: 1 | T4: =INDEX('Scoring Method'!$B$6:$B$9,MATCH(M4,'Scoring Method'!$A$6:$A$9,0))+INDEX('Scoring Method'!$B$12:$B$16,MATCH(N4,'Scoring Method'!$A$12:$A$16,0))+INDEX('Scoring Method'!$B$19:$B$22,MATCH(O4,'Scoring Method'!$A$19:$A$22,0))+INDEX('Scoring Method'!$B$25:$B$27,MATCH(P4,'Scoring Method'!$A$25:$A$27,0)) | U4: =(INDEX('Scoring Method'!$B$30:$B$33,MATCH(Q4,'Scoring Method'!$A$30:$A$33,0))+INDEX('Scoring Method'!$B$36:$B$42,MATCH(R4,'Scoring Method'!$A$36:$A$42,0))+INDEX('Scoring Method'!$B$45:$B$47,MATCH(IF(S4=1,"1",IF(S4=2,"2","3+")),'Scoring Method'!$A$45:$A$47,0)))/90*100 | V4: =T4*U4/100 | X4: X (minimal hazard) | Y4: 20300 | AC4: 0.54 | AD4: ok | AE4: No building | AF4: =INDEX('Scoring Method'!$B$63:$B$71,MATCH(AE4,'Scoring Method'!$A$63:$A$71,0))+INDEX('Scoring Method'!$B$75:$B$79,MATCH("Ample >=15k",'Scoring Method'!$A$75:$A$79,0))+INDEX('Scoring Method'!$B$343:$B$347,MATCH(X4,'Scoring Method'!$A$343:$A$347,0))+INDEX('Scoring Method'!$B$25:$B$27,MATCH(P4,'Scoring Method'!$A$25:$A$27,0)) | AG4: =AF4*U4/100 | AH4: LINK-GIS + LoopNet | AI4: 39.08608 | AJ4: -84.51918 | AK4: 0.14 | AL4: 0.67 | AM4: 1.13 | AN4: 0.14 | AO4: Core <=0.35mi | AP4: Built-out kitchen | AQ4: Ample >=15k | AS4: =ROUND(INDEX('Scoring Method'!$B$63:$B$70,MATCH(AE4,'Scoring Method'!$A$63:$A$70,0))*0.625+INDEX('Scoring Method'!$B$105:$B$113,MATCH(AP4,'Scoring Method'!$A$105:$A$113,0))+INDEX('Scoring Method'!$B$74:$B$78,MATCH(AQ4,'Scoring Method'!$A$74:$A$78,0))*0.6667+INDEX('Scoring Method'!$B$96:$B$101,MATCH(AO4,'Scoring Method'!$A$96:$A$101,0))+INDEX('Scoring Method'!$B$343:$B$347,MATCH(X4,'Scoring Method'!$A$343:$A$347,0))*0.3333+INDEX('Scoring Method'!$B$25:$B$27,MATCH(P4,'Scoring Method'!$A$25:$A$27,0))*0.3333,1) | AT4: =AS4*U4/100 | AU4: Botany Hills / Riverfront West | AV4: 45 | AW4: ESTIMATED | AX4: Mixed 45-59 | AY4: =ROUND(INDEX('Scoring Method'!$B$132:$B$140,MATCH(AE4,'Scoring Method'!$A$132:$A$140,0))+INDEX('Scoring Method'!$B$144:$B$152,MATCH(AP4,'Scoring Method'!$A$144:$A$152,0))+INDEX('Scoring Method'!$B$156:$B$160,MATCH(AQ4,'Scoring Method'!$A$156:$A$160,0))+INDEX('Scoring Method'!$B$164:$B$169,MATCH(AO4,'Scoring Method'!$A$164:$A$169,0))+INDEX('Scoring Method'!$B$173:$B$178,MATCH(AX4,'Scoring Method'!$A$173:$A$178,0))+INDEX('Scoring Method'!$B$349:$B$353,MATCH(X4,'Scoring Method'!$A$349:$A$353,0))+INDEX('Scoring Method'!$B$188:$B$190,MATCH(P4,'Scoring Method'!$A$188:$A$190,0)),1) | AZ4: =AY4*U4/100 | BA4: Chain format + local owner | BB4: 0.7 | BC4: Right-sized 0.35-0.75 AC | BD4: 1 | BE4: =ROUND(INDEX('Scoring Method'!$B$268:$B$276,MATCH(AE4,'Scoring Method'!$A$268:$A$276,0))+INDEX('Scoring Method'!$B$280:$B$288,MATCH(AP4,'Scoring Method'!$A$280:$A$288,0))+INDEX('Scoring Method'!$B$292:$B$296,MATCH(AQ4,'Scoring Method'!$A$292:$A$296,0))+INDEX('Scoring Method'!$B$300:$B$305,MATCH(AO4,'Scoring Method'!$A$300:$A$305,0))+INDEX('Scoring Method'!$B$309:$B$314,MATCH(AX4,'Scoring Method'!$A$309:$A$314,0))+INDEX('Scoring Method'!$B$337:$B$341,MATCH(X4,'Scoring Method'!$A$337:$A$341,0))+INDEX('Scoring Method'!$B$324:$B$326,MATCH(P4,'Scoring Method'!$A$324:$A$326,0)),1) | BF4: =ROUND(INDEX('Scoring Method'!$B$268:$B$276,MATCH(AE4,'Scoring Method'!$A$268:$A$276,0))*BB4*BD4+INDEX('Scoring Method'!$B$280:$B$288,MATCH(AP4,'Scoring Method'!$A$280:$A$288,0))*BM4*BB4*BD4+INDEX('Scoring Method'!$B$292:$B$296,MATCH(AQ4,'Scoring Method'!$A$292:$A$296,0))*BD4+INDEX('Scoring Method'!$B$300:$B$305,MATCH(AO4,'Scoring Method'!$A$300:$A$305,0))*BM4*BB4+INDEX('Scoring Method'!$B$309:$B$314,MATCH(AX4,'Scoring Method'!$A$309:$A$314,0))+INDEX('Scoring Method'!$B$337:$B$341,MATCH(X4,'Scoring Method'!$A$337:$A$341,0))+INDEX('Scoring Method'!$B$324:$B$326,MATCH(P4,'Scoring Method'!$A$324:$A$326,0)),1) | BH4: AUC | BI4: Auto-Urban Commercial | BL4: Bar permitted | BM4: =INDEX('Scoring Method'!$B$358:$B$363,MATCH(BL4,'Scoring Method'!$A$358:$A$363,0))
A5: 4 | B5: 054-23-13-001.00 | C5: 602 SCOTT ST | D5: CUMMINS THOMAS M & PATRICIA | E5: 3638 ROUND BOTTOM RD | F5: CINCINNATI | G5: OH | H5: FAST FOOD-DRIVE THRU REST | I5: 22010 | J5: =I5/43560 | K5: 612 | L5: =I5/(K5^2) | M5: Ideal 18-32k | N5: C | O5: Compact >=.055 | P5: Low | Q5: Out-of-state | R5: Individual | S5: 1 | T5: =INDEX('Scoring Method'!$B$6:$B$9,MATCH(M5,'Scoring Method'!$A$6:$A$9,0))+INDEX('Scoring Method'!$B$12:$B$16,MATCH(N5,'Scoring Method'!$A$12:$A$16,0))+INDEX('Scoring Method'!$B$19:$B$22,MATCH(O5,'Scoring Method'!$A$19:$A$22,0))+INDEX('Scoring Method'!$B$25:$B$27,MATCH(P5,'Scoring Method'!$A$25:$A$27,0)) | U5: =(INDEX('Scoring Method'!$B$30:$B$33,MATCH(Q5,'Scoring Method'!$A$30:$A$33,0))+INDEX('Scoring Method'!$B$36:$B$42,MATCH(R5,'Scoring Method'!$A$36:$A$42,0))+INDEX('Scoring Method'!$B$45:$B$47,MATCH(IF(S5=1,"1",IF(S5=2,"2","3+")),'Scoring Method'!$A$45:$A$47,0)))/90*100 | V5: =T5*U5/100 | W5: 2350 | X5: X (minimal hazard) | Y5: 16775 | Z5: =W5/I5 | AA5: =MAX(0,(Y5-5000)/300) | AC5: 0.51 | AD5: ok | AE5: Target 1.5-2.5k | AF5: =INDEX('Scoring Method'!$B$63:$B$71,MATCH(AE5,'Scoring Method'!$A$63:$A$71,0))+INDEX('Scoring Method'!$B$75:$B$79,MATCH("Ample >=15k",'Scoring Method'!$A$75:$A$79,0))+INDEX('Scoring Method'!$B$343:$B$347,MATCH(X5,'Scoring Method'!$A$343:$A$347,0))+INDEX('Scoring Method'!$B$25:$B$27,MATCH(P5,'Scoring Method'!$A$25:$A$27,0)) | AG5: =AF5*U5/100 | AH5: LINK-GIS + LoopNet | AI5: 39.08475 | AJ5: -84.50838 | AK5: 0.51 | AL5: 0.42 | AM5: 1.18 | AN5: 0.15 | AO5: Core <=0.35mi | AP5: Built-out kitchen | AQ5: Ample >=15k | AS5: =ROUND(INDEX('Scoring Method'!$B$63:$B$70,MATCH(AE5,'Scoring Method'!$A$63:$A$70,0))*0.625+INDEX('Scoring Method'!$B$105:$B$113,MATCH(AP5,'Scoring Method'!$A$105:$A$113,0))+INDEX('Scoring Method'!$B$74:$B$78,MATCH(AQ5,'Scoring Method'!$A$74:$A$78,0))*0.6667+INDEX('Scoring Method'!$B$96:$B$101,MATCH(AO5,'Scoring Method'!$A$96:$A$101,0))+INDEX('Scoring Method'!$B$343:$B$347,MATCH(X5,'Scoring Method'!$A$343:$A$347,0))*0.3333+INDEX('Scoring Method'!$B$25:$B$27,MATCH(P5,'Scoring Method'!$A$25:$A$27,0))*0.3333,1) | AT5: =AS5*U5/100 | AU5: Central Business District | AV5: 48 | AW5: ESTIMATED | AX5: Mixed 45-59 | AY5: =ROUND(INDEX('Scoring Method'!$B$132:$B$140,MATCH(AE5,'Scoring Method'!$A$132:$A$140,0))+INDEX('Scoring Method'!$B$144:$B$152,MATCH(AP5,'Scoring Method'!$A$144:$A$152,0))+INDEX('Scoring Method'!$B$156:$B$160,MATCH(AQ5,'Scoring Method'!$A$156:$A$160,0))+INDEX('Scoring Method'!$B$164:$B$169,MATCH(AO5,'Scoring Method'!$A$164:$A$169,0))+INDEX('Scoring Method'!$B$173:$B$178,MATCH(AX5,'Scoring Method'!$A$173:$A$178,0))+INDEX('Scoring Method'!$B$349:$B$353,MATCH(X5,'Scoring Method'!$A$349:$A$353,0))+INDEX('Scoring Method'!$B$188:$B$190,MATCH(P5,'Scoring Method'!$A$188:$A$190,0)),1) | AZ5: =AY5*U5/100 | BA5: Chain format + local owner | BB5: 0.7 | BC5: Right-sized 0.35-0.75 AC | BD5: 1 | BE5: =ROUND(INDEX('Scoring Method'!$B$268:$B$276,MATCH(AE5,'Scoring Method'!$A$268:$A$276,0))+INDEX('Scoring Method'!$B$280:$B$288,MATCH(AP5,'Scoring Method'!$A$280:$A$288,0))+INDEX('Scoring Method'!$B$292:$B$296,MATCH(AQ5,'Scoring Method'!$A$292:$A$296,0))+INDEX('Scoring Method'!$B$300:$B$305,MATCH(AO5,'Scoring Method'!$A$300:$A$305,0))+INDEX('Scoring Method'!$B$309:$B$314,MATCH(AX5,'Scoring Method'!$A$309:$A$314,0))+INDEX('Scoring Method'!$B$337:$B$341,MATCH(X5,'Scoring Method'!$A$337:$A$341,0))+INDEX('Scoring Method'!$B$324:$B$326,MATCH(P5,'Scoring Method'!$A$324:$A$326,0)),1) | BF5: =ROUND(INDEX('Scoring Method'!$B$268:$B$276,MATCH(AE5,'Scoring Method'!$A$268:$A$276,0))*BB5*BD5+INDEX('Scoring Method'!$B$280:$B$288,MATCH(AP5,'Scoring Method'!$A$280:$A$288,0))*BM5*BB5*BD5+INDEX('Scoring Method'!$B$292:$B$296,MATCH(AQ5,'Scoring Method'!$A$292:$A$296,0))*BD5+INDEX('Scoring Method'!$B$300:$B$305,MATCH(AO5,'Scoring Method'!$A$300:$A$305,0))*BM5*BB5+INDEX('Scoring Method'!$B$309:$B$314,MATCH(AX5,'Scoring Method'!$A$309:$A$314,0))+INDEX('Scoring Method'!$B$337:$B$341,MATCH(X5,'Scoring Method'!$A$337:$A$341,0))+INDEX('Scoring Method'!$B$324:$B$326,MATCH(P5,'Scoring Method'!$A$324:$A$326,0)),1) | BG5: Fits (~$2,154/mo) | BH5: DTC (HP) | BI5: Downtown Core | BJ5: HP | BL5: Bar permitted | BM5: =INDEX('Scoring Method'!$B$358:$B$363,MATCH(BL5,'Scoring Method'!$A$358:$A$363,0))
A6: 5 | B6: 054-24-03-004.00 | C6: 1041 MADISON AVE | D6: MURPHY & ROWDY ENTERPRISES LLC | E6: 915 W 8TH ST | F6: CINCINNATI | G6: OH | H6: MFG/ASSEMBLY 20000 SF OR LESS | I6: 20908 | J6: =I6/43560 | K6: 639.1 | L6: =I6/(K6^2) | M6: Ideal 18-32k | N6: A | O6: Regular .045-.055 | P6: Moderate | Q6: Out-of-state | R6: Passive vehicle | S6: 1 | T6: =INDEX('Scoring Method'!$B$6:$B$9,MATCH(M6,'Scoring Method'!$A$6:$A$9,0))+INDEX('Scoring Method'!$B$12:$B$16,MATCH(N6,'Scoring Method'!$A$12:$A$16,0))+INDEX('Scoring Method'!$B$19:$B$22,MATCH(O6,'Scoring Method'!$A$19:$A$22,0))+INDEX('Scoring Method'!$B$25:$B$27,MATCH(P6,'Scoring Method'!$A$25:$A$27,0)) | U6: =(INDEX('Scoring Method'!$B$30:$B$33,MATCH(Q6,'Scoring Method'!$A$30:$A$33,0))+INDEX('Scoring Method'!$B$36:$B$42,MATCH(R6,'Scoring Method'!$A$36:$A$42,0))+INDEX('Scoring Method'!$B$45:$B$47,MATCH(IF(S6=1,"1",IF(S6=2,"2","3+")),'Scoring Method'!$A$45:$A$47,0)))/90*100 | V6: =T6*U6/100 | W6: 14000 | X6: X (minimal hazard) | Y6: 3225 | Z6: =W6/I6 | AA6: =MAX(0,(Y6-5000)/300) | AC6: 0.44 | AD6: ok | AE6: Far oversize >12k | AF6: =INDEX('Scoring Method'!$B$63:$B$71,MATCH(AE6,'Scoring Method'!$A$63:$A$71,0))+INDEX('Scoring Method'!$B$75:$B$79,MATCH("Tight 2-5k",'Scoring Method'!$A$75:$A$79,0))+INDEX('Scoring Method'!$B$343:$B$347,MATCH(X6,'Scoring Method'!$A$343:$A$347,0))+INDEX('Scoring Method'!$B$25:$B$27,MATCH(P6,'Scoring Method'!$A$25:$A$27,0)) | AG6: =AF6*U6/100 | AH6: LINK-GIS + LoopNet | AI6: 39.07912 | AJ6: -84.50942 | AK6: 0.58 | AL6: 0.81 | AM6: 1.55 | AN6: 0.35 | AO6: Core <=0.35mi | AP6: Open span | AQ6: Tight 2-5k | AS6: =ROUND(INDEX('Scoring Method'!$B$63:$B$70,MATCH(AE6,'Scoring Method'!$A$63:$A$70,0))*0.625+INDEX('Scoring Method'!$B$105:$B$113,MATCH(AP6,'Scoring Method'!$A$105:$A$113,0))+INDEX('Scoring Method'!$B$74:$B$78,MATCH(AQ6,'Scoring Method'!$A$74:$A$78,0))*0.6667+INDEX('Scoring Method'!$B$96:$B$101,MATCH(AO6,'Scoring Method'!$A$96:$A$101,0))+INDEX('Scoring Method'!$B$343:$B$347,MATCH(X6,'Scoring Method'!$A$343:$A$347,0))*0.3333+INDEX('Scoring Method'!$B$25:$B$27,MATCH(P6,'Scoring Method'!$A$25:$A$27,0))*0.3333,1) | AT6: =AS6*U6/100 | AU6: Central Business District | AV6: 48 | AW6: ESTIMATED | AX6: Mixed 45-59 | AY6: =ROUND(INDEX('Scoring Method'!$B$132:$B$140,MATCH(AE6,'Scoring Method'!$A$132:$A$140,0))+INDEX('Scoring Method'!$B$144:$B$152,MATCH(AP6,'Scoring Method'!$A$144:$A$152,0))+INDEX('Scoring Method'!$B$156:$B$160,MATCH(AQ6,'Scoring Method'!$A$156:$A$160,0))+INDEX('Scoring Method'!$B$164:$B$169,MATCH(AO6,'Scoring Method'!$A$164:$A$169,0))+INDEX('Scoring Method'!$B$173:$B$178,MATCH(AX6,'Scoring Method'!$A$173:$A$178,0))+INDEX('Scoring Method'!$B$349:$B$353,MATCH(X6,'Scoring Method'!$A$349:$A$353,0))+INDEX('Scoring Method'!$B$188:$B$190,MATCH(P6,'Scoring Method'!$A$188:$A$190,0)),1) | AZ6: =AY6*U6/100 | BA6: No chain signal | BB6: 1 | BC6: Right-sized 0.35-0.75 AC | BD6: 1 | BE6: =ROUND(INDEX('Scoring Method'!$B$268:$B$276,MATCH(AE6,'Scoring Method'!$A$268:$A$276,0))+INDEX('Scoring Method'!$B$280:$B$288,MATCH(AP6,'Scoring Method'!$A$280:$A$288,0))+INDEX('Scoring Method'!$B$292:$B$296,MATCH(AQ6,'Scoring Method'!$A$292:$A$296,0))+INDEX('Scoring Method'!$B$300:$B$305,MATCH(AO6,'Scoring Method'!$A$300:$A$305,0))+INDEX('Scoring Method'!$B$309:$B$314,MATCH(AX6,'Scoring Method'!$A$309:$A$314,0))+INDEX('Scoring Method'!$B$337:$B$341,MATCH(X6,'Scoring Method'!$A$337:$A$341,0))+INDEX('Scoring Method'!$B$324:$B$326,MATCH(P6,'Scoring Method'!$A$324:$A$326,0)),1) | BF6: =ROUND(INDEX('Scoring Method'!$B$268:$B$276,MATCH(AE6,'Scoring Method'!$A$268:$A$276,0))*BB6*BD6+INDEX('Scoring Method'!$B$280:$B$288,MATCH(AP6,'Scoring Method'!$A$280:$A$288,0))*BM6*BB6*BD6+INDEX('Scoring Method'!$B$292:$B$296,MATCH(AQ6,'Scoring Method'!$A$292:$A$296,0))*BD6+INDEX('Scoring Method'!$B$300:$B$305,MATCH(AO6,'Scoring Method'!$A$300:$A$305,0))*BM6*BB6+INDEX('Scoring Method'!$B$309:$B$314,MATCH(AX6,'Scoring Method'!$A$309:$A$314,0))+INDEX('Scoring Method'!$B$337:$B$341,MATCH(X6,'Scoring Method'!$A$337:$A$341,0))+INDEX('Scoring Method'!$B$324:$B$326,MATCH(P6,'Scoring Method'!$A$324:$A$326,0)),1) | BG6: Over (~$12,833/mo) | BH6: DTC | BI6: Downtown Core | BL6: Bar permitted | BM6: =INDEX('Scoring Method'!$B$358:$B$363,MATCH(BL6,'Scoring Method'!$A$358:$A$363,0))
A7: 6 | B7: 056-31-09-002.00 | C7: 119 E 32ND ST | D7: MW & MW PROPERTIES INC | E7: PO BOX 15609 | F7: COVINGTON | G7: KY | H7: SMALL SHOP | I7: 19464 | J7: =I7/43560 | K7: 712.4 | L7: =I7/(K7^2) | M7: Ideal 18-32k | N7: A | O7: Elongated .035-.045 | P7: Low | Q7: Local absentee | R7: Passive vehicle | S7: 3 | T7: =INDEX('Scoring Method'!$B$6:$B$9,MATCH(M7,'Scoring Method'!$A$6:$A$9,0))+INDEX('Scoring Method'!$B$12:$B$16,MATCH(N7,'Scoring Method'!$A$12:$A$16,0))+INDEX('Scoring Method'!$B$19:$B$22,MATCH(O7,'Scoring Method'!$A$19:$A$22,0))+INDEX('Scoring Method'!$B$25:$B$27,MATCH(P7,'Scoring Method'!$A$25:$A$27,0)) | U7: =(INDEX('Scoring Method'!$B$30:$B$33,MATCH(Q7,'Scoring Method'!$A$30:$A$33,0))+INDEX('Scoring Method'!$B$36:$B$42,MATCH(R7,'Scoring Method'!$A$36:$A$42,0))+INDEX('Scoring Method'!$B$45:$B$47,MATCH(IF(S7=1,"1",IF(S7=2,"2","3+")),'Scoring Method'!$A$45:$A$47,0)))/90*100 | V7: =T7*U7/100 | W7: 5110 | X7: X (minimal hazard) | Y7: 10525 | Z7: =W7/I7 | AA7: =MAX(0,(Y7-5000)/300) | AC7: 0.45 | AD7: ok | AE7: Large 4-6k | AF7: =INDEX('Scoring Method'!$B$63:$B$71,MATCH(AE7,'Scoring Method'!$A$63:$A$71,0))+INDEX('Scoring Method'!$B$75:$B$79,MATCH("Good 8-15k",'Scoring Method'!$A$75:$A$79,0))+INDEX('Scoring Method'!$B$343:$B$347,MATCH(X7,'Scoring Method'!$A$343:$A$347,0))+INDEX('Scoring Method'!$B$25:$B$27,MATCH(P7,'Scoring Method'!$A$25:$A$27,0)) | AG7: =AF7*U7/100 | AH7: LINK-GIS + LoopNet | AI7: 39.05315 | AJ7: -84.5004 | AK7: 2.35 | AL7: 2.64 | AM7: 3.4 | AN7: 2.21 | AO7: Distant 2-3mi | AP7: Open span | AQ7: Good 8-15k | AS7: =ROUND(INDEX('Scoring Method'!$B$63:$B$70,MATCH(AE7,'Scoring Method'!$A$63:$A$70,0))*0.625+INDEX('Scoring Method'!$B$105:$B$113,MATCH(AP7,'Scoring Method'!$A$105:$A$113,0))+INDEX('Scoring Method'!$B$74:$B$78,MATCH(AQ7,'Scoring Method'!$A$74:$A$78,0))*0.6667+INDEX('Scoring Method'!$B$96:$B$101,MATCH(AO7,'Scoring Method'!$A$96:$A$101,0))+INDEX('Scoring Method'!$B$343:$B$347,MATCH(X7,'Scoring Method'!$A$343:$A$347,0))*0.3333+INDEX('Scoring Method'!$B$25:$B$27,MATCH(P7,'Scoring Method'!$A$25:$A$27,0))*0.3333,1) | AT7: =AS7*U7/100 | AU7: Latonia | AV7: 78 | AW7: Sourced | AX7: Safe 70-79 | AY7: =ROUND(INDEX('Scoring Method'!$B$132:$B$140,MATCH(AE7,'Scoring Method'!$A$132:$A$140,0))+INDEX('Scoring Method'!$B$144:$B$152,MATCH(AP7,'Scoring Method'!$A$144:$A$152,0))+INDEX('Scoring Method'!$B$156:$B$160,MATCH(AQ7,'Scoring Method'!$A$156:$A$160,0))+INDEX('Scoring Method'!$B$164:$B$169,MATCH(AO7,'Scoring Method'!$A$164:$A$169,0))+INDEX('Scoring Method'!$B$173:$B$178,MATCH(AX7,'Scoring Method'!$A$173:$A$178,0))+INDEX('Scoring Method'!$B$349:$B$353,MATCH(X7,'Scoring Method'!$A$349:$A$353,0))+INDEX('Scoring Method'!$B$188:$B$190,MATCH(P7,'Scoring Method'!$A$188:$A$190,0)),1) | AZ7: =AY7*U7/100 | BA7: No chain signal | BB7: 1 | BC7: Right-sized 0.35-0.75 AC | BD7: 1 | BE7: =ROUND(INDEX('Scoring Method'!$B$268:$B$276,MATCH(AE7,'Scoring Method'!$A$268:$A$276,0))+INDEX('Scoring Method'!$B$280:$B$288,MATCH(AP7,'Scoring Method'!$A$280:$A$288,0))+INDEX('Scoring Method'!$B$292:$B$296,MATCH(AQ7,'Scoring Method'!$A$292:$A$296,0))+INDEX('Scoring Method'!$B$300:$B$305,MATCH(AO7,'Scoring Method'!$A$300:$A$305,0))+INDEX('Scoring Method'!$B$309:$B$314,MATCH(AX7,'Scoring Method'!$A$309:$A$314,0))+INDEX('Scoring Method'!$B$337:$B$341,MATCH(X7,'Scoring Method'!$A$337:$A$341,0))+INDEX('Scoring Method'!$B$324:$B$326,MATCH(P7,'Scoring Method'!$A$324:$A$326,0)),1) | BF7: =ROUND(INDEX('Scoring Method'!$B$268:$B$276,MATCH(AE7,'Scoring Method'!$A$268:$A$276,0))*BB7*BD7+INDEX('Scoring Method'!$B$280:$B$288,MATCH(AP7,'Scoring Method'!$A$280:$A$288,0))*BM7*BB7*BD7+INDEX('Scoring Method'!$B$292:$B$296,MATCH(AQ7,'Scoring Method'!$A$292:$A$296,0))*BD7+INDEX('Scoring Method'!$B$300:$B$305,MATCH(AO7,'Scoring Method'!$A$300:$A$305,0))*BM7*BB7+INDEX('Scoring Method'!$B$309:$B$314,MATCH(AX7,'Scoring Method'!$A$309:$A$314,0))+INDEX('Scoring Method'!$B$337:$B$341,MATCH(X7,'Scoring Method'!$A$337:$A$341,0))+INDEX('Scoring Method'!$B$324:$B$326,MATCH(P7,'Scoring Method'!$A$324:$A$326,0)),1) | BG7: Fits (~$4,684/mo) | BH7: GI | BI7: General Industrial | BL7: No path | BM7: =INDEX('Scoring Method'!$B$358:$B$363,MATCH(BL7,'Scoring Method'!$A$358:$A$363,0))
A8: 7 | B8: 056-11-09-003.00 | C8: 3022 MADISON AVE | D8: JCR INVESTMENTS LLC | E8: 9455 TEBBS CT | F8: HARRISON | G8: OH | H8: LAUNDROMAT | I8: 20578 | J8: =I8/43560 | K8: 605.9 | L8: =I8/(K8^2) | M8: Ideal 18-32k | N8: C | O8: Compact >=.055 | P8: Low | Q8: Out-of-state | R8: Passive vehicle | S8: 1 | T8: =INDEX('Scoring Method'!$B$6:$B$9,MATCH(M8,'Scoring Method'!$A$6:$A$9,0))+INDEX('Scoring Method'!$B$12:$B$16,MATCH(N8,'Scoring Method'!$A$12:$A$16,0))+INDEX('Scoring Method'!$B$19:$B$22,MATCH(O8,'Scoring Method'!$A$19:$A$22,0))+INDEX('Scoring Method'!$B$25:$B$27,MATCH(P8,'Scoring Method'!$A$25:$A$27,0)) | U8: =(INDEX('Scoring Method'!$B$30:$B$33,MATCH(Q8,'Scoring Method'!$A$30:$A$33,0))+INDEX('Scoring Method'!$B$36:$B$42,MATCH(R8,'Scoring Method'!$A$36:$A$42,0))+INDEX('Scoring Method'!$B$45:$B$47,MATCH(IF(S8=1,"1",IF(S8=2,"2","3+")),'Scoring Method'!$A$45:$A$47,0)))/90*100 | V8: =T8*U8/100 | W8: 2300 | X8: X (minimal hazard) | Y8: 17650 | Z8: =W8/I8 | AA8: =MAX(0,(Y8-5000)/300) | AC8: 0.45 | AD8: ok | AE8: Target 1.5-2.5k | AF8: =INDEX('Scoring Method'!$B$63:$B$71,MATCH(AE8,'Scoring Method'!$A$63:$A$71,0))+INDEX('Scoring Method'!$B$75:$B$79,MATCH("Ample >=15k",'Scoring Method'!$A$75:$A$79,0))+INDEX('Scoring Method'!$B$343:$B$347,MATCH(X8,'Scoring Method'!$A$343:$A$347,0))+INDEX('Scoring Method'!$B$25:$B$27,MATCH(P8,'Scoring Method'!$A$25:$A$27,0)) | AG8: =AF8*U8/100 | AH8: LINK-GIS + LoopNet | AI8: 39.05255 | AJ8: -84.51619 | AK8: 2.2 | AL8: 2.68 | AM8: 3.39 | AN8: 2.19 | AO8: Distant 2-3mi | AP8: Retail shell | AQ8: Ample >=15k | AS8: =ROUND(INDEX('Scoring Method'!$B$63:$B$70,MATCH(AE8,'Scoring Method'!$A$63:$A$70,0))*0.625+INDEX('Scoring Method'!$B$105:$B$113,MATCH(AP8,'Scoring Method'!$A$105:$A$113,0))+INDEX('Scoring Method'!$B$74:$B$78,MATCH(AQ8,'Scoring Method'!$A$74:$A$78,0))*0.6667+INDEX('Scoring Method'!$B$96:$B$101,MATCH(AO8,'Scoring Method'!$A$96:$A$101,0))+INDEX('Scoring Method'!$B$343:$B$347,MATCH(X8,'Scoring Method'!$A$343:$A$347,0))*0.3333+INDEX('Scoring Method'!$B$25:$B$27,MATCH(P8,'Scoring Method'!$A$25:$A$27,0))*0.3333,1) | AT8: =AS8*U8/100 | AU8: Latonia Rosedale | AV8: 68 | AW8: Sourced | AX8: Moderate 60-69 | AY8: =ROUND(INDEX('Scoring Method'!$B$132:$B$140,MATCH(AE8,'Scoring Method'!$A$132:$A$140,0))+INDEX('Scoring Method'!$B$144:$B$152,MATCH(AP8,'Scoring Method'!$A$144:$A$152,0))+INDEX('Scoring Method'!$B$156:$B$160,MATCH(AQ8,'Scoring Method'!$A$156:$A$160,0))+INDEX('Scoring Method'!$B$164:$B$169,MATCH(AO8,'Scoring Method'!$A$164:$A$169,0))+INDEX('Scoring Method'!$B$173:$B$178,MATCH(AX8,'Scoring Method'!$A$173:$A$178,0))+INDEX('Scoring Method'!$B$349:$B$353,MATCH(X8,'Scoring Method'!$A$349:$A$353,0))+INDEX('Scoring Method'!$B$188:$B$190,MATCH(P8,'Scoring Method'!$A$188:$A$190,0)),1) | AZ8: =AY8*U8/100 | BA8: No chain signal | BB8: 1 | BC8: Right-sized 0.35-0.75 AC | BD8: 1 | BE8: =ROUND(INDEX('Scoring Method'!$B$268:$B$276,MATCH(AE8,'Scoring Method'!$A$268:$A$276,0))+INDEX('Scoring Method'!$B$280:$B$288,MATCH(AP8,'Scoring Method'!$A$280:$A$288,0))+INDEX('Scoring Method'!$B$292:$B$296,MATCH(AQ8,'Scoring Method'!$A$292:$A$296,0))+INDEX('Scoring Method'!$B$300:$B$305,MATCH(AO8,'Scoring Method'!$A$300:$A$305,0))+INDEX('Scoring Method'!$B$309:$B$314,MATCH(AX8,'Scoring Method'!$A$309:$A$314,0))+INDEX('Scoring Method'!$B$337:$B$341,MATCH(X8,'Scoring Method'!$A$337:$A$341,0))+INDEX('Scoring Method'!$B$324:$B$326,MATCH(P8,'Scoring Method'!$A$324:$A$326,0)),1) | BF8: =ROUND(INDEX('Scoring Method'!$B$268:$B$276,MATCH(AE8,'Scoring Method'!$A$268:$A$276,0))*BB8*BD8+INDEX('Scoring Method'!$B$280:$B$288,MATCH(AP8,'Scoring Method'!$A$280:$A$288,0))*BM8*BB8*BD8+INDEX('Scoring Method'!$B$292:$B$296,MATCH(AQ8,'Scoring Method'!$A$292:$A$296,0))*BD8+INDEX('Scoring Method'!$B$300:$B$305,MATCH(AO8,'Scoring Method'!$A$300:$A$305,0))*BM8*BB8+INDEX('Scoring Method'!$B$309:$B$314,MATCH(AX8,'Scoring Method'!$A$309:$A$314,0))+INDEX('Scoring Method'!$B$337:$B$341,MATCH(X8,'Scoring Method'!$A$337:$A$341,0))+INDEX('Scoring Method'!$B$324:$B$326,MATCH(P8,'Scoring Method'!$A$324:$A$326,0)),1) | BG8: Fits (~$2,108/mo) | BH8: SU | BI8: Semi-Urban Residential | BL8: SU corner unverified | BM8: =INDEX('Scoring Method'!$B$358:$B$363,MATCH(BL8,'Scoring Method'!$A$358:$A$363,0))
A9: 8 | B9: 040-34-06-001.02 | C9: 316 PHILADELPHIA ST | D9: CURTIS JAMES INVESTMENTS | E9: PO BOX 6969 | F9: SYRACUSE | G9: NY | H9: FAST FOOD-DRIVE THRU REST | I9: 29874 | J9: =I9/43560 | K9: 692 | L9: =I9/(K9^2) | M9: Ideal 18-32k | N9: C | O9: Compact >=.055 | P9: Low | Q9: Out-of-state | R9: Passive vehicle | S9: 1 | T9: =INDEX('Scoring Method'!$B$6:$B$9,MATCH(M9,'Scoring Method'!$A$6:$A$9,0))+INDEX('Scoring Method'!$B$12:$B$16,MATCH(N9,'Scoring Method'!$A$12:$A$16,0))+INDEX('Scoring Method'!$B$19:$B$22,MATCH(O9,'Scoring Method'!$A$19:$A$22,0))+INDEX('Scoring Method'!$B$25:$B$27,MATCH(P9,'Scoring Method'!$A$25:$A$27,0)) | U9: =(INDEX('Scoring Method'!$B$30:$B$33,MATCH(Q9,'Scoring Method'!$A$30:$A$33,0))+INDEX('Scoring Method'!$B$36:$B$42,MATCH(R9,'Scoring Method'!$A$36:$A$42,0))+INDEX('Scoring Method'!$B$45:$B$47,MATCH(IF(S9=1,"1",IF(S9=2,"2","3+")),'Scoring Method'!$A$45:$A$47,0)))/90*100 | V9: =T9*U9/100 | W9: 2759 | X9: X (levee-protected) | Y9: 25925 | Z9: =W9/I9 | AA9: =MAX(0,(Y9-5000)/300) | AC9: 0.69 | AD9: ok | AE9: Above 2.5-4k | AF9: =INDEX('Scoring Method'!$B$63:$B$71,MATCH(AE9,'Scoring Method'!$A$63:$A$71,0))+INDEX('Scoring Method'!$B$75:$B$79,MATCH("Ample >=15k",'Scoring Method'!$A$75:$A$79,0))+INDEX('Scoring Method'!$B$343:$B$347,MATCH(X9,'Scoring Method'!$A$343:$A$347,0))+INDEX('Scoring Method'!$B$25:$B$27,MATCH(P9,'Scoring Method'!$A$25:$A$27,0)) | AG9: =AF9*U9/100 | AH9: LINK-GIS + LoopNet | AI9: 39.08678 | AJ9: -84.51954 | AK9: 0.19 | AL9: 0.66 | AM9: 1.09 | AN9: 0.19 | AO9: Core <=0.35mi | AP9: Built-out kitchen | AQ9: Ample >=15k | AS9: =ROUND(INDEX('Scoring Method'!$B$63:$B$70,MATCH(AE9,'Scoring Method'!$A$63:$A$70,0))*0.625+INDEX('Scoring Method'!$B$105:$B$113,MATCH(AP9,'Scoring Method'!$A$105:$A$113,0))+INDEX('Scoring Method'!$B$74:$B$78,MATCH(AQ9,'Scoring Method'!$A$74:$A$78,0))*0.6667+INDEX('Scoring Method'!$B$96:$B$101,MATCH(AO9,'Scoring Method'!$A$96:$A$101,0))+INDEX('Scoring Method'!$B$343:$B$347,MATCH(X9,'Scoring Method'!$A$343:$A$347,0))*0.3333+INDEX('Scoring Method'!$B$25:$B$27,MATCH(P9,'Scoring Method'!$A$25:$A$27,0))*0.3333,1) | AT9: =AS9*U9/100 | AU9: Botany Hills / Riverfront West | AV9: 45 | AW9: ESTIMATED | AX9: Mixed 45-59 | AY9: =ROUND(INDEX('Scoring Method'!$B$132:$B$140,MATCH(AE9,'Scoring Method'!$A$132:$A$140,0))+INDEX('Scoring Method'!$B$144:$B$152,MATCH(AP9,'Scoring Method'!$A$144:$A$152,0))+INDEX('Scoring Method'!$B$156:$B$160,MATCH(AQ9,'Scoring Method'!$A$156:$A$160,0))+INDEX('Scoring Method'!$B$164:$B$169,MATCH(AO9,'Scoring Method'!$A$164:$A$169,0))+INDEX('Scoring Method'!$B$173:$B$178,MATCH(AX9,'Scoring Method'!$A$173:$A$178,0))+INDEX('Scoring Method'!$B$349:$B$353,MATCH(X9,'Scoring Method'!$A$349:$A$353,0))+INDEX('Scoring Method'!$B$188:$B$190,MATCH(P9,'Scoring Method'!$A$188:$A$190,0)),1) | AZ9: =AY9*U9/100 | BA9: Chain format + investor | BB9: 0.45 | BC9: Right-sized 0.35-0.75 AC | BD9: 1 | BE9: =ROUND(INDEX('Scoring Method'!$B$268:$B$276,MATCH(AE9,'Scoring Method'!$A$268:$A$276,0))+INDEX('Scoring Method'!$B$280:$B$288,MATCH(AP9,'Scoring Method'!$A$280:$A$288,0))+INDEX('Scoring Method'!$B$292:$B$296,MATCH(AQ9,'Scoring Method'!$A$292:$A$296,0))+INDEX('Scoring Method'!$B$300:$B$305,MATCH(AO9,'Scoring Method'!$A$300:$A$305,0))+INDEX('Scoring Method'!$B$309:$B$314,MATCH(AX9,'Scoring Method'!$A$309:$A$314,0))+INDEX('Scoring Method'!$B$337:$B$341,MATCH(X9,'Scoring Method'!$A$337:$A$341,0))+INDEX('Scoring Method'!$B$324:$B$326,MATCH(P9,'Scoring Method'!$A$324:$A$326,0)),1) | BF9: =ROUND(INDEX('Scoring Method'!$B$268:$B$276,MATCH(AE9,'Scoring Method'!$A$268:$A$276,0))*BB9*BD9+INDEX('Scoring Method'!$B$280:$B$288,MATCH(AP9,'Scoring Method'!$A$280:$A$288,0))*BM9*BB9*BD9+INDEX('Scoring Method'!$B$292:$B$296,MATCH(AQ9,'Scoring Method'!$A$292:$A$296,0))*BD9+INDEX('Scoring Method'!$B$300:$B$305,MATCH(AO9,'Scoring Method'!$A$300:$A$305,0))*BM9*BB9+INDEX('Scoring Method'!$B$309:$B$314,MATCH(AX9,'Scoring Method'!$A$309:$A$314,0))+INDEX('Scoring Method'!$B$337:$B$341,MATCH(X9,'Scoring Method'!$A$337:$A$341,0))+INDEX('Scoring Method'!$B$324:$B$326,MATCH(P9,'Scoring Method'!$A$324:$A$326,0)),1) | BG9: Fits (~$2,529/mo) | BH9: AUC | BI9: Auto-Urban Commercial | BL9: Bar permitted | BM9: =INDEX('Scoring Method'!$B$358:$B$363,MATCH(BL9,'Scoring Method'!$A$358:$A$363,0))
A10: 9 | B10: 055-20-00-002.00 | C10: 2601 BENTON RD | D10: TIBTANI HICHAM & | E10: NO KNOWN ADDRESS | H10: CONVENIENCE STORE | I10: 18193 | J10: =I10/43560 | K10: 586 | L10: =I10/(K10^2) | M10: Ideal 18-32k | N10: C | O10: Regular .045-.055 | P10: Low | Q10: Out-of-state | R10: Individual | S10: 1 | T10: =INDEX('Scoring Method'!$B$6:$B$9,MATCH(M10,'Scoring Method'!$A$6:$A$9,0))+INDEX('Scoring Method'!$B$12:$B$16,MATCH(N10,'Scoring Method'!$A$12:$A$16,0))+INDEX('Scoring Method'!$B$19:$B$22,MATCH(O10,'Scoring Method'!$A$19:$A$22,0))+INDEX('Scoring Method'!$B$25:$B$27,MATCH(P10,'Scoring Method'!$A$25:$A$27,0)) | U10: =(INDEX('Scoring Method'!$B$30:$B$33,MATCH(Q10,'Scoring Method'!$A$30:$A$33,0))+INDEX('Scoring Method'!$B$36:$B$42,MATCH(R10,'Scoring Method'!$A$36:$A$42,0))+INDEX('Scoring Method'!$B$45:$B$47,MATCH(IF(S10=1,"1",IF(S10=2,"2","3+")),'Scoring Method'!$A$45:$A$47,0)))/90*100 | V10: =T10*U10/100 | W10: 4000 | X10: X (minimal hazard) | Y10: 11375 | Z10: =W10/I10 | AA10: =MAX(0,(Y10-5000)/300) | AC10: 0.33 | AD10: ok | AE10: Above 2.5-4k | AF10: =INDEX('Scoring Method'!$B$63:$B$71,MATCH(AE10,'Scoring Method'!$A$63:$A$71,0))+INDEX('Scoring Method'!$B$75:$B$79,MATCH("Good 8-15k",'Scoring Method'!$A$75:$A$79,0))+INDEX('Scoring Method'!$B$343:$B$347,MATCH(X10,'Scoring Method'!$A$343:$A$347,0))+INDEX('Scoring Method'!$B$25:$B$27,MATCH(P10,'Scoring Method'!$A$25:$A$27,0)) | AG10: =AF10*U10/100 | AH10: LINK-GIS + LoopNet | AI10: 39.05758 | AJ10: -84.51356 | AK10: 1.87 | AL10: 2.32 | AM10: 3.04 | AN10: 1.83 | AO10: Outer 1.25-2mi | AP10: Built-out kitchen | AQ10: Good 8-15k | AS10: =ROUND(INDEX('Scoring Method'!$B$63:$B$70,MATCH(AE10,'Scoring Method'!$A$63:$A$70,0))*0.625+INDEX('Scoring Method'!$B$105:$B$113,MATCH(AP10,'Scoring Method'!$A$105:$A$113,0))+INDEX('Scoring Method'!$B$74:$B$78,MATCH(AQ10,'Scoring Method'!$A$74:$A$78,0))*0.6667+INDEX('Scoring Method'!$B$96:$B$101,MATCH(AO10,'Scoring Method'!$A$96:$A$101,0))+INDEX('Scoring Method'!$B$343:$B$347,MATCH(X10,'Scoring Method'!$A$343:$A$347,0))*0.3333+INDEX('Scoring Method'!$B$25:$B$27,MATCH(P10,'Scoring Method'!$A$25:$A$27,0))*0.3333,1) | AT10: =AS10*U10/100 | AU10: Latonia Rosedale | AV10: 68 | AW10: Sourced | AX10: Moderate 60-69 | AY10: =ROUND(INDEX('Scoring Method'!$B$132:$B$140,MATCH(AE10,'Scoring Method'!$A$132:$A$140,0))+INDEX('Scoring Method'!$B$144:$B$152,MATCH(AP10,'Scoring Method'!$A$144:$A$152,0))+INDEX('Scoring Method'!$B$156:$B$160,MATCH(AQ10,'Scoring Method'!$A$156:$A$160,0))+INDEX('Scoring Method'!$B$164:$B$169,MATCH(AO10,'Scoring Method'!$A$164:$A$169,0))+INDEX('Scoring Method'!$B$173:$B$178,MATCH(AX10,'Scoring Method'!$A$173:$A$178,0))+INDEX('Scoring Method'!$B$349:$B$353,MATCH(X10,'Scoring Method'!$A$349:$A$353,0))+INDEX('Scoring Method'!$B$188:$B$190,MATCH(P10,'Scoring Method'!$A$188:$A$190,0)),1) | AZ10: =AY10*U10/100 | BA10: Chain format + local owner | BB10: 0.7 | BC10: Right-sized 0.35-0.75 AC | BD10: 1 | BE10: =ROUND(INDEX('Scoring Method'!$B$268:$B$276,MATCH(AE10,'Scoring Method'!$A$268:$A$276,0))+INDEX('Scoring Method'!$B$280:$B$288,MATCH(AP10,'Scoring Method'!$A$280:$A$288,0))+INDEX('Scoring Method'!$B$292:$B$296,MATCH(AQ10,'Scoring Method'!$A$292:$A$296,0))+INDEX('Scoring Method'!$B$300:$B$305,MATCH(AO10,'Scoring Method'!$A$300:$A$305,0))+INDEX('Scoring Method'!$B$309:$B$314,MATCH(AX10,'Scoring Method'!$A$309:$A$314,0))+INDEX('Scoring Method'!$B$337:$B$341,MATCH(X10,'Scoring Method'!$A$337:$A$341,0))+INDEX('Scoring Method'!$B$324:$B$326,MATCH(P10,'Scoring Method'!$A$324:$A$326,0)),1) | BF10: =ROUND(INDEX('Scoring Method'!$B$268:$B$276,MATCH(AE10,'Scoring Method'!$A$268:$A$276,0))*BB10*BD10+INDEX('Scoring Method'!$B$280:$B$288,MATCH(AP10,'Scoring Method'!$A$280:$A$288,0))*BM10*BB10*BD10+INDEX('Scoring Method'!$B$292:$B$296,MATCH(AQ10,'Scoring Method'!$A$292:$A$296,0))*BD10+INDEX('Scoring Method'!$B$300:$B$305,MATCH(AO10,'Scoring Method'!$A$300:$A$305,0))*BM10*BB10+INDEX('Scoring Method'!$B$309:$B$314,MATCH(AX10,'Scoring Method'!$A$309:$A$314,0))+INDEX('Scoring Method'!$B$337:$B$341,MATCH(X10,'Scoring Method'!$A$337:$A$341,0))+INDEX('Scoring Method'!$B$324:$B$326,MATCH(P10,'Scoring Method'!$A$324:$A$326,0)),1) | BG10: Fits (~$3,667/mo) | BH10: SU | BI10: Semi-Urban Residential | BL10: SU corner unverified | BM10: =INDEX('Scoring Method'!$B$358:$B$363,MATCH(BL10,'Scoring Method'!$A$358:$A$363,0))
A11: 10 | B11: 042-30-00-039.00 | C11: 3296 MADISON PIKE | D11: SCHLIPF DANIEL W | E11: 3197 HIGH RIDGE DR | F11: TAYLOR MILL | G11: KY | H11: AUTO SERVICE/REPAIR | I11: 23623 | J11: =I11/43560 | K11: 693.4 | L11: =I11/(K11^2) | M11: Ideal 18-32k | N11: A | O11: Regular .045-.055 | P11: Moderate | Q11: Out-of-city KY | R11: Individual | S11: 1 | T11: =INDEX('Scoring Method'!$B$6:$B$9,MATCH(M11,'Scoring Method'!$A$6:$A$9,0))+INDEX('Scoring Method'!$B$12:$B$16,MATCH(N11,'Scoring Method'!$A$12:$A$16,0))+INDEX('Scoring Method'!$B$19:$B$22,MATCH(O11,'Scoring Method'!$A$19:$A$22,0))+INDEX('Scoring Method'!$B$25:$B$27,MATCH(P11,'Scoring Method'!$A$25:$A$27,0)) | U11: =(INDEX('Scoring Method'!$B$30:$B$33,MATCH(Q11,'Scoring Method'!$A$30:$A$33,0))+INDEX('Scoring Method'!$B$36:$B$42,MATCH(R11,'Scoring Method'!$A$36:$A$42,0))+INDEX('Scoring Method'!$B$45:$B$47,MATCH(IF(S11=1,"1",IF(S11=2,"2","3+")),'Scoring Method'!$A$45:$A$47,0)))/90*100 | V11: =T11*U11/100 | W11: 4467 | X11: X shaded (0.2%) | Y11: 18825 | Z11: =W11/I11 | AA11: =MAX(0,(Y11-5000)/300) | AC11: 0.59 | AD11: ok | AE11: Large 4-6k | AF11: =INDEX('Scoring Method'!$B$63:$B$71,MATCH(AE11,'Scoring Method'!$A$63:$A$71,0))+INDEX('Scoring Method'!$B$75:$B$79,MATCH("Ample >=15k",'Scoring Method'!$A$75:$A$79,0))+INDEX('Scoring Method'!$B$343:$B$347,MATCH(X11,'Scoring Method'!$A$343:$A$347,0))+INDEX('Scoring Method'!$B$25:$B$27,MATCH(P11,'Scoring Method'!$A$25:$A$27,0)) | AG11: =AF11*U11/100 | AH11: LINK-GIS + LoopNet | AI11: 39.04224 | AJ11: -84.52584 | AK11: 2.94 | AL11: 3.49 | AM11: 4.16 | AN11: 2.94 | AO11: Distant 2-3mi | AP11: Open span | AQ11: Ample >=15k | AS11: =ROUND(INDEX('Scoring Method'!$B$63:$B$70,MATCH(AE11,'Scoring Method'!$A$63:$A$70,0))*0.625+INDEX('Scoring Method'!$B$105:$B$113,MATCH(AP11,'Scoring Method'!$A$105:$A$113,0))+INDEX('Scoring Method'!$B$74:$B$78,MATCH(AQ11,'Scoring Method'!$A$74:$A$78,0))*0.6667+INDEX('Scoring Method'!$B$96:$B$101,MATCH(AO11,'Scoring Method'!$A$96:$A$101,0))+INDEX('Scoring Method'!$B$343:$B$347,MATCH(X11,'Scoring Method'!$A$343:$A$347,0))*0.3333+INDEX('Scoring Method'!$B$25:$B$27,MATCH(P11,'Scoring Method'!$A$25:$A$27,0))*0.3333,1) | AT11: =AS11*U11/100 | AU11: Rittes East / Winston Park | AV11: 82 | AW11: Sourced | AX11: Very safe 80+ | AY11: =ROUND(INDEX('Scoring Method'!$B$132:$B$140,MATCH(AE11,'Scoring Method'!$A$132:$A$140,0))+INDEX('Scoring Method'!$B$144:$B$152,MATCH(AP11,'Scoring Method'!$A$144:$A$152,0))+INDEX('Scoring Method'!$B$156:$B$160,MATCH(AQ11,'Scoring Method'!$A$156:$A$160,0))+INDEX('Scoring Method'!$B$164:$B$169,MATCH(AO11,'Scoring Method'!$A$164:$A$169,0))+INDEX('Scoring Method'!$B$173:$B$178,MATCH(AX11,'Scoring Method'!$A$173:$A$178,0))+INDEX('Scoring Method'!$B$349:$B$353,MATCH(X11,'Scoring Method'!$A$349:$A$353,0))+INDEX('Scoring Method'!$B$188:$B$190,MATCH(P11,'Scoring Method'!$A$188:$A$190,0)),1) | AZ11: =AY11*U11/100 | BA11: No chain signal | BB11: 1 | BC11: Right-sized 0.35-0.75 AC | BD11: 1 | BE11: =ROUND(INDEX('Scoring Method'!$B$268:$B$276,MATCH(AE11,'Scoring Method'!$A$268:$A$276,0))+INDEX('Scoring Method'!$B$280:$B$288,MATCH(AP11,'Scoring Method'!$A$280:$A$288,0))+INDEX('Scoring Method'!$B$292:$B$296,MATCH(AQ11,'Scoring Method'!$A$292:$A$296,0))+INDEX('Scoring Method'!$B$300:$B$305,MATCH(AO11,'Scoring Method'!$A$300:$A$305,0))+INDEX('Scoring Method'!$B$309:$B$314,MATCH(AX11,'Scoring Method'!$A$309:$A$314,0))+INDEX('Scoring Method'!$B$337:$B$341,MATCH(X11,'Scoring Method'!$A$337:$A$341,0))+INDEX('Scoring Method'!$B$324:$B$326,MATCH(P11,'Scoring Method'!$A$324:$A$326,0)),1) | BF11: =ROUND(INDEX('Scoring Method'!$B$268:$B$276,MATCH(AE11,'Scoring Method'!$A$268:$A$276,0))*BB11*BD11+INDEX('Scoring Method'!$B$280:$B$288,MATCH(AP11,'Scoring Method'!$A$280:$A$288,0))*BM11*BB11*BD11+INDEX('Scoring Method'!$B$292:$B$296,MATCH(AQ11,'Scoring Method'!$A$292:$A$296,0))*BD11+INDEX('Scoring Method'!$B$300:$B$305,MATCH(AO11,'Scoring Method'!$A$300:$A$305,0))*BM11*BB11+INDEX('Scoring Method'!$B$309:$B$314,MATCH(AX11,'Scoring Method'!$A$309:$A$314,0))+INDEX('Scoring Method'!$B$337:$B$341,MATCH(X11,'Scoring Method'!$A$337:$A$341,0))+INDEX('Scoring Method'!$B$324:$B$326,MATCH(P11,'Scoring Method'!$A$324:$A$326,0)),1) | BG11: Fits (~$4,095/mo) | BH11: AUC | BI11: Auto-Urban Commercial | BL11: Bar permitted | BM11: =INDEX('Scoring Method'!$B$358:$B$363,MATCH(BL11,'Scoring Method'!$A$358:$A$363,0))
A12: 11 | B12: 054-22-39-009.00 | C12: 1116 RUSSELL ST | D12: SKLO ACQUISITIONS LLC | E12: PO BOX 172576 | F12: TAMPA | G12: FL | H12: GARAGE | I12: 37630 | J12: =I12/43560 | K12: 776 | L12: =I12/(K12^2) | M12: Near 14-18k/32-45k | N12: A | O12: Compact >=.055 | P12: Moderate | Q12: Out-of-state | R12: Passive vehicle | S12: 1 | T12: =INDEX('Scoring Method'!$B$6:$B$9,MATCH(M12,'Scoring Method'!$A$6:$A$9,0))+INDEX('Scoring Method'!$B$12:$B$16,MATCH(N12,'Scoring Method'!$A$12:$A$16,0))+INDEX('Scoring Method'!$B$19:$B$22,MATCH(O12,'Scoring Method'!$A$19:$A$22,0))+INDEX('Scoring Method'!$B$25:$B$27,MATCH(P12,'Scoring Method'!$A$25:$A$27,0)) | U12: =(INDEX('Scoring Method'!$B$30:$B$33,MATCH(Q12,'Scoring Method'!$A$30:$A$33,0))+INDEX('Scoring Method'!$B$36:$B$42,MATCH(R12,'Scoring Method'!$A$36:$A$42,0))+INDEX('Scoring Method'!$B$45:$B$47,MATCH(IF(S12=1,"1",IF(S12=2,"2","3+")),'Scoring Method'!$A$45:$A$47,0)))/90*100 | V12: =T12*U12/100 | W12: 21500 | X12: X (minimal hazard) | Y12: 13525 | Z12: =W12/I12 | AA12: =MAX(0,(Y12-5000)/300) | AC12: 0.86 | AD12: ok | AE12: Far oversize >12k | AF12: =INDEX('Scoring Method'!$B$63:$B$71,MATCH(AE12,'Scoring Method'!$A$63:$A$71,0))+INDEX('Scoring Method'!$B$75:$B$79,MATCH("Good 8-15k",'Scoring Method'!$A$75:$A$79,0))+INDEX('Scoring Method'!$B$343:$B$347,MATCH(X12,'Scoring Method'!$A$343:$A$347,0))+INDEX('Scoring Method'!$B$25:$B$27,MATCH(P12,'Scoring Method'!$A$25:$A$27,0)) | AG12: =AF12*U12/100 | AH12: LINK-GIS + LoopNet | AI12: 39.07773 | AJ12: -84.51152 | AK12: 0.57 | AL12: 0.92 | AM12: 1.64 | AN12: 0.43 | AO12: Near 0.35-0.75mi | AP12: Open span | AQ12: Good 8-15k | AS12: =ROUND(INDEX('Scoring Method'!$B$63:$B$70,MATCH(AE12,'Scoring Method'!$A$63:$A$70,0))*0.625+INDEX('Scoring Method'!$B$105:$B$113,MATCH(AP12,'Scoring Method'!$A$105:$A$113,0))+INDEX('Scoring Method'!$B$74:$B$78,MATCH(AQ12,'Scoring Method'!$A$74:$A$78,0))*0.6667+INDEX('Scoring Method'!$B$96:$B$101,MATCH(AO12,'Scoring Method'!$A$96:$A$101,0))+INDEX('Scoring Method'!$B$343:$B$347,MATCH(X12,'Scoring Method'!$A$343:$A$347,0))*0.3333+INDEX('Scoring Method'!$B$25:$B$27,MATCH(P12,'Scoring Method'!$A$25:$A$27,0))*0.3333,1) | AT12: =AS12*U12/100 | AU12: Old Seminary Square | AV12: 35 | AW12: ESTIMATED | AX12: Elevated 35-44 | AY12: =ROUND(INDEX('Scoring Method'!$B$132:$B$140,MATCH(AE12,'Scoring Method'!$A$132:$A$140,0))+INDEX('Scoring Method'!$B$144:$B$152,MATCH(AP12,'Scoring Method'!$A$144:$A$152,0))+INDEX('Scoring Method'!$B$156:$B$160,MATCH(AQ12,'Scoring Method'!$A$156:$A$160,0))+INDEX('Scoring Method'!$B$164:$B$169,MATCH(AO12,'Scoring Method'!$A$164:$A$169,0))+INDEX('Scoring Method'!$B$173:$B$178,MATCH(AX12,'Scoring Method'!$A$173:$A$178,0))+INDEX('Scoring Method'!$B$349:$B$353,MATCH(X12,'Scoring Method'!$A$349:$A$353,0))+INDEX('Scoring Method'!$B$188:$B$190,MATCH(P12,'Scoring Method'!$A$188:$A$190,0)),1) | AZ12: =AY12*U12/100 | BA12: No chain signal | BB12: 1 | BC12: Large 0.75-1.25 AC | BD12: 0.9 | BE12: =ROUND(INDEX('Scoring Method'!$B$268:$B$276,MATCH(AE12,'Scoring Method'!$A$268:$A$276,0))+INDEX('Scoring Method'!$B$280:$B$288,MATCH(AP12,'Scoring Method'!$A$280:$A$288,0))+INDEX('Scoring Method'!$B$292:$B$296,MATCH(AQ12,'Scoring Method'!$A$292:$A$296,0))+INDEX('Scoring Method'!$B$300:$B$305,MATCH(AO12,'Scoring Method'!$A$300:$A$305,0))+INDEX('Scoring Method'!$B$309:$B$314,MATCH(AX12,'Scoring Method'!$A$309:$A$314,0))+INDEX('Scoring Method'!$B$337:$B$341,MATCH(X12,'Scoring Method'!$A$337:$A$341,0))+INDEX('Scoring Method'!$B$324:$B$326,MATCH(P12,'Scoring Method'!$A$324:$A$326,0)),1) | BF12: =ROUND(INDEX('Scoring Method'!$B$268:$B$276,MATCH(AE12,'Scoring Method'!$A$268:$A$276,0))*BB12*BD12+INDEX('Scoring Method'!$B$280:$B$288,MATCH(AP12,'Scoring Method'!$A$280:$A$288,0))*BM12*BB12*BD12+INDEX('Scoring Method'!$B$292:$B$296,MATCH(AQ12,'Scoring Method'!$A$292:$A$296,0))*BD12+INDEX('Scoring Method'!$B$300:$B$305,MATCH(AO12,'Scoring Method'!$A$300:$A$305,0))*BM12*BB12+INDEX('Scoring Method'!$B$309:$B$314,MATCH(AX12,'Scoring Method'!$A$309:$A$314,0))+INDEX('Scoring Method'!$B$337:$B$341,MATCH(X12,'Scoring Method'!$A$337:$A$341,0))+INDEX('Scoring Method'!$B$324:$B$326,MATCH(P12,'Scoring Method'!$A$324:$A$326,0)),1) | BG12: Over (~$19,708/mo) | BH12: TUMU (TS) | BI12: Traditional Urban Mixed Use | BK12: Yes | BL12: Bar permitted | BM12: =INDEX('Scoring Method'!$B$358:$B$363,MATCH(BL12,'Scoring Method'!$A$358:$A$363,0))
A13: 12 | B13: 054-23-04-012.00 | C13: 423 SCOTT ST | D13: DECASTRO MANAGEMENT LLC | E13: 700 WALNUT ST STE 311 | F13: CINCINNATI | G13: OH | H13: AUTO SERVICE/REPAIR | I13: 36100 | J13: =I13/43560 | K13: 760 | L13: =I13/(K13^2) | M13: Near 14-18k/32-45k | N13: A | O13: Compact >=.055 | P13: Moderate | Q13: Out-of-state | R13: Passive vehicle | S13: 1 | T13: =INDEX('Scoring Method'!$B$6:$B$9,MATCH(M13,'Scoring Method'!$A$6:$A$9,0))+INDEX('Scoring Method'!$B$12:$B$16,MATCH(N13,'Scoring Method'!$A$12:$A$16,0))+INDEX('Scoring Method'!$B$19:$B$22,MATCH(O13,'Scoring Method'!$A$19:$A$22,0))+INDEX('Scoring Method'!$B$25:$B$27,MATCH(P13,'Scoring Method'!$A$25:$A$27,0)) | U13: =(INDEX('Scoring Method'!$B$30:$B$33,MATCH(Q13,'Scoring Method'!$A$30:$A$33,0))+INDEX('Scoring Method'!$B$36:$B$42,MATCH(R13,'Scoring Method'!$A$36:$A$42,0))+INDEX('Scoring Method'!$B$45:$B$47,MATCH(IF(S13=1,"1",IF(S13=2,"2","3+")),'Scoring Method'!$A$45:$A$47,0)))/90*100 | V13: =T13*U13/100 | W13: 17586 | X13: X (minimal hazard) | Y13: 17825 | Z13: =W13/I13 | AA13: =MAX(0,(Y13-5000)/300) | AC13: 0.83 | AD13: ok | AE13: Far oversize >12k | AF13: =INDEX('Scoring Method'!$B$63:$B$71,MATCH(AE13,'Scoring Method'!$A$63:$A$71,0))+INDEX('Scoring Method'!$B$75:$B$79,MATCH("Ample >=15k",'Scoring Method'!$A$75:$A$79,0))+INDEX('Scoring Method'!$B$343:$B$347,MATCH(X13,'Scoring Method'!$A$343:$A$347,0))+INDEX('Scoring Method'!$B$25:$B$27,MATCH(P13,'Scoring Method'!$A$25:$A$27,0)) | AG13: =AF13*U13/100 | AH13: LINK-GIS + LoopNet | AI13: 39.08638 | AJ13: -84.50972 | AK13: 0.46 | AL13: 0.32 | AM13: 1.05 | AN13: 0.18 | AO13: Core <=0.35mi | AP13: Open span | AQ13: Ample >=15k | AS13: =ROUND(INDEX('Scoring Method'!$B$63:$B$70,MATCH(AE13,'Scoring Method'!$A$63:$A$70,0))*0.625+INDEX('Scoring Method'!$B$105:$B$113,MATCH(AP13,'Scoring Method'!$A$105:$A$113,0))+INDEX('Scoring Method'!$B$74:$B$78,MATCH(AQ13,'Scoring Method'!$A$74:$A$78,0))*0.6667+INDEX('Scoring Method'!$B$96:$B$101,MATCH(AO13,'Scoring Method'!$A$96:$A$101,0))+INDEX('Scoring Method'!$B$343:$B$347,MATCH(X13,'Scoring Method'!$A$343:$A$347,0))*0.3333+INDEX('Scoring Method'!$B$25:$B$27,MATCH(P13,'Scoring Method'!$A$25:$A$27,0))*0.3333,1) | AT13: =AS13*U13/100 | AU13: Central Business District | AV13: 48 | AW13: ESTIMATED | AX13: Mixed 45-59 | AY13: =ROUND(INDEX('Scoring Method'!$B$132:$B$140,MATCH(AE13,'Scoring Method'!$A$132:$A$140,0))+INDEX('Scoring Method'!$B$144:$B$152,MATCH(AP13,'Scoring Method'!$A$144:$A$152,0))+INDEX('Scoring Method'!$B$156:$B$160,MATCH(AQ13,'Scoring Method'!$A$156:$A$160,0))+INDEX('Scoring Method'!$B$164:$B$169,MATCH(AO13,'Scoring Method'!$A$164:$A$169,0))+INDEX('Scoring Method'!$B$173:$B$178,MATCH(AX13,'Scoring Method'!$A$173:$A$178,0))+INDEX('Scoring Method'!$B$349:$B$353,MATCH(X13,'Scoring Method'!$A$349:$A$353,0))+INDEX('Scoring Method'!$B$188:$B$190,MATCH(P13,'Scoring Method'!$A$188:$A$190,0)),1) | AZ13: =AY13*U13/100 | BA13: No chain signal | BB13: 1 | BC13: Large 0.75-1.25 AC | BD13: 0.9 | BE13: =ROUND(INDEX('Scoring Method'!$B$268:$B$276,MATCH(AE13,'Scoring Method'!$A$268:$A$276,0))+INDEX('Scoring Method'!$B$280:$B$288,MATCH(AP13,'Scoring Method'!$A$280:$A$288,0))+INDEX('Scoring Method'!$B$292:$B$296,MATCH(AQ13,'Scoring Method'!$A$292:$A$296,0))+INDEX('Scoring Method'!$B$300:$B$305,MATCH(AO13,'Scoring Method'!$A$300:$A$305,0))+INDEX('Scoring Method'!$B$309:$B$314,MATCH(AX13,'Scoring Method'!$A$309:$A$314,0))+INDEX('Scoring Method'!$B$337:$B$341,MATCH(X13,'Scoring Method'!$A$337:$A$341,0))+INDEX('Scoring Method'!$B$324:$B$326,MATCH(P13,'Scoring Method'!$A$324:$A$326,0)),1) | BF13: =ROUND(INDEX('Scoring Method'!$B$268:$B$276,MATCH(AE13,'Scoring Method'!$A$268:$A$276,0))*BB13*BD13+INDEX('Scoring Method'!$B$280:$B$288,MATCH(AP13,'Scoring Method'!$A$280:$A$288,0))*BM13*BB13*BD13+INDEX('Scoring Method'!$B$292:$B$296,MATCH(AQ13,'Scoring Method'!$A$292:$A$296,0))*BD13+INDEX('Scoring Method'!$B$300:$B$305,MATCH(AO13,'Scoring Method'!$A$300:$A$305,0))*BM13*BB13+INDEX('Scoring Method'!$B$309:$B$314,MATCH(AX13,'Scoring Method'!$A$309:$A$314,0))+INDEX('Scoring Method'!$B$337:$B$341,MATCH(X13,'Scoring Method'!$A$337:$A$341,0))+INDEX('Scoring Method'!$B$324:$B$326,MATCH(P13,'Scoring Method'!$A$324:$A$326,0)),1) | BG13: Over (~$16,120/mo) | BH13: DTC (HP) | BI13: Downtown Core | BJ13: HP | BL13: Bar permitted | BM13: =INDEX('Scoring Method'!$B$358:$B$363,MATCH(BL13,'Scoring Method'!$A$358:$A$363,0))
A14: 13 | B14: 056-20-00-059.02 | C14: 4387 WINSTON AVE | D14: J & S LATONIA CENTRE KY LLC | E14: PO BOX 24550 | F14: COLUMBUS | G14: OH | H14: FAST FOOD-DRIVE THRU REST | I14: 26797 | J14: =I14/43560 | K14: 661 | L14: =I14/(K14^2) | M14: Ideal 18-32k | N14: C | O14: Compact >=.055 | P14: Low | Q14: Out-of-state | R14: Operating entity | S14: 4 | T14: =INDEX('Scoring Method'!$B$6:$B$9,MATCH(M14,'Scoring Method'!$A$6:$A$9,0))+INDEX('Scoring Method'!$B$12:$B$16,MATCH(N14,'Scoring Method'!$A$12:$A$16,0))+INDEX('Scoring Method'!$B$19:$B$22,MATCH(O14,'Scoring Method'!$A$19:$A$22,0))+INDEX('Scoring Method'!$B$25:$B$27,MATCH(P14,'Scoring Method'!$A$25:$A$27,0)) | U14: =(INDEX('Scoring Method'!$B$30:$B$33,MATCH(Q14,'Scoring Method'!$A$30:$A$33,0))+INDEX('Scoring Method'!$B$36:$B$42,MATCH(R14,'Scoring Method'!$A$36:$A$42,0))+INDEX('Scoring Method'!$B$45:$B$47,MATCH(IF(S14=1,"1",IF(S14=2,"2","3+")),'Scoring Method'!$A$45:$A$47,0)))/90*100 | V14: =T14*U14/100 | W14: 2768 | X14: X (minimal hazard) | Y14: 23875 | Z14: =W14/I14 | AA14: =MAX(0,(Y14-5000)/300) | AC14: 38.19 | AD14: CHECK | AE14: Above 2.5-4k | AF14: =INDEX('Scoring Method'!$B$63:$B$71,MATCH(AE14,'Scoring Method'!$A$63:$A$71,0))+INDEX('Scoring Method'!$B$75:$B$79,MATCH("Ample >=15k",'Scoring Method'!$A$75:$A$79,0))+INDEX('Scoring Method'!$B$343:$B$347,MATCH(X14,'Scoring Method'!$A$343:$A$347,0))+INDEX('Scoring Method'!$B$25:$B$27,MATCH(P14,'Scoring Method'!$A$25:$A$27,0)) | AG14: =AF14*U14/100 | AH14: LINK-GIS + LoopNet | AI14: 39.0392 | AJ14: -84.50831 | AK14: 3.16 | AL14: 3.57 | AM14: 4.31 | AN14: 3.1 | AO14: Remote >3mi | AP14: Built-out kitchen | AQ14: Ample >=15k | AS14: =ROUND(INDEX('Scoring Method'!$B$63:$B$70,MATCH(AE14,'Scoring Method'!$A$63:$A$70,0))*0.625+INDEX('Scoring Method'!$B$105:$B$113,MATCH(AP14,'Scoring Method'!$A$105:$A$113,0))+INDEX('Scoring Method'!$B$74:$B$78,MATCH(AQ14,'Scoring Method'!$A$74:$A$78,0))*0.6667+INDEX('Scoring Method'!$B$96:$B$101,MATCH(AO14,'Scoring Method'!$A$96:$A$101,0))+INDEX('Scoring Method'!$B$343:$B$347,MATCH(X14,'Scoring Method'!$A$343:$A$347,0))*0.3333+INDEX('Scoring Method'!$B$25:$B$27,MATCH(P14,'Scoring Method'!$A$25:$A$27,0))*0.3333,1) | AT14: =AS14*U14/100 | AU14: Rittes East / Winston Park | AV14: 82 | AW14: Sourced | AX14: Very safe 80+ | AY14: =ROUND(INDEX('Scoring Method'!$B$132:$B$140,MATCH(AE14,'Scoring Method'!$A$132:$A$140,0))+INDEX('Scoring Method'!$B$144:$B$152,MATCH(AP14,'Scoring Method'!$A$144:$A$152,0))+INDEX('Scoring Method'!$B$156:$B$160,MATCH(AQ14,'Scoring Method'!$A$156:$A$160,0))+INDEX('Scoring Method'!$B$164:$B$169,MATCH(AO14,'Scoring Method'!$A$164:$A$169,0))+INDEX('Scoring Method'!$B$173:$B$178,MATCH(AX14,'Scoring Method'!$A$173:$A$178,0))+INDEX('Scoring Method'!$B$349:$B$353,MATCH(X14,'Scoring Method'!$A$349:$A$353,0))+INDEX('Scoring Method'!$B$188:$B$190,MATCH(P14,'Scoring Method'!$A$188:$A$190,0)),1) | AZ14: =AY14*U14/100 | BA14: Chain format + investor | BB14: 0.45 | BC14: Right-sized 0.35-0.75 AC | BD14: 1 | BE14: =ROUND(INDEX('Scoring Method'!$B$268:$B$276,MATCH(AE14,'Scoring Method'!$A$268:$A$276,0))+INDEX('Scoring Method'!$B$280:$B$288,MATCH(AP14,'Scoring Method'!$A$280:$A$288,0))+INDEX('Scoring Method'!$B$292:$B$296,MATCH(AQ14,'Scoring Method'!$A$292:$A$296,0))+INDEX('Scoring Method'!$B$300:$B$305,MATCH(AO14,'Scoring Method'!$A$300:$A$305,0))+INDEX('Scoring Method'!$B$309:$B$314,MATCH(AX14,'Scoring Method'!$A$309:$A$314,0))+INDEX('Scoring Method'!$B$337:$B$341,MATCH(X14,'Scoring Method'!$A$337:$A$341,0))+INDEX('Scoring Method'!$B$324:$B$326,MATCH(P14,'Scoring Method'!$A$324:$A$326,0)),1) | BF14: =ROUND(INDEX('Scoring Method'!$B$268:$B$276,MATCH(AE14,'Scoring Method'!$A$268:$A$276,0))*BB14*BD14+INDEX('Scoring Method'!$B$280:$B$288,MATCH(AP14,'Scoring Method'!$A$280:$A$288,0))*BM14*BB14*BD14+INDEX('Scoring Method'!$B$292:$B$296,MATCH(AQ14,'Scoring Method'!$A$292:$A$296,0))*BD14+INDEX('Scoring Method'!$B$300:$B$305,MATCH(AO14,'Scoring Method'!$A$300:$A$305,0))*BM14*BB14+INDEX('Scoring Method'!$B$309:$B$314,MATCH(AX14,'Scoring Method'!$A$309:$A$314,0))+INDEX('Scoring Method'!$B$337:$B$341,MATCH(X14,'Scoring Method'!$A$337:$A$341,0))+INDEX('Scoring Method'!$B$324:$B$326,MATCH(P14,'Scoring Method'!$A$324:$A$326,0)),1) | BG14: Fits (~$2,537/mo) | BH14: AUC | BI14: Auto-Urban Commercial | BL14: Bar permitted | BM14: =INDEX('Scoring Method'!$B$358:$B$363,MATCH(BL14,'Scoring Method'!$A$358:$A$363,0))
A15: 14 | B15: 056-20-00-059.03 | C15: 4307 WINSTON AVE | D15: J & S LATONIA CENTRE KY LLC | E15: PO BOX 24550 | F15: COLUMBUS | G15: OH | H15: FAST FOOD-DRIVE THRU REST | I15: 23740 | J15: =I15/43560 | K15: 635 | L15: =I15/(K15^2) | M15: Ideal 18-32k | N15: C | O15: Compact >=.055 | P15: Low | Q15: Out-of-state | R15: Operating entity | S15: 4 | T15: =INDEX('Scoring Method'!$B$6:$B$9,MATCH(M15,'Scoring Method'!$A$6:$A$9,0))+INDEX('Scoring Method'!$B$12:$B$16,MATCH(N15,'Scoring Method'!$A$12:$A$16,0))+INDEX('Scoring Method'!$B$19:$B$22,MATCH(O15,'Scoring Method'!$A$19:$A$22,0))+INDEX('Scoring Method'!$B$25:$B$27,MATCH(P15,'Scoring Method'!$A$25:$A$27,0)) | U15: =(INDEX('Scoring Method'!$B$30:$B$33,MATCH(Q15,'Scoring Method'!$A$30:$A$33,0))+INDEX('Scoring Method'!$B$36:$B$42,MATCH(R15,'Scoring Method'!$A$36:$A$42,0))+INDEX('Scoring Method'!$B$45:$B$47,MATCH(IF(S15=1,"1",IF(S15=2,"2","3+")),'Scoring Method'!$A$45:$A$47,0)))/90*100 | V15: =T15*U15/100 | W15: 2160 | X15: X (minimal hazard) | Y15: 20825 | Z15: =W15/I15 | AA15: =MAX(0,(Y15-5000)/300) | AC15: 39.19 | AD15: CHECK | AE15: Target 1.5-2.5k | AF15: =INDEX('Scoring Method'!$B$63:$B$71,MATCH(AE15,'Scoring Method'!$A$63:$A$71,0))+INDEX('Scoring Method'!$B$75:$B$79,MATCH("Ample >=15k",'Scoring Method'!$A$75:$A$79,0))+INDEX('Scoring Method'!$B$343:$B$347,MATCH(X15,'Scoring Method'!$A$343:$A$347,0))+INDEX('Scoring Method'!$B$25:$B$27,MATCH(P15,'Scoring Method'!$A$25:$A$27,0)) | AG15: =AF15*U15/100 | AH15: LINK-GIS + LoopNet | AI15: 39.03863 | AJ15: -84.50864 | AK15: 3.2 | AL15: 3.61 | AM15: 4.35 | AN15: 3.14 | AO15: Remote >3mi | AP15: Built-out kitchen | AQ15: Ample >=15k | AS15: =ROUND(INDEX('Scoring Method'!$B$63:$B$70,MATCH(AE15,'Scoring Method'!$A$63:$A$70,0))*0.625+INDEX('Scoring Method'!$B$105:$B$113,MATCH(AP15,'Scoring Method'!$A$105:$A$113,0))+INDEX('Scoring Method'!$B$74:$B$78,MATCH(AQ15,'Scoring Method'!$A$74:$A$78,0))*0.6667+INDEX('Scoring Method'!$B$96:$B$101,MATCH(AO15,'Scoring Method'!$A$96:$A$101,0))+INDEX('Scoring Method'!$B$343:$B$347,MATCH(X15,'Scoring Method'!$A$343:$A$347,0))*0.3333+INDEX('Scoring Method'!$B$25:$B$27,MATCH(P15,'Scoring Method'!$A$25:$A$27,0))*0.3333,1) | AT15: =AS15*U15/100 | AU15: Rittes East / Winston Park | AV15: 82 | AW15: Sourced | AX15: Very safe 80+ | AY15: =ROUND(INDEX('Scoring Method'!$B$132:$B$140,MATCH(AE15,'Scoring Method'!$A$132:$A$140,0))+INDEX('Scoring Method'!$B$144:$B$152,MATCH(AP15,'Scoring Method'!$A$144:$A$152,0))+INDEX('Scoring Method'!$B$156:$B$160,MATCH(AQ15,'Scoring Method'!$A$156:$A$160,0))+INDEX('Scoring Method'!$B$164:$B$169,MATCH(AO15,'Scoring Method'!$A$164:$A$169,0))+INDEX('Scoring Method'!$B$173:$B$178,MATCH(AX15,'Scoring Method'!$A$173:$A$178,0))+INDEX('Scoring Method'!$B$349:$B$353,MATCH(X15,'Scoring Method'!$A$349:$A$353,0))+INDEX('Scoring Method'!$B$188:$B$190,MATCH(P15,'Scoring Method'!$A$188:$A$190,0)),1) | AZ15: =AY15*U15/100 | BA15: Chain format + investor | BB15: 0.45 | BC15: Right-sized 0.35-0.75 AC | BD15: 1 | BE15: =ROUND(INDEX('Scoring Method'!$B$268:$B$276,MATCH(AE15,'Scoring Method'!$A$268:$A$276,0))+INDEX('Scoring Method'!$B$280:$B$288,MATCH(AP15,'Scoring Method'!$A$280:$A$288,0))+INDEX('Scoring Method'!$B$292:$B$296,MATCH(AQ15,'Scoring Method'!$A$292:$A$296,0))+INDEX('Scoring Method'!$B$300:$B$305,MATCH(AO15,'Scoring Method'!$A$300:$A$305,0))+INDEX('Scoring Method'!$B$309:$B$314,MATCH(AX15,'Scoring Method'!$A$309:$A$314,0))+INDEX('Scoring Method'!$B$337:$B$341,MATCH(X15,'Scoring Method'!$A$337:$A$341,0))+INDEX('Scoring Method'!$B$324:$B$326,MATCH(P15,'Scoring Method'!$A$324:$A$326,0)),1) | BF15: =ROUND(INDEX('Scoring Method'!$B$268:$B$276,MATCH(AE15,'Scoring Method'!$A$268:$A$276,0))*BB15*BD15+INDEX('Scoring Method'!$B$280:$B$288,MATCH(AP15,'Scoring Method'!$A$280:$A$288,0))*BM15*BB15*BD15+INDEX('Scoring Method'!$B$292:$B$296,MATCH(AQ15,'Scoring Method'!$A$292:$A$296,0))*BD15+INDEX('Scoring Method'!$B$300:$B$305,MATCH(AO15,'Scoring Method'!$A$300:$A$305,0))*BM15*BB15+INDEX('Scoring Method'!$B$309:$B$314,MATCH(AX15,'Scoring Method'!$A$309:$A$314,0))+INDEX('Scoring Method'!$B$337:$B$341,MATCH(X15,'Scoring Method'!$A$337:$A$341,0))+INDEX('Scoring Method'!$B$324:$B$326,MATCH(P15,'Scoring Method'!$A$324:$A$326,0)),1) | BG15: Fits (~$1,980/mo) | BH15: AUC | BI15: Auto-Urban Commercial | BL15: Bar permitted | BM15: =INDEX('Scoring Method'!$B$358:$B$363,MATCH(BL15,'Scoring Method'!$A$358:$A$363,0))
A16: 15 | B16: 056-31-03-001.00 | C16: 609 UNION ST | D16: MW & MW PROPERTIES INC | E16: PO BOX 15609 | F16: COVINGTON | G16: KY | H16: OTHER RETAIL | I16: 31879 | J16: =I16/43560 | K16: 748.9 | L16: =I16/(K16^2) | M16: Ideal 18-32k | N16: C | O16: Compact >=.055 | P16: Low | Q16: Local absentee | R16: Passive vehicle | S16: 3 | T16: =INDEX('Scoring Method'!$B$6:$B$9,MATCH(M16,'Scoring Method'!$A$6:$A$9,0))+INDEX('Scoring Method'!$B$12:$B$16,MATCH(N16,'Scoring Method'!$A$12:$A$16,0))+INDEX('Scoring Method'!$B$19:$B$22,MATCH(O16,'Scoring Method'!$A$19:$A$22,0))+INDEX('Scoring Method'!$B$25:$B$27,MATCH(P16,'Scoring Method'!$A$25:$A$27,0)) | U16: =(INDEX('Scoring Method'!$B$30:$B$33,MATCH(Q16,'Scoring Method'!$A$30:$A$33,0))+INDEX('Scoring Method'!$B$36:$B$42,MATCH(R16,'Scoring Method'!$A$36:$A$42,0))+INDEX('Scoring Method'!$B$45:$B$47,MATCH(IF(S16=1,"1",IF(S16=2,"2","3+")),'Scoring Method'!$A$45:$A$47,0)))/90*100 | V16: =T16*U16/100 | W16: 960 | X16: X (minimal hazard) | Y16: 30425 | Z16: =W16/I16 | AA16: =MAX(0,(Y16-5000)/300) | AC16: 0.73 | AD16: ok | AE16: Too small <1.2k | AF16: =INDEX('Scoring Method'!$B$63:$B$71,MATCH(AE16,'Scoring Method'!$A$63:$A$71,0))+INDEX('Scoring Method'!$B$75:$B$79,MATCH("Ample >=15k",'Scoring Method'!$A$75:$A$79,0))+INDEX('Scoring Method'!$B$343:$B$347,MATCH(X16,'Scoring Method'!$A$343:$A$347,0))+INDEX('Scoring Method'!$B$25:$B$27,MATCH(P16,'Scoring Method'!$A$25:$A$27,0)) | AG16: =AF16*U16/100 | AH16: LINK-GIS + LoopNet | AI16: 39.05232 | AJ16: -84.50216 | AK16: 2.37 | AL16: 2.68 | AM16: 3.44 | AN16: 2.24 | AO16: Distant 2-3mi | AP16: Retail shell | AQ16: Ample >=15k | AS16: =ROUND(INDEX('Scoring Method'!$B$63:$B$70,MATCH(AE16,'Scoring Method'!$A$63:$A$70,0))*0.625+INDEX('Scoring Method'!$B$105:$B$113,MATCH(AP16,'Scoring Method'!$A$105:$A$113,0))+INDEX('Scoring Method'!$B$74:$B$78,MATCH(AQ16,'Scoring Method'!$A$74:$A$78,0))*0.6667+INDEX('Scoring Method'!$B$96:$B$101,MATCH(AO16,'Scoring Method'!$A$96:$A$101,0))+INDEX('Scoring Method'!$B$343:$B$347,MATCH(X16,'Scoring Method'!$A$343:$A$347,0))*0.3333+INDEX('Scoring Method'!$B$25:$B$27,MATCH(P16,'Scoring Method'!$A$25:$A$27,0))*0.3333,1) | AT16: =AS16*U16/100 | AU16: Latonia | AV16: 78 | AW16: Sourced | AX16: Safe 70-79 | AY16: =ROUND(INDEX('Scoring Method'!$B$132:$B$140,MATCH(AE16,'Scoring Method'!$A$132:$A$140,0))+INDEX('Scoring Method'!$B$144:$B$152,MATCH(AP16,'Scoring Method'!$A$144:$A$152,0))+INDEX('Scoring Method'!$B$156:$B$160,MATCH(AQ16,'Scoring Method'!$A$156:$A$160,0))+INDEX('Scoring Method'!$B$164:$B$169,MATCH(AO16,'Scoring Method'!$A$164:$A$169,0))+INDEX('Scoring Method'!$B$173:$B$178,MATCH(AX16,'Scoring Method'!$A$173:$A$178,0))+INDEX('Scoring Method'!$B$349:$B$353,MATCH(X16,'Scoring Method'!$A$349:$A$353,0))+INDEX('Scoring Method'!$B$188:$B$190,MATCH(P16,'Scoring Method'!$A$188:$A$190,0)),1) | AZ16: =AY16*U16/100 | BA16: No chain signal | BB16: 1 | BC16: Right-sized 0.35-0.75 AC | BD16: 1 | BE16: =ROUND(INDEX('Scoring Method'!$B$268:$B$276,MATCH(AE16,'Scoring Method'!$A$268:$A$276,0))+INDEX('Scoring Method'!$B$280:$B$288,MATCH(AP16,'Scoring Method'!$A$280:$A$288,0))+INDEX('Scoring Method'!$B$292:$B$296,MATCH(AQ16,'Scoring Method'!$A$292:$A$296,0))+INDEX('Scoring Method'!$B$300:$B$305,MATCH(AO16,'Scoring Method'!$A$300:$A$305,0))+INDEX('Scoring Method'!$B$309:$B$314,MATCH(AX16,'Scoring Method'!$A$309:$A$314,0))+INDEX('Scoring Method'!$B$337:$B$341,MATCH(X16,'Scoring Method'!$A$337:$A$341,0))+INDEX('Scoring Method'!$B$324:$B$326,MATCH(P16,'Scoring Method'!$A$324:$A$326,0)),1) | BF16: =ROUND(INDEX('Scoring Method'!$B$268:$B$276,MATCH(AE16,'Scoring Method'!$A$268:$A$276,0))*BB16*BD16+INDEX('Scoring Method'!$B$280:$B$288,MATCH(AP16,'Scoring Method'!$A$280:$A$288,0))*BM16*BB16*BD16+INDEX('Scoring Method'!$B$292:$B$296,MATCH(AQ16,'Scoring Method'!$A$292:$A$296,0))*BD16+INDEX('Scoring Method'!$B$300:$B$305,MATCH(AO16,'Scoring Method'!$A$300:$A$305,0))*BM16*BB16+INDEX('Scoring Method'!$B$309:$B$314,MATCH(AX16,'Scoring Method'!$A$309:$A$314,0))+INDEX('Scoring Method'!$B$337:$B$341,MATCH(X16,'Scoring Method'!$A$337:$A$341,0))+INDEX('Scoring Method'!$B$324:$B$326,MATCH(P16,'Scoring Method'!$A$324:$A$326,0)),1) | BG16: Fits (~$880/mo) | BH16: AUC | BI16: Auto-Urban Commercial | BL16: Bar permitted | BM16: =INDEX('Scoring Method'!$B$358:$B$363,MATCH(BL16,'Scoring Method'!$A$358:$A$363,0))
A17: 16 | B17: 054-23-12-002.00 | C17: 501 GREENUP ST | D17: PFLP LLC | E17: 7450 INDUSTRIAL RD | F17: FLORENCE | G17: KY | H17: ORGANIZATIONAL MEETING HALL | I17: 22420 | J17: =I17/43560 | K17: 616 | L17: =I17/(K17^2) | M17: Ideal 18-32k | N17: B | O17: Compact >=.055 | P17: Low | Q17: Out-of-city KY | R17: Operating entity | S17: 3 | T17: =INDEX('Scoring Method'!$B$6:$B$9,MATCH(M17,'Scoring Method'!$A$6:$A$9,0))+INDEX('Scoring Method'!$B$12:$B$16,MATCH(N17,'Scoring Method'!$A$12:$A$16,0))+INDEX('Scoring Method'!$B$19:$B$22,MATCH(O17,'Scoring Method'!$A$19:$A$22,0))+INDEX('Scoring Method'!$B$25:$B$27,MATCH(P17,'Scoring Method'!$A$25:$A$27,0)) | U17: =(INDEX('Scoring Method'!$B$30:$B$33,MATCH(Q17,'Scoring Method'!$A$30:$A$33,0))+INDEX('Scoring Method'!$B$36:$B$42,MATCH(R17,'Scoring Method'!$A$36:$A$42,0))+INDEX('Scoring Method'!$B$45:$B$47,MATCH(IF(S17=1,"1",IF(S17=2,"2","3+")),'Scoring Method'!$A$45:$A$47,0)))/90*100 | V17: =T17*U17/100 | X17: X (minimal hazard) | Y17: 6300 | AC17: 0.52 | AD17: ok | AE17: No building | AF17: =INDEX('Scoring Method'!$B$63:$B$71,MATCH(AE17,'Scoring Method'!$A$63:$A$71,0))+INDEX('Scoring Method'!$B$75:$B$79,MATCH("Adequate 5-8k",'Scoring Method'!$A$75:$A$79,0))+INDEX('Scoring Method'!$B$343:$B$347,MATCH(X17,'Scoring Method'!$A$343:$A$347,0))+INDEX('Scoring Method'!$B$25:$B$27,MATCH(P17,'Scoring Method'!$A$25:$A$27,0)) | AG17: =AF17*U17/100 | AH17: LINK-GIS + LoopNet | AI17: 39.08606 | AJ17: -84.50798 | AK17: 0.54 | AL17: 0.33 | AM17: 1.09 | AN17: 0.22 | AO17: Core <=0.35mi | AP17: Assembly hall | AQ17: Adequate 5-8k | AS17: =ROUND(INDEX('Scoring Method'!$B$63:$B$70,MATCH(AE17,'Scoring Method'!$A$63:$A$70,0))*0.625+INDEX('Scoring Method'!$B$105:$B$113,MATCH(AP17,'Scoring Method'!$A$105:$A$113,0))+INDEX('Scoring Method'!$B$74:$B$78,MATCH(AQ17,'Scoring Method'!$A$74:$A$78,0))*0.6667+INDEX('Scoring Method'!$B$96:$B$101,MATCH(AO17,'Scoring Method'!$A$96:$A$101,0))+INDEX('Scoring Method'!$B$343:$B$347,MATCH(X17,'Scoring Method'!$A$343:$A$347,0))*0.3333+INDEX('Scoring Method'!$B$25:$B$27,MATCH(P17,'Scoring Method'!$A$25:$A$27,0))*0.3333,1) | AT17: =AS17*U17/100 | AU17: Central Business District | AV17: 48 | AW17: ESTIMATED | AX17: Mixed 45-59 | AY17: =ROUND(INDEX('Scoring Method'!$B$132:$B$140,MATCH(AE17,'Scoring Method'!$A$132:$A$140,0))+INDEX('Scoring Method'!$B$144:$B$152,MATCH(AP17,'Scoring Method'!$A$144:$A$152,0))+INDEX('Scoring Method'!$B$156:$B$160,MATCH(AQ17,'Scoring Method'!$A$156:$A$160,0))+INDEX('Scoring Method'!$B$164:$B$169,MATCH(AO17,'Scoring Method'!$A$164:$A$169,0))+INDEX('Scoring Method'!$B$173:$B$178,MATCH(AX17,'Scoring Method'!$A$173:$A$178,0))+INDEX('Scoring Method'!$B$349:$B$353,MATCH(X17,'Scoring Method'!$A$349:$A$353,0))+INDEX('Scoring Method'!$B$188:$B$190,MATCH(P17,'Scoring Method'!$A$188:$A$190,0)),1) | AZ17: =AY17*U17/100 | BA17: No chain signal | BB17: 1 | BC17: Right-sized 0.35-0.75 AC | BD17: 1 | BE17: =ROUND(INDEX('Scoring Method'!$B$268:$B$276,MATCH(AE17,'Scoring Method'!$A$268:$A$276,0))+INDEX('Scoring Method'!$B$280:$B$288,MATCH(AP17,'Scoring Method'!$A$280:$A$288,0))+INDEX('Scoring Method'!$B$292:$B$296,MATCH(AQ17,'Scoring Method'!$A$292:$A$296,0))+INDEX('Scoring Method'!$B$300:$B$305,MATCH(AO17,'Scoring Method'!$A$300:$A$305,0))+INDEX('Scoring Method'!$B$309:$B$314,MATCH(AX17,'Scoring Method'!$A$309:$A$314,0))+INDEX('Scoring Method'!$B$337:$B$341,MATCH(X17,'Scoring Method'!$A$337:$A$341,0))+INDEX('Scoring Method'!$B$324:$B$326,MATCH(P17,'Scoring Method'!$A$324:$A$326,0)),1) | BF17: =ROUND(INDEX('Scoring Method'!$B$268:$B$276,MATCH(AE17,'Scoring Method'!$A$268:$A$276,0))*BB17*BD17+INDEX('Scoring Method'!$B$280:$B$288,MATCH(AP17,'Scoring Method'!$A$280:$A$288,0))*BM17*BB17*BD17+INDEX('Scoring Method'!$B$292:$B$296,MATCH(AQ17,'Scoring Method'!$A$292:$A$296,0))*BD17+INDEX('Scoring Method'!$B$300:$B$305,MATCH(AO17,'Scoring Method'!$A$300:$A$305,0))*BM17*BB17+INDEX('Scoring Method'!$B$309:$B$314,MATCH(AX17,'Scoring Method'!$A$309:$A$314,0))+INDEX('Scoring Method'!$B$337:$B$341,MATCH(X17,'Scoring Method'!$A$337:$A$341,0))+INDEX('Scoring Method'!$B$324:$B$326,MATCH(P17,'Scoring Method'!$A$324:$A$326,0)),1) | BH17: TUR (HP) | BI17: Traditional Urban Residential | BJ17: HP | BL17: Bar prohibited, alt-path | BM17: =INDEX('Scoring Method'!$B$358:$B$363,MATCH(BL17,'Scoring Method'!$A$358:$A$363,0))
A18: 17 | B18: 055-23-13-013.00 | C18: 2547 MADISON AVE | D18: WALKER AMY & JAMES | E18: 13504 MADISON PK | F18: MORNING VIEW | G18: KY | H18: DAY CARE CENTER | I18: 18634 | J18: =I18/43560 | K18: 542.9 | L18: =I18/(K18^2) | M18: Ideal 18-32k | N18: C | O18: Compact >=.055 | P18: Low | Q18: Out-of-city KY | R18: Individual | S18: 1 | T18: =INDEX('Scoring Method'!$B$6:$B$9,MATCH(M18,'Scoring Method'!$A$6:$A$9,0))+INDEX('Scoring Method'!$B$12:$B$16,MATCH(N18,'Scoring Method'!$A$12:$A$16,0))+INDEX('Scoring Method'!$B$19:$B$22,MATCH(O18,'Scoring Method'!$A$19:$A$22,0))+INDEX('Scoring Method'!$B$25:$B$27,MATCH(P18,'Scoring Method'!$A$25:$A$27,0)) | U18: =(INDEX('Scoring Method'!$B$30:$B$33,MATCH(Q18,'Scoring Method'!$A$30:$A$33,0))+INDEX('Scoring Method'!$B$36:$B$42,MATCH(R18,'Scoring Method'!$A$36:$A$42,0))+INDEX('Scoring Method'!$B$45:$B$47,MATCH(IF(S18=1,"1",IF(S18=2,"2","3+")),'Scoring Method'!$A$45:$A$47,0)))/90*100 | V18: =T18*U18/100 | W18: 3665 | X18: X (minimal hazard) | Y18: 12725 | Z18: =W18/I18 | AA18: =MAX(0,(Y18-5000)/300) | AC18: 0.44 | AD18: ok | AE18: Above 2.5-4k | AF18: =INDEX('Scoring Method'!$B$63:$B$71,MATCH(AE18,'Scoring Method'!$A$63:$A$71,0))+INDEX('Scoring Method'!$B$75:$B$79,MATCH("Good 8-15k",'Scoring Method'!$A$75:$A$79,0))+INDEX('Scoring Method'!$B$343:$B$347,MATCH(X18,'Scoring Method'!$A$343:$A$347,0))+INDEX('Scoring Method'!$B$25:$B$27,MATCH(P18,'Scoring Method'!$A$25:$A$27,0)) | AG18: =AF18*U18/100 | AH18: LINK-GIS + LoopNet | AI18: 39.05939 | AJ18: -84.50286 | AK18: 1.91 | AL18: 2.19 | AM18: 2.95 | AN18: 1.75 | AO18: Outer 1.25-2mi | AP18: Cellular | AQ18: Good 8-15k | AS18: =ROUND(INDEX('Scoring Method'!$B$63:$B$70,MATCH(AE18,'Scoring Method'!$A$63:$A$70,0))*0.625+INDEX('Scoring Method'!$B$105:$B$113,MATCH(AP18,'Scoring Method'!$A$105:$A$113,0))+INDEX('Scoring Method'!$B$74:$B$78,MATCH(AQ18,'Scoring Method'!$A$74:$A$78,0))*0.6667+INDEX('Scoring Method'!$B$96:$B$101,MATCH(AO18,'Scoring Method'!$A$96:$A$101,0))+INDEX('Scoring Method'!$B$343:$B$347,MATCH(X18,'Scoring Method'!$A$343:$A$347,0))*0.3333+INDEX('Scoring Method'!$B$25:$B$27,MATCH(P18,'Scoring Method'!$A$25:$A$27,0))*0.3333,1) | AT18: =AS18*U18/100 | AU18: Levassor Park | AV18: 42 | AW18: ESTIMATED | AX18: Elevated 35-44 | AY18: =ROUND(INDEX('Scoring Method'!$B$132:$B$140,MATCH(AE18,'Scoring Method'!$A$132:$A$140,0))+INDEX('Scoring Method'!$B$144:$B$152,MATCH(AP18,'Scoring Method'!$A$144:$A$152,0))+INDEX('Scoring Method'!$B$156:$B$160,MATCH(AQ18,'Scoring Method'!$A$156:$A$160,0))+INDEX('Scoring Method'!$B$164:$B$169,MATCH(AO18,'Scoring Method'!$A$164:$A$169,0))+INDEX('Scoring Method'!$B$173:$B$178,MATCH(AX18,'Scoring Method'!$A$173:$A$178,0))+INDEX('Scoring Method'!$B$349:$B$353,MATCH(X18,'Scoring Method'!$A$349:$A$353,0))+INDEX('Scoring Method'!$B$188:$B$190,MATCH(P18,'Scoring Method'!$A$188:$A$190,0)),1) | AZ18: =AY18*U18/100 | BA18: No chain signal | BB18: 1 | BC18: Right-sized 0.35-0.75 AC | BD18: 1 | BE18: =ROUND(INDEX('Scoring Method'!$B$268:$B$276,MATCH(AE18,'Scoring Method'!$A$268:$A$276,0))+INDEX('Scoring Method'!$B$280:$B$288,MATCH(AP18,'Scoring Method'!$A$280:$A$288,0))+INDEX('Scoring Method'!$B$292:$B$296,MATCH(AQ18,'Scoring Method'!$A$292:$A$296,0))+INDEX('Scoring Method'!$B$300:$B$305,MATCH(AO18,'Scoring Method'!$A$300:$A$305,0))+INDEX('Scoring Method'!$B$309:$B$314,MATCH(AX18,'Scoring Method'!$A$309:$A$314,0))+INDEX('Scoring Method'!$B$337:$B$341,MATCH(X18,'Scoring Method'!$A$337:$A$341,0))+INDEX('Scoring Method'!$B$324:$B$326,MATCH(P18,'Scoring Method'!$A$324:$A$326,0)),1) | BF18: =ROUND(INDEX('Scoring Method'!$B$268:$B$276,MATCH(AE18,'Scoring Method'!$A$268:$A$276,0))*BB18*BD18+INDEX('Scoring Method'!$B$280:$B$288,MATCH(AP18,'Scoring Method'!$A$280:$A$288,0))*BM18*BB18*BD18+INDEX('Scoring Method'!$B$292:$B$296,MATCH(AQ18,'Scoring Method'!$A$292:$A$296,0))*BD18+INDEX('Scoring Method'!$B$300:$B$305,MATCH(AO18,'Scoring Method'!$A$300:$A$305,0))*BM18*BB18+INDEX('Scoring Method'!$B$309:$B$314,MATCH(AX18,'Scoring Method'!$A$309:$A$314,0))+INDEX('Scoring Method'!$B$337:$B$341,MATCH(X18,'Scoring Method'!$A$337:$A$341,0))+INDEX('Scoring Method'!$B$324:$B$326,MATCH(P18,'Scoring Method'!$A$324:$A$326,0)),1) | BG18: Fits (~$3,360/mo) | BH18: AUC | BI18: Auto-Urban Commercial | BL18: Bar permitted | BM18: =INDEX('Scoring Method'!$B$358:$B$363,MATCH(BL18,'Scoring Method'!$A$358:$A$363,0))
A19: 18 | B19: 055-14-09-001.01 | C19: 1701 MADISON AVE | D19: ARDESHNA SATISHKUMAR M & | E19: 8708 MACKENZIE DR | F19: MCKINNEY | G19: TX | H19: OTHER RETAIL | I19: 14511 | J19: =I19/43560 | K19: 490.3 | L19: =I19/(K19^2) | M19: Near 14-18k/32-45k | N19: C | O19: Compact >=.055 | P19: Low | Q19: Out-of-state | R19: Individual | S19: 1 | T19: =INDEX('Scoring Method'!$B$6:$B$9,MATCH(M19,'Scoring Method'!$A$6:$A$9,0))+INDEX('Scoring Method'!$B$12:$B$16,MATCH(N19,'Scoring Method'!$A$12:$A$16,0))+INDEX('Scoring Method'!$B$19:$B$22,MATCH(O19,'Scoring Method'!$A$19:$A$22,0))+INDEX('Scoring Method'!$B$25:$B$27,MATCH(P19,'Scoring Method'!$A$25:$A$27,0)) | U19: =(INDEX('Scoring Method'!$B$30:$B$33,MATCH(Q19,'Scoring Method'!$A$30:$A$33,0))+INDEX('Scoring Method'!$B$36:$B$42,MATCH(R19,'Scoring Method'!$A$36:$A$42,0))+INDEX('Scoring Method'!$B$45:$B$47,MATCH(IF(S19=1,"1",IF(S19=2,"2","3+")),'Scoring Method'!$A$45:$A$47,0)))/90*100 | V19: =T19*U19/100 | W19: 4590 | X19: X (minimal hazard) | Y19: 8125 | Z19: =W19/I19 | AA19: =MAX(0,(Y19-5000)/300) | AC19: 0.37 | AD19: ok | AE19: Large 4-6k | AF19: =INDEX('Scoring Method'!$B$63:$B$71,MATCH(AE19,'Scoring Method'!$A$63:$A$71,0))+INDEX('Scoring Method'!$B$75:$B$79,MATCH("Good 8-15k",'Scoring Method'!$A$75:$A$79,0))+INDEX('Scoring Method'!$B$343:$B$347,MATCH(X19,'Scoring Method'!$A$343:$A$347,0))+INDEX('Scoring Method'!$B$25:$B$27,MATCH(P19,'Scoring Method'!$A$25:$A$27,0)) | AG19: =AF19*U19/100 | AH19: LINK-GIS + LoopNet | AI19: 39.07033 | AJ19: -84.50701 | AK19: 1.13 | AL19: 1.42 | AM19: 2.17 | AN19: 0.97 | AO19: Fringe 0.75-1.25mi | AP19: Retail shell | AQ19: Good 8-15k | AS19: =ROUND(INDEX('Scoring Method'!$B$63:$B$70,MATCH(AE19,'Scoring Method'!$A$63:$A$70,0))*0.625+INDEX('Scoring Method'!$B$105:$B$113,MATCH(AP19,'Scoring Method'!$A$105:$A$113,0))+INDEX('Scoring Method'!$B$74:$B$78,MATCH(AQ19,'Scoring Method'!$A$74:$A$78,0))*0.6667+INDEX('Scoring Method'!$B$96:$B$101,MATCH(AO19,'Scoring Method'!$A$96:$A$101,0))+INDEX('Scoring Method'!$B$343:$B$347,MATCH(X19,'Scoring Method'!$A$343:$A$347,0))*0.3333+INDEX('Scoring Method'!$B$25:$B$27,MATCH(P19,'Scoring Method'!$A$25:$A$27,0))*0.3333,1) | AT19: =AS19*U19/100 | AU19: Eastside | AV19: 28 | AW19: ESTIMATED | AX19: High <35 | AY19: =ROUND(INDEX('Scoring Method'!$B$132:$B$140,MATCH(AE19,'Scoring Method'!$A$132:$A$140,0))+INDEX('Scoring Method'!$B$144:$B$152,MATCH(AP19,'Scoring Method'!$A$144:$A$152,0))+INDEX('Scoring Method'!$B$156:$B$160,MATCH(AQ19,'Scoring Method'!$A$156:$A$160,0))+INDEX('Scoring Method'!$B$164:$B$169,MATCH(AO19,'Scoring Method'!$A$164:$A$169,0))+INDEX('Scoring Method'!$B$173:$B$178,MATCH(AX19,'Scoring Method'!$A$173:$A$178,0))+INDEX('Scoring Method'!$B$349:$B$353,MATCH(X19,'Scoring Method'!$A$349:$A$353,0))+INDEX('Scoring Method'!$B$188:$B$190,MATCH(P19,'Scoring Method'!$A$188:$A$190,0)),1) | AZ19: =AY19*U19/100 | BA19: No chain signal | BB19: 1 | BC19: Small 0.25-0.35 AC | BD19: 0.9 | BE19: =ROUND(INDEX('Scoring Method'!$B$268:$B$276,MATCH(AE19,'Scoring Method'!$A$268:$A$276,0))+INDEX('Scoring Method'!$B$280:$B$288,MATCH(AP19,'Scoring Method'!$A$280:$A$288,0))+INDEX('Scoring Method'!$B$292:$B$296,MATCH(AQ19,'Scoring Method'!$A$292:$A$296,0))+INDEX('Scoring Method'!$B$300:$B$305,MATCH(AO19,'Scoring Method'!$A$300:$A$305,0))+INDEX('Scoring Method'!$B$309:$B$314,MATCH(AX19,'Scoring Method'!$A$309:$A$314,0))+INDEX('Scoring Method'!$B$337:$B$341,MATCH(X19,'Scoring Method'!$A$337:$A$341,0))+INDEX('Scoring Method'!$B$324:$B$326,MATCH(P19,'Scoring Method'!$A$324:$A$326,0)),1) | BF19: =ROUND(INDEX('Scoring Method'!$B$268:$B$276,MATCH(AE19,'Scoring Method'!$A$268:$A$276,0))*BB19*BD19+INDEX('Scoring Method'!$B$280:$B$288,MATCH(AP19,'Scoring Method'!$A$280:$A$288,0))*BM19*BB19*BD19+INDEX('Scoring Method'!$B$292:$B$296,MATCH(AQ19,'Scoring Method'!$A$292:$A$296,0))*BD19+INDEX('Scoring Method'!$B$300:$B$305,MATCH(AO19,'Scoring Method'!$A$300:$A$305,0))*BM19*BB19+INDEX('Scoring Method'!$B$309:$B$314,MATCH(AX19,'Scoring Method'!$A$309:$A$314,0))+INDEX('Scoring Method'!$B$337:$B$341,MATCH(X19,'Scoring Method'!$A$337:$A$341,0))+INDEX('Scoring Method'!$B$324:$B$326,MATCH(P19,'Scoring Method'!$A$324:$A$326,0)),1) | BG19: Fits (~$4,208/mo) | BH19: AUC | BI19: Auto-Urban Commercial | BL19: Bar permitted | BM19: =INDEX('Scoring Method'!$B$358:$B$363,MATCH(BL19,'Scoring Method'!$A$358:$A$363,0))
A20: 19 | B20: 055-14-15-026.00 | C20: 1722 MADISON AVE | D20: SHELL MGM COVINGTON LLC | E20: 2582 GRANDIN RD | F20: CINCINNATI | G20: OH | H20: OTHER RETAIL | I20: 24820 | J20: =I20/43560 | K20: 648.3 | L20: =I20/(K20^2) | M20: Ideal 18-32k | N20: C | O20: Compact >=.055 | P20: Low | Q20: Out-of-state | R20: Operating entity | S20: 2 | T20: =INDEX('Scoring Method'!$B$6:$B$9,MATCH(M20,'Scoring Method'!$A$6:$A$9,0))+INDEX('Scoring Method'!$B$12:$B$16,MATCH(N20,'Scoring Method'!$A$12:$A$16,0))+INDEX('Scoring Method'!$B$19:$B$22,MATCH(O20,'Scoring Method'!$A$19:$A$22,0))+INDEX('Scoring Method'!$B$25:$B$27,MATCH(P20,'Scoring Method'!$A$25:$A$27,0)) | U20: =(INDEX('Scoring Method'!$B$30:$B$33,MATCH(Q20,'Scoring Method'!$A$30:$A$33,0))+INDEX('Scoring Method'!$B$36:$B$42,MATCH(R20,'Scoring Method'!$A$36:$A$42,0))+INDEX('Scoring Method'!$B$45:$B$47,MATCH(IF(S20=1,"1",IF(S20=2,"2","3+")),'Scoring Method'!$A$45:$A$47,0)))/90*100 | V20: =T20*U20/100 | W20: 15000 | X20: X (minimal hazard) | Y20: 8875 | Z20: =W20/I20 | AA20: =MAX(0,(Y20-5000)/300) | AC20: 0.57 | AD20: ok | AE20: Far oversize >12k | AF20: =INDEX('Scoring Method'!$B$63:$B$71,MATCH(AE20,'Scoring Method'!$A$63:$A$71,0))+INDEX('Scoring Method'!$B$75:$B$79,MATCH("Good 8-15k",'Scoring Method'!$A$75:$A$79,0))+INDEX('Scoring Method'!$B$343:$B$347,MATCH(X20,'Scoring Method'!$A$343:$A$347,0))+INDEX('Scoring Method'!$B$25:$B$27,MATCH(P20,'Scoring Method'!$A$25:$A$27,0)) | AG20: =AF20*U20/100 | AH20: LINK-GIS + LoopNet | AI20: 39.06995 | AJ20: -84.50623 | AK20: 1.18 | AL20: 1.45 | AM20: 2.2 | AN20: 1 | AO20: Fringe 0.75-1.25mi | AP20: Retail shell | AQ20: Good 8-15k | AS20: =ROUND(INDEX('Scoring Method'!$B$63:$B$70,MATCH(AE20,'Scoring Method'!$A$63:$A$70,0))*0.625+INDEX('Scoring Method'!$B$105:$B$113,MATCH(AP20,'Scoring Method'!$A$105:$A$113,0))+INDEX('Scoring Method'!$B$74:$B$78,MATCH(AQ20,'Scoring Method'!$A$74:$A$78,0))*0.6667+INDEX('Scoring Method'!$B$96:$B$101,MATCH(AO20,'Scoring Method'!$A$96:$A$101,0))+INDEX('Scoring Method'!$B$343:$B$347,MATCH(X20,'Scoring Method'!$A$343:$A$347,0))*0.3333+INDEX('Scoring Method'!$B$25:$B$27,MATCH(P20,'Scoring Method'!$A$25:$A$27,0))*0.3333,1) | AT20: =AS20*U20/100 | AU20: Levassor Park | AV20: 42 | AW20: ESTIMATED | AX20: Elevated 35-44 | AY20: =ROUND(INDEX('Scoring Method'!$B$132:$B$140,MATCH(AE20,'Scoring Method'!$A$132:$A$140,0))+INDEX('Scoring Method'!$B$144:$B$152,MATCH(AP20,'Scoring Method'!$A$144:$A$152,0))+INDEX('Scoring Method'!$B$156:$B$160,MATCH(AQ20,'Scoring Method'!$A$156:$A$160,0))+INDEX('Scoring Method'!$B$164:$B$169,MATCH(AO20,'Scoring Method'!$A$164:$A$169,0))+INDEX('Scoring Method'!$B$173:$B$178,MATCH(AX20,'Scoring Method'!$A$173:$A$178,0))+INDEX('Scoring Method'!$B$349:$B$353,MATCH(X20,'Scoring Method'!$A$349:$A$353,0))+INDEX('Scoring Method'!$B$188:$B$190,MATCH(P20,'Scoring Method'!$A$188:$A$190,0)),1) | AZ20: =AY20*U20/100 | BA20: No chain signal | BB20: 1 | BC20: Right-sized 0.35-0.75 AC | BD20: 1 | BE20: =ROUND(INDEX('Scoring Method'!$B$268:$B$276,MATCH(AE20,'Scoring Method'!$A$268:$A$276,0))+INDEX('Scoring Method'!$B$280:$B$288,MATCH(AP20,'Scoring Method'!$A$280:$A$288,0))+INDEX('Scoring Method'!$B$292:$B$296,MATCH(AQ20,'Scoring Method'!$A$292:$A$296,0))+INDEX('Scoring Method'!$B$300:$B$305,MATCH(AO20,'Scoring Method'!$A$300:$A$305,0))+INDEX('Scoring Method'!$B$309:$B$314,MATCH(AX20,'Scoring Method'!$A$309:$A$314,0))+INDEX('Scoring Method'!$B$337:$B$341,MATCH(X20,'Scoring Method'!$A$337:$A$341,0))+INDEX('Scoring Method'!$B$324:$B$326,MATCH(P20,'Scoring Method'!$A$324:$A$326,0)),1) | BF20: =ROUND(INDEX('Scoring Method'!$B$268:$B$276,MATCH(AE20,'Scoring Method'!$A$268:$A$276,0))*BB20*BD20+INDEX('Scoring Method'!$B$280:$B$288,MATCH(AP20,'Scoring Method'!$A$280:$A$288,0))*BM20*BB20*BD20+INDEX('Scoring Method'!$B$292:$B$296,MATCH(AQ20,'Scoring Method'!$A$292:$A$296,0))*BD20+INDEX('Scoring Method'!$B$300:$B$305,MATCH(AO20,'Scoring Method'!$A$300:$A$305,0))*BM20*BB20+INDEX('Scoring Method'!$B$309:$B$314,MATCH(AX20,'Scoring Method'!$A$309:$A$314,0))+INDEX('Scoring Method'!$B$337:$B$341,MATCH(X20,'Scoring Method'!$A$337:$A$341,0))+INDEX('Scoring Method'!$B$324:$B$326,MATCH(P20,'Scoring Method'!$A$324:$A$326,0)),1) | BG20: Over (~$13,750/mo) | BH20: SU | BI20: Semi-Urban Residential | BL20: SU corner unverified | BM20: =INDEX('Scoring Method'!$B$358:$B$363,MATCH(BL20,'Scoring Method'!$A$358:$A$363,0))
A21: 20 | B21: 056-13-18-001.00 | C21: 3503 DECOURSEY AVE | D21: FIRST FEDERAL SVGS & LOAN ASSN | E21: PO BOX 182390 | F21: COLUMBUS | G21: OH | H21: FULL SERVICE BANK | I21: 26433 | J21: =I21/43560 | K21: 686 | L21: =I21/(K21^2) | M21: Ideal 18-32k | N21: E | O21: Compact >=.055 | P21: Low | Q21: Out-of-state | R21: Individual | S21: 1 | T21: =INDEX('Scoring Method'!$B$6:$B$9,MATCH(M21,'Scoring Method'!$A$6:$A$9,0))+INDEX('Scoring Method'!$B$12:$B$16,MATCH(N21,'Scoring Method'!$A$12:$A$16,0))+INDEX('Scoring Method'!$B$19:$B$22,MATCH(O21,'Scoring Method'!$A$19:$A$22,0))+INDEX('Scoring Method'!$B$25:$B$27,MATCH(P21,'Scoring Method'!$A$25:$A$27,0)) | U21: =(INDEX('Scoring Method'!$B$30:$B$33,MATCH(Q21,'Scoring Method'!$A$30:$A$33,0))+INDEX('Scoring Method'!$B$36:$B$42,MATCH(R21,'Scoring Method'!$A$36:$A$42,0))+INDEX('Scoring Method'!$B$45:$B$47,MATCH(IF(S21=1,"1",IF(S21=2,"2","3+")),'Scoring Method'!$A$45:$A$47,0)))/90*100 | V21: =T21*U21/100 | W21: 4358 | X21: X (minimal hazard) | Y21: 21250 | AA21: =MAX(0,(Y21-5000)/300) | AE21: Large 4-6k | AF21: =INDEX('Scoring Method'!$B$63:$B$71,MATCH(AE21,'Scoring Method'!$A$63:$A$71,0))+INDEX('Scoring Method'!$B$75:$B$79,MATCH("Ample >=15k",'Scoring Method'!$A$75:$A$79,0))+INDEX('Scoring Method'!$B$343:$B$347,MATCH(X21,'Scoring Method'!$A$343:$A$347,0))+INDEX('Scoring Method'!$B$25:$B$27,MATCH(P21,'Scoring Method'!$A$25:$A$27,0)) | AG21: =AF21*U21/100 | AH21: LINK-GIS only | AI21: 39.04912 | AJ21: -84.50354 | AK21: 2.56 | AL21: 2.89 | AM21: 3.65 | AN21: 2.44 | AO21: Distant 2-3mi | AP21: Office/institutional | AQ21: Ample >=15k | AS21: =ROUND(INDEX('Scoring Method'!$B$63:$B$70,MATCH(AE21,'Scoring Method'!$A$63:$A$70,0))*0.625+INDEX('Scoring Method'!$B$105:$B$113,MATCH(AP21,'Scoring Method'!$A$105:$A$113,0))+INDEX('Scoring Method'!$B$74:$B$78,MATCH(AQ21,'Scoring Method'!$A$74:$A$78,0))*0.6667+INDEX('Scoring Method'!$B$96:$B$101,MATCH(AO21,'Scoring Method'!$A$96:$A$101,0))+INDEX('Scoring Method'!$B$343:$B$347,MATCH(X21,'Scoring Method'!$A$343:$A$347,0))*0.3333+INDEX('Scoring Method'!$B$25:$B$27,MATCH(P21,'Scoring Method'!$A$25:$A$27,0))*0.3333,1) | AT21: =AS21*U21/100 | AU21: Latonia | AV21: 78 | AW21: Sourced | AX21: Safe 70-79 | AY21: =ROUND(INDEX('Scoring Method'!$B$132:$B$140,MATCH(AE21,'Scoring Method'!$A$132:$A$140,0))+INDEX('Scoring Method'!$B$144:$B$152,MATCH(AP21,'Scoring Method'!$A$144:$A$152,0))+INDEX('Scoring Method'!$B$156:$B$160,MATCH(AQ21,'Scoring Method'!$A$156:$A$160,0))+INDEX('Scoring Method'!$B$164:$B$169,MATCH(AO21,'Scoring Method'!$A$164:$A$169,0))+INDEX('Scoring Method'!$B$173:$B$178,MATCH(AX21,'Scoring Method'!$A$173:$A$178,0))+INDEX('Scoring Method'!$B$349:$B$353,MATCH(X21,'Scoring Method'!$A$349:$A$353,0))+INDEX('Scoring Method'!$B$188:$B$190,MATCH(P21,'Scoring Method'!$A$188:$A$190,0)),1) | AZ21: =AY21*U21/100 | BA21: Brand-owned / net lease | BB21: 0.3 | BC21: Right-sized 0.35-0.75 AC | BD21: 1 | BE21: =ROUND(INDEX('Scoring Method'!$B$268:$B$276,MATCH(AE21,'Scoring Method'!$A$268:$A$276,0))+INDEX('Scoring Method'!$B$280:$B$288,MATCH(AP21,'Scoring Method'!$A$280:$A$288,0))+INDEX('Scoring Method'!$B$292:$B$296,MATCH(AQ21,'Scoring Method'!$A$292:$A$296,0))+INDEX('Scoring Method'!$B$300:$B$305,MATCH(AO21,'Scoring Method'!$A$300:$A$305,0))+INDEX('Scoring Method'!$B$309:$B$314,MATCH(AX21,'Scoring Method'!$A$309:$A$314,0))+INDEX('Scoring Method'!$B$337:$B$341,MATCH(X21,'Scoring Method'!$A$337:$A$341,0))+INDEX('Scoring Method'!$B$324:$B$326,MATCH(P21,'Scoring Method'!$A$324:$A$326,0)),1) | BF21: =ROUND(INDEX('Scoring Method'!$B$268:$B$276,MATCH(AE21,'Scoring Method'!$A$268:$A$276,0))*BB21*BD21+INDEX('Scoring Method'!$B$280:$B$288,MATCH(AP21,'Scoring Method'!$A$280:$A$288,0))*BM21*BB21*BD21+INDEX('Scoring Method'!$B$292:$B$296,MATCH(AQ21,'Scoring Method'!$A$292:$A$296,0))*BD21+INDEX('Scoring Method'!$B$300:$B$305,MATCH(AO21,'Scoring Method'!$A$300:$A$305,0))*BM21*BB21+INDEX('Scoring Method'!$B$309:$B$314,MATCH(AX21,'Scoring Method'!$A$309:$A$314,0))+INDEX('Scoring Method'!$B$337:$B$341,MATCH(X21,'Scoring Method'!$A$337:$A$341,0))+INDEX('Scoring Method'!$B$324:$B$326,MATCH(P21,'Scoring Method'!$A$324:$A$326,0)),1) | BG21: Fits (~$3,995/mo) | BH21: TUMU | BI21: Traditional Urban Mixed Use | BL21: Bar permitted | BM21: =INDEX('Scoring Method'!$B$358:$B$363,MATCH(BL21,'Scoring Method'!$A$358:$A$363,0))
A22: 21 | B22: 040-34-06-001.03 | C22: 504 W 4TH ST | D22: FAR DEVELOPMENT LLC | E22: 1074 BAYSWATER DR | F22: UNION | G22: KY | H22: FAST FOOD-DRIVE THRU REST | I22: 19989 | J22: =I22/43560 | K22: 573 | L22: =I22/(K22^2) | M22: Ideal 18-32k | N22: C | O22: Compact >=.055 | P22: Low | Q22: Out-of-city KY | R22: Passive vehicle | S22: 1 | T22: =INDEX('Scoring Method'!$B$6:$B$9,MATCH(M22,'Scoring Method'!$A$6:$A$9,0))+INDEX('Scoring Method'!$B$12:$B$16,MATCH(N22,'Scoring Method'!$A$12:$A$16,0))+INDEX('Scoring Method'!$B$19:$B$22,MATCH(O22,'Scoring Method'!$A$19:$A$22,0))+INDEX('Scoring Method'!$B$25:$B$27,MATCH(P22,'Scoring Method'!$A$25:$A$27,0)) | U22: =(INDEX('Scoring Method'!$B$30:$B$33,MATCH(Q22,'Scoring Method'!$A$30:$A$33,0))+INDEX('Scoring Method'!$B$36:$B$42,MATCH(R22,'Scoring Method'!$A$36:$A$42,0))+INDEX('Scoring Method'!$B$45:$B$47,MATCH(IF(S22=1,"1",IF(S22=2,"2","3+")),'Scoring Method'!$A$45:$A$47,0)))/90*100 | V22: =T22*U22/100 | W22: 2275 | X22: X (minimal hazard) | Y22: 16625 | Z22: =W22/I22 | AA22: =MAX(0,(Y22-5000)/300) | AC22: 0.46 | AD22: ok | AE22: Target 1.5-2.5k | AF22: =INDEX('Scoring Method'!$B$63:$B$71,MATCH(AE22,'Scoring Method'!$A$63:$A$71,0))+INDEX('Scoring Method'!$B$75:$B$79,MATCH("Ample >=15k",'Scoring Method'!$A$75:$A$79,0))+INDEX('Scoring Method'!$B$343:$B$347,MATCH(X22,'Scoring Method'!$A$343:$A$347,0))+INDEX('Scoring Method'!$B$25:$B$27,MATCH(P22,'Scoring Method'!$A$25:$A$27,0)) | AG22: =AF22*U22/100 | AH22: LINK-GIS + LoopNet | AI22: 39.08678 | AJ22: -84.51911 | AK22: 0.18 | AL22: 0.64 | AM22: 1.08 | AN22: 0.18 | AO22: Core <=0.35mi | AP22: Built-out kitchen | AQ22: Ample >=15k | AS22: =ROUND(INDEX('Scoring Method'!$B$63:$B$70,MATCH(AE22,'Scoring Method'!$A$63:$A$70,0))*0.625+INDEX('Scoring Method'!$B$105:$B$113,MATCH(AP22,'Scoring Method'!$A$105:$A$113,0))+INDEX('Scoring Method'!$B$74:$B$78,MATCH(AQ22,'Scoring Method'!$A$74:$A$78,0))*0.6667+INDEX('Scoring Method'!$B$96:$B$101,MATCH(AO22,'Scoring Method'!$A$96:$A$101,0))+INDEX('Scoring Method'!$B$343:$B$347,MATCH(X22,'Scoring Method'!$A$343:$A$347,0))*0.3333+INDEX('Scoring Method'!$B$25:$B$27,MATCH(P22,'Scoring Method'!$A$25:$A$27,0))*0.3333,1) | AT22: =AS22*U22/100 | AU22: Botany Hills / Riverfront West | AV22: 45 | AW22: ESTIMATED | AX22: Mixed 45-59 | AY22: =ROUND(INDEX('Scoring Method'!$B$132:$B$140,MATCH(AE22,'Scoring Method'!$A$132:$A$140,0))+INDEX('Scoring Method'!$B$144:$B$152,MATCH(AP22,'Scoring Method'!$A$144:$A$152,0))+INDEX('Scoring Method'!$B$156:$B$160,MATCH(AQ22,'Scoring Method'!$A$156:$A$160,0))+INDEX('Scoring Method'!$B$164:$B$169,MATCH(AO22,'Scoring Method'!$A$164:$A$169,0))+INDEX('Scoring Method'!$B$173:$B$178,MATCH(AX22,'Scoring Method'!$A$173:$A$178,0))+INDEX('Scoring Method'!$B$349:$B$353,MATCH(X22,'Scoring Method'!$A$349:$A$353,0))+INDEX('Scoring Method'!$B$188:$B$190,MATCH(P22,'Scoring Method'!$A$188:$A$190,0)),1) | AZ22: =AY22*U22/100 | BA22: Chain format + investor | BB22: 0.45 | BC22: Right-sized 0.35-0.75 AC | BD22: 1 | BE22: =ROUND(INDEX('Scoring Method'!$B$268:$B$276,MATCH(AE22,'Scoring Method'!$A$268:$A$276,0))+INDEX('Scoring Method'!$B$280:$B$288,MATCH(AP22,'Scoring Method'!$A$280:$A$288,0))+INDEX('Scoring Method'!$B$292:$B$296,MATCH(AQ22,'Scoring Method'!$A$292:$A$296,0))+INDEX('Scoring Method'!$B$300:$B$305,MATCH(AO22,'Scoring Method'!$A$300:$A$305,0))+INDEX('Scoring Method'!$B$309:$B$314,MATCH(AX22,'Scoring Method'!$A$309:$A$314,0))+INDEX('Scoring Method'!$B$337:$B$341,MATCH(X22,'Scoring Method'!$A$337:$A$341,0))+INDEX('Scoring Method'!$B$324:$B$326,MATCH(P22,'Scoring Method'!$A$324:$A$326,0)),1) | BF22: =ROUND(INDEX('Scoring Method'!$B$268:$B$276,MATCH(AE22,'Scoring Method'!$A$268:$A$276,0))*BB22*BD22+INDEX('Scoring Method'!$B$280:$B$288,MATCH(AP22,'Scoring Method'!$A$280:$A$288,0))*BM22*BB22*BD22+INDEX('Scoring Method'!$B$292:$B$296,MATCH(AQ22,'Scoring Method'!$A$292:$A$296,0))*BD22+INDEX('Scoring Method'!$B$300:$B$305,MATCH(AO22,'Scoring Method'!$A$300:$A$305,0))*BM22*BB22+INDEX('Scoring Method'!$B$309:$B$314,MATCH(AX22,'Scoring Method'!$A$309:$A$314,0))+INDEX('Scoring Method'!$B$337:$B$341,MATCH(X22,'Scoring Method'!$A$337:$A$341,0))+INDEX('Scoring Method'!$B$324:$B$326,MATCH(P22,'Scoring Method'!$A$324:$A$326,0)),1) | BG22: Fits (~$2,085/mo) | BH22: AUC | BI22: Auto-Urban Commercial | BL22: Bar permitted | BM22: =INDEX('Scoring Method'!$B$358:$B$363,MATCH(BL22,'Scoring Method'!$A$358:$A$363,0))
A23: 22 | B23: 054-22-18-029.00 | C23: 320 W MARTIN LUTHER KING JR BLVD REAR | D23: BROWN JAMES A | E23: 7774 SPICEWOOD | F23: CINCINNATI | G23: OH | H23: SMALL SHOP | I23: 8795 | J23: =I23/43560 | K23: 375.6 | L23: =I23/(K23^2) | M23: Poor <10k/>60k | N23: A | O23: Compact >=.055 | P23: Low | Q23: Out-of-state | R23: Individual | S23: 1 | T23: =INDEX('Scoring Method'!$B$6:$B$9,MATCH(M23,'Scoring Method'!$A$6:$A$9,0))+INDEX('Scoring Method'!$B$12:$B$16,MATCH(N23,'Scoring Method'!$A$12:$A$16,0))+INDEX('Scoring Method'!$B$19:$B$22,MATCH(O23,'Scoring Method'!$A$19:$A$22,0))+INDEX('Scoring Method'!$B$25:$B$27,MATCH(P23,'Scoring Method'!$A$25:$A$27,0)) | U23: =(INDEX('Scoring Method'!$B$30:$B$33,MATCH(Q23,'Scoring Method'!$A$30:$A$33,0))+INDEX('Scoring Method'!$B$36:$B$42,MATCH(R23,'Scoring Method'!$A$36:$A$42,0))+INDEX('Scoring Method'!$B$45:$B$47,MATCH(IF(S23=1,"1",IF(S23=2,"2","3+")),'Scoring Method'!$A$45:$A$47,0)))/90*100 | V23: =T23*U23/100 | X23: X (minimal hazard) | Y23: 5075 | AC23: 0.2 | AD23: ok | AE23: No building | AF23: =INDEX('Scoring Method'!$B$63:$B$71,MATCH(AE23,'Scoring Method'!$A$63:$A$71,0))+INDEX('Scoring Method'!$B$75:$B$79,MATCH("Adequate 5-8k",'Scoring Method'!$A$75:$A$79,0))+INDEX('Scoring Method'!$B$343:$B$347,MATCH(X23,'Scoring Method'!$A$343:$A$347,0))+INDEX('Scoring Method'!$B$25:$B$27,MATCH(P23,'Scoring Method'!$A$25:$A$27,0)) | AG23: =AF23*U23/100 | AH23: LINK-GIS + LoopNet | AI23: 39.07714 | AJ23: -84.51472 | AK23: 0.53 | AL23: 1.01 | AM23: 1.69 | AN23: 0.51 | AO23: Near 0.35-0.75mi | AP23: Open span | AQ23: Adequate 5-8k | AS23: =ROUND(INDEX('Scoring Method'!$B$63:$B$70,MATCH(AE23,'Scoring Method'!$A$63:$A$70,0))*0.625+INDEX('Scoring Method'!$B$105:$B$113,MATCH(AP23,'Scoring Method'!$A$105:$A$113,0))+INDEX('Scoring Method'!$B$74:$B$78,MATCH(AQ23,'Scoring Method'!$A$74:$A$78,0))*0.6667+INDEX('Scoring Method'!$B$96:$B$101,MATCH(AO23,'Scoring Method'!$A$96:$A$101,0))+INDEX('Scoring Method'!$B$343:$B$347,MATCH(X23,'Scoring Method'!$A$343:$A$347,0))*0.3333+INDEX('Scoring Method'!$B$25:$B$27,MATCH(P23,'Scoring Method'!$A$25:$A$27,0))*0.3333,1) | AT23: =AS23*U23/100 | AU23: Old Seminary Square | AV23: 35 | AW23: ESTIMATED | AX23: Elevated 35-44 | AY23: =ROUND(INDEX('Scoring Method'!$B$132:$B$140,MATCH(AE23,'Scoring Method'!$A$132:$A$140,0))+INDEX('Scoring Method'!$B$144:$B$152,MATCH(AP23,'Scoring Method'!$A$144:$A$152,0))+INDEX('Scoring Method'!$B$156:$B$160,MATCH(AQ23,'Scoring Method'!$A$156:$A$160,0))+INDEX('Scoring Method'!$B$164:$B$169,MATCH(AO23,'Scoring Method'!$A$164:$A$169,0))+INDEX('Scoring Method'!$B$173:$B$178,MATCH(AX23,'Scoring Method'!$A$173:$A$178,0))+INDEX('Scoring Method'!$B$349:$B$353,MATCH(X23,'Scoring Method'!$A$349:$A$353,0))+INDEX('Scoring Method'!$B$188:$B$190,MATCH(P23,'Scoring Method'!$A$188:$A$190,0)),1) | AZ23: =AY23*U23/100 | BA23: No chain signal | BB23: 1 | BC23: Extra small 0.15-0.25 AC | BD23: 0.8 | BE23: =ROUND(INDEX('Scoring Method'!$B$268:$B$276,MATCH(AE23,'Scoring Method'!$A$268:$A$276,0))+INDEX('Scoring Method'!$B$280:$B$288,MATCH(AP23,'Scoring Method'!$A$280:$A$288,0))+INDEX('Scoring Method'!$B$292:$B$296,MATCH(AQ23,'Scoring Method'!$A$292:$A$296,0))+INDEX('Scoring Method'!$B$300:$B$305,MATCH(AO23,'Scoring Method'!$A$300:$A$305,0))+INDEX('Scoring Method'!$B$309:$B$314,MATCH(AX23,'Scoring Method'!$A$309:$A$314,0))+INDEX('Scoring Method'!$B$337:$B$341,MATCH(X23,'Scoring Method'!$A$337:$A$341,0))+INDEX('Scoring Method'!$B$324:$B$326,MATCH(P23,'Scoring Method'!$A$324:$A$326,0)),1) | BF23: =ROUND(INDEX('Scoring Method'!$B$268:$B$276,MATCH(AE23,'Scoring Method'!$A$268:$A$276,0))*BB23*BD23+INDEX('Scoring Method'!$B$280:$B$288,MATCH(AP23,'Scoring Method'!$A$280:$A$288,0))*BM23*BB23*BD23+INDEX('Scoring Method'!$B$292:$B$296,MATCH(AQ23,'Scoring Method'!$A$292:$A$296,0))*BD23+INDEX('Scoring Method'!$B$300:$B$305,MATCH(AO23,'Scoring Method'!$A$300:$A$305,0))*BM23*BB23+INDEX('Scoring Method'!$B$309:$B$314,MATCH(AX23,'Scoring Method'!$A$309:$A$314,0))+INDEX('Scoring Method'!$B$337:$B$341,MATCH(X23,'Scoring Method'!$A$337:$A$341,0))+INDEX('Scoring Method'!$B$324:$B$326,MATCH(P23,'Scoring Method'!$A$324:$A$326,0)),1) | BH23: TUR (TS) | BI23: Traditional Urban Residential | BK23: Yes | BL23: Bar prohibited, alt-path | BM23: =INDEX('Scoring Method'!$B$358:$B$363,MATCH(BL23,'Scoring Method'!$A$358:$A$363,0))
A24: 23 | B24: 055-13-06-001.00 | C24: 1601 MADISON AVE | D24: TAPPAN PROPERTIES LTD PTN INC | E24: 1150 W 8TH ST STE 255 | F24: CINCINNATI | G24: OH | H24: NEIGHBORHOOD SHOPPING CENTER | I24: 41545 | J24: =I24/43560 | K24: 824 | L24: =I24/(K24^2) | M24: Near 14-18k/32-45k | N24: C | O24: Compact >=.055 | P24: Low | Q24: Out-of-state | R24: Passive vehicle | S24: 1 | T24: =INDEX('Scoring Method'!$B$6:$B$9,MATCH(M24,'Scoring Method'!$A$6:$A$9,0))+INDEX('Scoring Method'!$B$12:$B$16,MATCH(N24,'Scoring Method'!$A$12:$A$16,0))+INDEX('Scoring Method'!$B$19:$B$22,MATCH(O24,'Scoring Method'!$A$19:$A$22,0))+INDEX('Scoring Method'!$B$25:$B$27,MATCH(P24,'Scoring Method'!$A$25:$A$27,0)) | U24: =(INDEX('Scoring Method'!$B$30:$B$33,MATCH(Q24,'Scoring Method'!$A$30:$A$33,0))+INDEX('Scoring Method'!$B$36:$B$42,MATCH(R24,'Scoring Method'!$A$36:$A$42,0))+INDEX('Scoring Method'!$B$45:$B$47,MATCH(IF(S24=1,"1",IF(S24=2,"2","3+")),'Scoring Method'!$A$45:$A$47,0)))/90*100 | V24: =T24*U24/100 | W24: 16830 | X24: X (minimal hazard) | Y24: 22525 | Z24: =W24/I24 | AA24: =MAX(0,(Y24-5000)/300) | AC24: 0.95 | AD24: ok | AE24: Far oversize >12k | AF24: =INDEX('Scoring Method'!$B$63:$B$71,MATCH(AE24,'Scoring Method'!$A$63:$A$71,0))+INDEX('Scoring Method'!$B$75:$B$79,MATCH("Ample >=15k",'Scoring Method'!$A$75:$A$79,0))+INDEX('Scoring Method'!$B$343:$B$347,MATCH(X24,'Scoring Method'!$A$343:$A$347,0))+INDEX('Scoring Method'!$B$25:$B$27,MATCH(P24,'Scoring Method'!$A$25:$A$27,0)) | AG24: =AF24*U24/100 | AH24: LINK-GIS + LoopNet | AI24: 39.07129 | AJ24: -84.50747 | AK24: 1.06 | AL24: 1.35 | AM24: 2.1 | AN24: 0.9 | AO24: Fringe 0.75-1.25mi | AP24: Retail shell | AQ24: Ample >=15k | AS24: =ROUND(INDEX('Scoring Method'!$B$63:$B$70,MATCH(AE24,'Scoring Method'!$A$63:$A$70,0))*0.625+INDEX('Scoring Method'!$B$105:$B$113,MATCH(AP24,'Scoring Method'!$A$105:$A$113,0))+INDEX('Scoring Method'!$B$74:$B$78,MATCH(AQ24,'Scoring Method'!$A$74:$A$78,0))*0.6667+INDEX('Scoring Method'!$B$96:$B$101,MATCH(AO24,'Scoring Method'!$A$96:$A$101,0))+INDEX('Scoring Method'!$B$343:$B$347,MATCH(X24,'Scoring Method'!$A$343:$A$347,0))*0.3333+INDEX('Scoring Method'!$B$25:$B$27,MATCH(P24,'Scoring Method'!$A$25:$A$27,0))*0.3333,1) | AT24: =AS24*U24/100 | AU24: Eastside | AV24: 28 | AW24: ESTIMATED | AX24: High <35 | AY24: =ROUND(INDEX('Scoring Method'!$B$132:$B$140,MATCH(AE24,'Scoring Method'!$A$132:$A$140,0))+INDEX('Scoring Method'!$B$144:$B$152,MATCH(AP24,'Scoring Method'!$A$144:$A$152,0))+INDEX('Scoring Method'!$B$156:$B$160,MATCH(AQ24,'Scoring Method'!$A$156:$A$160,0))+INDEX('Scoring Method'!$B$164:$B$169,MATCH(AO24,'Scoring Method'!$A$164:$A$169,0))+INDEX('Scoring Method'!$B$173:$B$178,MATCH(AX24,'Scoring Method'!$A$173:$A$178,0))+INDEX('Scoring Method'!$B$349:$B$353,MATCH(X24,'Scoring Method'!$A$349:$A$353,0))+INDEX('Scoring Method'!$B$188:$B$190,MATCH(P24,'Scoring Method'!$A$188:$A$190,0)),1) | AZ24: =AY24*U24/100 | BA24: Chain format + investor | BB24: 0.45 | BC24: Large 0.75-1.25 AC | BD24: 0.9 | BE24: =ROUND(INDEX('Scoring Method'!$B$268:$B$276,MATCH(AE24,'Scoring Method'!$A$268:$A$276,0))+INDEX('Scoring Method'!$B$280:$B$288,MATCH(AP24,'Scoring Method'!$A$280:$A$288,0))+INDEX('Scoring Method'!$B$292:$B$296,MATCH(AQ24,'Scoring Method'!$A$292:$A$296,0))+INDEX('Scoring Method'!$B$300:$B$305,MATCH(AO24,'Scoring Method'!$A$300:$A$305,0))+INDEX('Scoring Method'!$B$309:$B$314,MATCH(AX24,'Scoring Method'!$A$309:$A$314,0))+INDEX('Scoring Method'!$B$337:$B$341,MATCH(X24,'Scoring Method'!$A$337:$A$341,0))+INDEX('Scoring Method'!$B$324:$B$326,MATCH(P24,'Scoring Method'!$A$324:$A$326,0)),1) | BF24: =ROUND(INDEX('Scoring Method'!$B$268:$B$276,MATCH(AE24,'Scoring Method'!$A$268:$A$276,0))*BB24*BD24+INDEX('Scoring Method'!$B$280:$B$288,MATCH(AP24,'Scoring Method'!$A$280:$A$288,0))*BM24*BB24*BD24+INDEX('Scoring Method'!$B$292:$B$296,MATCH(AQ24,'Scoring Method'!$A$292:$A$296,0))*BD24+INDEX('Scoring Method'!$B$300:$B$305,MATCH(AO24,'Scoring Method'!$A$300:$A$305,0))*BM24*BB24+INDEX('Scoring Method'!$B$309:$B$314,MATCH(AX24,'Scoring Method'!$A$309:$A$314,0))+INDEX('Scoring Method'!$B$337:$B$341,MATCH(X24,'Scoring Method'!$A$337:$A$341,0))+INDEX('Scoring Method'!$B$324:$B$326,MATCH(P24,'Scoring Method'!$A$324:$A$326,0)),1) | BG24: Over (~$15,428/mo) | BH24: AUC | BI24: Auto-Urban Commercial | BL24: Bar permitted | BM24: =INDEX('Scoring Method'!$B$358:$B$363,MATCH(BL24,'Scoring Method'!$A$358:$A$363,0))
A25: 24 | B25: 056-20-00-059.01 | C25: 4385 WINSTON AVE | D25: J & S LATONIA CENTRE KY LLC | E25: PO BOX 24550 | F25: COLUMBUS | G25: OH | H25: FAST FOOD-DRIVE THRU REST | I25: 40531 | J25: =I25/43560 | K25: 810 | L25: =I25/(K25^2) | M25: Near 14-18k/32-45k | N25: C | O25: Compact >=.055 | P25: Low | Q25: Out-of-state | R25: Operating entity | S25: 4 | T25: =INDEX('Scoring Method'!$B$6:$B$9,MATCH(M25,'Scoring Method'!$A$6:$A$9,0))+INDEX('Scoring Method'!$B$12:$B$16,MATCH(N25,'Scoring Method'!$A$12:$A$16,0))+INDEX('Scoring Method'!$B$19:$B$22,MATCH(O25,'Scoring Method'!$A$19:$A$22,0))+INDEX('Scoring Method'!$B$25:$B$27,MATCH(P25,'Scoring Method'!$A$25:$A$27,0)) | U25: =(INDEX('Scoring Method'!$B$30:$B$33,MATCH(Q25,'Scoring Method'!$A$30:$A$33,0))+INDEX('Scoring Method'!$B$36:$B$42,MATCH(R25,'Scoring Method'!$A$36:$A$42,0))+INDEX('Scoring Method'!$B$45:$B$47,MATCH(IF(S25=1,"1",IF(S25=2,"2","3+")),'Scoring Method'!$A$45:$A$47,0)))/90*100 | V25: =T25*U25/100 | W25: 3595 | X25: X (minimal hazard) | Y25: 36500 | Z25: =W25/I25 | AA25: =MAX(0,(Y25-5000)/300) | AC25: 38.19 | AD25: CHECK | AE25: Above 2.5-4k | AF25: =INDEX('Scoring Method'!$B$63:$B$71,MATCH(AE25,'Scoring Method'!$A$63:$A$71,0))+INDEX('Scoring Method'!$B$75:$B$79,MATCH("Ample >=15k",'Scoring Method'!$A$75:$A$79,0))+INDEX('Scoring Method'!$B$343:$B$347,MATCH(X25,'Scoring Method'!$A$343:$A$347,0))+INDEX('Scoring Method'!$B$25:$B$27,MATCH(P25,'Scoring Method'!$A$25:$A$27,0)) | AG25: =AF25*U25/100 | AH25: LINK-GIS + LoopNet | AI25: 39.03987 | AJ25: -84.50796 | AK25: 3.12 | AL25: 3.52 | AM25: 4.26 | AN25: 3.05 | AO25: Remote >3mi | AP25: Built-out kitchen | AQ25: Ample >=15k | AS25: =ROUND(INDEX('Scoring Method'!$B$63:$B$70,MATCH(AE25,'Scoring Method'!$A$63:$A$70,0))*0.625+INDEX('Scoring Method'!$B$105:$B$113,MATCH(AP25,'Scoring Method'!$A$105:$A$113,0))+INDEX('Scoring Method'!$B$74:$B$78,MATCH(AQ25,'Scoring Method'!$A$74:$A$78,0))*0.6667+INDEX('Scoring Method'!$B$96:$B$101,MATCH(AO25,'Scoring Method'!$A$96:$A$101,0))+INDEX('Scoring Method'!$B$343:$B$347,MATCH(X25,'Scoring Method'!$A$343:$A$347,0))*0.3333+INDEX('Scoring Method'!$B$25:$B$27,MATCH(P25,'Scoring Method'!$A$25:$A$27,0))*0.3333,1) | AT25: =AS25*U25/100 | AU25: Rittes East / Winston Park | AV25: 82 | AW25: Sourced | AX25: Very safe 80+ | AY25: =ROUND(INDEX('Scoring Method'!$B$132:$B$140,MATCH(AE25,'Scoring Method'!$A$132:$A$140,0))+INDEX('Scoring Method'!$B$144:$B$152,MATCH(AP25,'Scoring Method'!$A$144:$A$152,0))+INDEX('Scoring Method'!$B$156:$B$160,MATCH(AQ25,'Scoring Method'!$A$156:$A$160,0))+INDEX('Scoring Method'!$B$164:$B$169,MATCH(AO25,'Scoring Method'!$A$164:$A$169,0))+INDEX('Scoring Method'!$B$173:$B$178,MATCH(AX25,'Scoring Method'!$A$173:$A$178,0))+INDEX('Scoring Method'!$B$349:$B$353,MATCH(X25,'Scoring Method'!$A$349:$A$353,0))+INDEX('Scoring Method'!$B$188:$B$190,MATCH(P25,'Scoring Method'!$A$188:$A$190,0)),1) | AZ25: =AY25*U25/100 | BA25: Chain format + investor | BB25: 0.45 | BC25: Large 0.75-1.25 AC | BD25: 0.9 | BE25: =ROUND(INDEX('Scoring Method'!$B$268:$B$276,MATCH(AE25,'Scoring Method'!$A$268:$A$276,0))+INDEX('Scoring Method'!$B$280:$B$288,MATCH(AP25,'Scoring Method'!$A$280:$A$288,0))+INDEX('Scoring Method'!$B$292:$B$296,MATCH(AQ25,'Scoring Method'!$A$292:$A$296,0))+INDEX('Scoring Method'!$B$300:$B$305,MATCH(AO25,'Scoring Method'!$A$300:$A$305,0))+INDEX('Scoring Method'!$B$309:$B$314,MATCH(AX25,'Scoring Method'!$A$309:$A$314,0))+INDEX('Scoring Method'!$B$337:$B$341,MATCH(X25,'Scoring Method'!$A$337:$A$341,0))+INDEX('Scoring Method'!$B$324:$B$326,MATCH(P25,'Scoring Method'!$A$324:$A$326,0)),1) | BF25: =ROUND(INDEX('Scoring Method'!$B$268:$B$276,MATCH(AE25,'Scoring Method'!$A$268:$A$276,0))*BB25*BD25+INDEX('Scoring Method'!$B$280:$B$288,MATCH(AP25,'Scoring Method'!$A$280:$A$288,0))*BM25*BB25*BD25+INDEX('Scoring Method'!$B$292:$B$296,MATCH(AQ25,'Scoring Method'!$A$292:$A$296,0))*BD25+INDEX('Scoring Method'!$B$300:$B$305,MATCH(AO25,'Scoring Method'!$A$300:$A$305,0))*BM25*BB25+INDEX('Scoring Method'!$B$309:$B$314,MATCH(AX25,'Scoring Method'!$A$309:$A$314,0))+INDEX('Scoring Method'!$B$337:$B$341,MATCH(X25,'Scoring Method'!$A$337:$A$341,0))+INDEX('Scoring Method'!$B$324:$B$326,MATCH(P25,'Scoring Method'!$A$324:$A$326,0)),1) | BG25: Fits (~$3,295/mo) | BH25: AUC | BI25: Auto-Urban Commercial | BL25: Bar permitted | BM25: =INDEX('Scoring Method'!$B$358:$B$363,MATCH(BL25,'Scoring Method'!$A$358:$A$363,0))
A26: 25 | B26: 055-13-02-013.00 | C26: 1600 RUSSELL ST | D26: TMV HOLDINGS LLC | E26: 10838 OMAHA TRACE | F26: UNION | G26: KY | H26: WAREHOUSE 20001 - 100000 SQ FT | I26: 48172 | J26: =I26/43560 | K26: 945 | L26: =I26/(K26^2) | M26: Marginal 10-14k/45-60k | N26: B | O26: Regular .045-.055 | P26: Low | Q26: Out-of-city KY | R26: Passive vehicle | S26: 3 | T26: =INDEX('Scoring Method'!$B$6:$B$9,MATCH(M26,'Scoring Method'!$A$6:$A$9,0))+INDEX('Scoring Method'!$B$12:$B$16,MATCH(N26,'Scoring Method'!$A$12:$A$16,0))+INDEX('Scoring Method'!$B$19:$B$22,MATCH(O26,'Scoring Method'!$A$19:$A$22,0))+INDEX('Scoring Method'!$B$25:$B$27,MATCH(P26,'Scoring Method'!$A$25:$A$27,0)) | U26: =(INDEX('Scoring Method'!$B$30:$B$33,MATCH(Q26,'Scoring Method'!$A$30:$A$33,0))+INDEX('Scoring Method'!$B$36:$B$42,MATCH(R26,'Scoring Method'!$A$36:$A$42,0))+INDEX('Scoring Method'!$B$45:$B$47,MATCH(IF(S26=1,"1",IF(S26=2,"2","3+")),'Scoring Method'!$A$45:$A$47,0)))/90*100 | V26: =T26*U26/100 | W26: 24000 | X26: X (minimal hazard) | Y26: 22750 | Z26: =W26/I26 | AA26: =MAX(0,(Y26-5000)/300) | AC26: 1.09 | AD26: ok | AE26: Far oversize >12k | AF26: =INDEX('Scoring Method'!$B$63:$B$71,MATCH(AE26,'Scoring Method'!$A$63:$A$71,0))+INDEX('Scoring Method'!$B$75:$B$79,MATCH("Ample >=15k",'Scoring Method'!$A$75:$A$79,0))+INDEX('Scoring Method'!$B$343:$B$347,MATCH(X26,'Scoring Method'!$A$343:$A$347,0))+INDEX('Scoring Method'!$B$25:$B$27,MATCH(P26,'Scoring Method'!$A$25:$A$27,0)) | AG26: =AF26*U26/100 | AH26: LINK-GIS + LoopNet | AI26: 39.07098 | AJ26: -84.50956 | AK26: 1.03 | AL26: 1.37 | AM26: 2.11 | AN26: 0.9 | AO26: Fringe 0.75-1.25mi | AP26: Open span | AQ26: Ample >=15k | AS26: =ROUND(INDEX('Scoring Method'!$B$63:$B$70,MATCH(AE26,'Scoring Method'!$A$63:$A$70,0))*0.625+INDEX('Scoring Method'!$B$105:$B$113,MATCH(AP26,'Scoring Method'!$A$105:$A$113,0))+INDEX('Scoring Method'!$B$74:$B$78,MATCH(AQ26,'Scoring Method'!$A$74:$A$78,0))*0.6667+INDEX('Scoring Method'!$B$96:$B$101,MATCH(AO26,'Scoring Method'!$A$96:$A$101,0))+INDEX('Scoring Method'!$B$343:$B$347,MATCH(X26,'Scoring Method'!$A$343:$A$347,0))*0.3333+INDEX('Scoring Method'!$B$25:$B$27,MATCH(P26,'Scoring Method'!$A$25:$A$27,0))*0.3333,1) | AT26: =AS26*U26/100 | AU26: Eastside | AV26: 28 | AW26: ESTIMATED | AX26: High <35 | AY26: =ROUND(INDEX('Scoring Method'!$B$132:$B$140,MATCH(AE26,'Scoring Method'!$A$132:$A$140,0))+INDEX('Scoring Method'!$B$144:$B$152,MATCH(AP26,'Scoring Method'!$A$144:$A$152,0))+INDEX('Scoring Method'!$B$156:$B$160,MATCH(AQ26,'Scoring Method'!$A$156:$A$160,0))+INDEX('Scoring Method'!$B$164:$B$169,MATCH(AO26,'Scoring Method'!$A$164:$A$169,0))+INDEX('Scoring Method'!$B$173:$B$178,MATCH(AX26,'Scoring Method'!$A$173:$A$178,0))+INDEX('Scoring Method'!$B$349:$B$353,MATCH(X26,'Scoring Method'!$A$349:$A$353,0))+INDEX('Scoring Method'!$B$188:$B$190,MATCH(P26,'Scoring Method'!$A$188:$A$190,0)),1) | AZ26: =AY26*U26/100 | BA26: No chain signal | BB26: 1 | BC26: Large 0.75-1.25 AC | BD26: 0.9 | BE26: =ROUND(INDEX('Scoring Method'!$B$268:$B$276,MATCH(AE26,'Scoring Method'!$A$268:$A$276,0))+INDEX('Scoring Method'!$B$280:$B$288,MATCH(AP26,'Scoring Method'!$A$280:$A$288,0))+INDEX('Scoring Method'!$B$292:$B$296,MATCH(AQ26,'Scoring Method'!$A$292:$A$296,0))+INDEX('Scoring Method'!$B$300:$B$305,MATCH(AO26,'Scoring Method'!$A$300:$A$305,0))+INDEX('Scoring Method'!$B$309:$B$314,MATCH(AX26,'Scoring Method'!$A$309:$A$314,0))+INDEX('Scoring Method'!$B$337:$B$341,MATCH(X26,'Scoring Method'!$A$337:$A$341,0))+INDEX('Scoring Method'!$B$324:$B$326,MATCH(P26,'Scoring Method'!$A$324:$A$326,0)),1) | BF26: =ROUND(INDEX('Scoring Method'!$B$268:$B$276,MATCH(AE26,'Scoring Method'!$A$268:$A$276,0))*BB26*BD26+INDEX('Scoring Method'!$B$280:$B$288,MATCH(AP26,'Scoring Method'!$A$280:$A$288,0))*BM26*BB26*BD26+INDEX('Scoring Method'!$B$292:$B$296,MATCH(AQ26,'Scoring Method'!$A$292:$A$296,0))*BD26+INDEX('Scoring Method'!$B$300:$B$305,MATCH(AO26,'Scoring Method'!$A$300:$A$305,0))*BM26*BB26+INDEX('Scoring Method'!$B$309:$B$314,MATCH(AX26,'Scoring Method'!$A$309:$A$314,0))+INDEX('Scoring Method'!$B$337:$B$341,MATCH(X26,'Scoring Method'!$A$337:$A$341,0))+INDEX('Scoring Method'!$B$324:$B$326,MATCH(P26,'Scoring Method'!$A$324:$A$326,0)),1) | BG26: Over (~$22,000/mo) | BH26: LI | BI26: Limited Industrial | BL26: Bar prohibited, alt-path | BM26: =INDEX('Scoring Method'!$B$358:$B$363,MATCH(BL26,'Scoring Method'!$A$358:$A$363,0))
A27: 26 | B27: 056-31-03-002.00 | C27: 21 E 32ND ST | D27: MW & MW PROPERTIES INC | E27: PO BOX 15609 | F27: COVINGTON | G27: KY | H27: OTHER RETAIL | I27: 42126 | J27: =I27/43560 | K27: 822.9 | L27: =I27/(K27^2) | M27: Near 14-18k/32-45k | N27: C | O27: Compact >=.055 | P27: Low | Q27: Local absentee | R27: Passive vehicle | S27: 3 | T27: =INDEX('Scoring Method'!$B$6:$B$9,MATCH(M27,'Scoring Method'!$A$6:$A$9,0))+INDEX('Scoring Method'!$B$12:$B$16,MATCH(N27,'Scoring Method'!$A$12:$A$16,0))+INDEX('Scoring Method'!$B$19:$B$22,MATCH(O27,'Scoring Method'!$A$19:$A$22,0))+INDEX('Scoring Method'!$B$25:$B$27,MATCH(P27,'Scoring Method'!$A$25:$A$27,0)) | U27: =(INDEX('Scoring Method'!$B$30:$B$33,MATCH(Q27,'Scoring Method'!$A$30:$A$33,0))+INDEX('Scoring Method'!$B$36:$B$42,MATCH(R27,'Scoring Method'!$A$36:$A$42,0))+INDEX('Scoring Method'!$B$45:$B$47,MATCH(IF(S27=1,"1",IF(S27=2,"2","3+")),'Scoring Method'!$A$45:$A$47,0)))/90*100 | V27: =T27*U27/100 | W27: 37000 | X27: X (minimal hazard) | Y27: 0 | Z27: =W27/I27 | AA27: =MAX(0,(Y27-5000)/300) | AC27: 0.97 | AD27: ok | AE27: Far oversize >12k | AF27: =INDEX('Scoring Method'!$B$63:$B$71,MATCH(AE27,'Scoring Method'!$A$63:$A$71,0))+INDEX('Scoring Method'!$B$75:$B$79,MATCH("Insufficient <2k",'Scoring Method'!$A$75:$A$79,0))+INDEX('Scoring Method'!$B$343:$B$347,MATCH(X27,'Scoring Method'!$A$343:$A$347,0))+INDEX('Scoring Method'!$B$25:$B$27,MATCH(P27,'Scoring Method'!$A$25:$A$27,0)) | AG27: =AF27*U27/100 | AH27: LINK-GIS + LoopNet | AI27: 39.05257 | AJ27: -84.50158 | AK27: 2.37 | AL27: 2.67 | AM27: 3.43 | AN27: 2.23 | AO27: Distant 2-3mi | AP27: Retail shell | AQ27: Insufficient <2k | AS27: =ROUND(INDEX('Scoring Method'!$B$63:$B$70,MATCH(AE27,'Scoring Method'!$A$63:$A$70,0))*0.625+INDEX('Scoring Method'!$B$105:$B$113,MATCH(AP27,'Scoring Method'!$A$105:$A$113,0))+INDEX('Scoring Method'!$B$74:$B$78,MATCH(AQ27,'Scoring Method'!$A$74:$A$78,0))*0.6667+INDEX('Scoring Method'!$B$96:$B$101,MATCH(AO27,'Scoring Method'!$A$96:$A$101,0))+INDEX('Scoring Method'!$B$343:$B$347,MATCH(X27,'Scoring Method'!$A$343:$A$347,0))*0.3333+INDEX('Scoring Method'!$B$25:$B$27,MATCH(P27,'Scoring Method'!$A$25:$A$27,0))*0.3333,1) | AT27: =AS27*U27/100 | AU27: Latonia | AV27: 78 | AW27: Sourced | AX27: Safe 70-79 | AY27: =ROUND(INDEX('Scoring Method'!$B$132:$B$140,MATCH(AE27,'Scoring Method'!$A$132:$A$140,0))+INDEX('Scoring Method'!$B$144:$B$152,MATCH(AP27,'Scoring Method'!$A$144:$A$152,0))+INDEX('Scoring Method'!$B$156:$B$160,MATCH(AQ27,'Scoring Method'!$A$156:$A$160,0))+INDEX('Scoring Method'!$B$164:$B$169,MATCH(AO27,'Scoring Method'!$A$164:$A$169,0))+INDEX('Scoring Method'!$B$173:$B$178,MATCH(AX27,'Scoring Method'!$A$173:$A$178,0))+INDEX('Scoring Method'!$B$349:$B$353,MATCH(X27,'Scoring Method'!$A$349:$A$353,0))+INDEX('Scoring Method'!$B$188:$B$190,MATCH(P27,'Scoring Method'!$A$188:$A$190,0)),1) | AZ27: =AY27*U27/100 | BA27: No chain signal | BB27: 1 | BC27: Large 0.75-1.25 AC | BD27: 0.9 | BE27: =ROUND(INDEX('Scoring Method'!$B$268:$B$276,MATCH(AE27,'Scoring Method'!$A$268:$A$276,0))+INDEX('Scoring Method'!$B$280:$B$288,MATCH(AP27,'Scoring Method'!$A$280:$A$288,0))+INDEX('Scoring Method'!$B$292:$B$296,MATCH(AQ27,'Scoring Method'!$A$292:$A$296,0))+INDEX('Scoring Method'!$B$300:$B$305,MATCH(AO27,'Scoring Method'!$A$300:$A$305,0))+INDEX('Scoring Method'!$B$309:$B$314,MATCH(AX27,'Scoring Method'!$A$309:$A$314,0))+INDEX('Scoring Method'!$B$337:$B$341,MATCH(X27,'Scoring Method'!$A$337:$A$341,0))+INDEX('Scoring Method'!$B$324:$B$326,MATCH(P27,'Scoring Method'!$A$324:$A$326,0)),1) | BF27: =ROUND(INDEX('Scoring Method'!$B$268:$B$276,MATCH(AE27,'Scoring Method'!$A$268:$A$276,0))*BB27*BD27+INDEX('Scoring Method'!$B$280:$B$288,MATCH(AP27,'Scoring Method'!$A$280:$A$288,0))*BM27*BB27*BD27+INDEX('Scoring Method'!$B$292:$B$296,MATCH(AQ27,'Scoring Method'!$A$292:$A$296,0))*BD27+INDEX('Scoring Method'!$B$300:$B$305,MATCH(AO27,'Scoring Method'!$A$300:$A$305,0))*BM27*BB27+INDEX('Scoring Method'!$B$309:$B$314,MATCH(AX27,'Scoring Method'!$A$309:$A$314,0))+INDEX('Scoring Method'!$B$337:$B$341,MATCH(X27,'Scoring Method'!$A$337:$A$341,0))+INDEX('Scoring Method'!$B$324:$B$326,MATCH(P27,'Scoring Method'!$A$324:$A$326,0)),1) | BG27: Over (~$33,917/mo) | BH27: AUC | BI27: Auto-Urban Commercial | BL27: Bar permitted | BM27: =INDEX('Scoring Method'!$B$358:$B$363,MATCH(BL27,'Scoring Method'!$A$358:$A$363,0))
A28: 27 | B28: 055-13-08-020.00 | C28: 1442 MADISON AVE | D28: NEW HORIZON PROPERTIES LLC | E28: 3000 READING RD | F28: CINCINNATI | G28: OH | H28: OFFICE BLDG 1 OR 2 STORY | I28: 15022 | J28: =I28/43560 | K28: 501 | L28: =I28/(K28^2) | M28: Near 14-18k/32-45k | N28: E | O28: Compact >=.055 | P28: Low | Q28: Out-of-state | R28: Passive vehicle | S28: 2 | T28: =INDEX('Scoring Method'!$B$6:$B$9,MATCH(M28,'Scoring Method'!$A$6:$A$9,0))+INDEX('Scoring Method'!$B$12:$B$16,MATCH(N28,'Scoring Method'!$A$12:$A$16,0))+INDEX('Scoring Method'!$B$19:$B$22,MATCH(O28,'Scoring Method'!$A$19:$A$22,0))+INDEX('Scoring Method'!$B$25:$B$27,MATCH(P28,'Scoring Method'!$A$25:$A$27,0)) | U28: =(INDEX('Scoring Method'!$B$30:$B$33,MATCH(Q28,'Scoring Method'!$A$30:$A$33,0))+INDEX('Scoring Method'!$B$36:$B$42,MATCH(R28,'Scoring Method'!$A$36:$A$42,0))+INDEX('Scoring Method'!$B$45:$B$47,MATCH(IF(S28=1,"1",IF(S28=2,"2","3+")),'Scoring Method'!$A$45:$A$47,0)))/90*100 | V28: =T28*U28/100 | W28: 4250 | X28: X (minimal hazard) | Y28: 8550 | AA28: =MAX(0,(Y28-5000)/300) | AE28: Large 4-6k | AF28: =INDEX('Scoring Method'!$B$63:$B$71,MATCH(AE28,'Scoring Method'!$A$63:$A$71,0))+INDEX('Scoring Method'!$B$75:$B$79,MATCH("Good 8-15k",'Scoring Method'!$A$75:$A$79,0))+INDEX('Scoring Method'!$B$343:$B$347,MATCH(X28,'Scoring Method'!$A$343:$A$347,0))+INDEX('Scoring Method'!$B$25:$B$27,MATCH(P28,'Scoring Method'!$A$25:$A$27,0)) | AG28: =AF28*U28/100 | AH28: LINK-GIS + LoopNet (2026-08-02) | AI28: 39.07402 | AJ28: -84.50719 | AK28: 0.92 | AL28: 1.16 | AM28: 1.92 | AN28: 0.72 | AO28: Near 0.35-0.75mi | AP28: Office/institutional | AQ28: Good 8-15k | AS28: =ROUND(INDEX('Scoring Method'!$B$63:$B$70,MATCH(AE28,'Scoring Method'!$A$63:$A$70,0))*0.625+INDEX('Scoring Method'!$B$105:$B$113,MATCH(AP28,'Scoring Method'!$A$105:$A$113,0))+INDEX('Scoring Method'!$B$74:$B$78,MATCH(AQ28,'Scoring Method'!$A$74:$A$78,0))*0.6667+INDEX('Scoring Method'!$B$96:$B$101,MATCH(AO28,'Scoring Method'!$A$96:$A$101,0))+INDEX('Scoring Method'!$B$343:$B$347,MATCH(X28,'Scoring Method'!$A$343:$A$347,0))*0.3333+INDEX('Scoring Method'!$B$25:$B$27,MATCH(P28,'Scoring Method'!$A$25:$A$27,0))*0.3333,1) | AT28: =AS28*U28/100 | AU28: Eastside | AV28: 28 | AW28: ESTIMATED | AX28: High <35 | AY28: =ROUND(INDEX('Scoring Method'!$B$132:$B$140,MATCH(AE28,'Scoring Method'!$A$132:$A$140,0))+INDEX('Scoring Method'!$B$144:$B$152,MATCH(AP28,'Scoring Method'!$A$144:$A$152,0))+INDEX('Scoring Method'!$B$156:$B$160,MATCH(AQ28,'Scoring Method'!$A$156:$A$160,0))+INDEX('Scoring Method'!$B$164:$B$169,MATCH(AO28,'Scoring Method'!$A$164:$A$169,0))+INDEX('Scoring Method'!$B$173:$B$178,MATCH(AX28,'Scoring Method'!$A$173:$A$178,0))+INDEX('Scoring Method'!$B$349:$B$353,MATCH(X28,'Scoring Method'!$A$349:$A$353,0))+INDEX('Scoring Method'!$B$188:$B$190,MATCH(P28,'Scoring Method'!$A$188:$A$190,0)),1) | AZ28: =AY28*U28/100 | BA28: No chain signal | BB28: 1 | BC28: Small 0.25-0.35 AC | BD28: 0.9 | BE28: =ROUND(INDEX('Scoring Method'!$B$268:$B$276,MATCH(AE28,'Scoring Method'!$A$268:$A$276,0))+INDEX('Scoring Method'!$B$280:$B$288,MATCH(AP28,'Scoring Method'!$A$280:$A$288,0))+INDEX('Scoring Method'!$B$292:$B$296,MATCH(AQ28,'Scoring Method'!$A$292:$A$296,0))+INDEX('Scoring Method'!$B$300:$B$305,MATCH(AO28,'Scoring Method'!$A$300:$A$305,0))+INDEX('Scoring Method'!$B$309:$B$314,MATCH(AX28,'Scoring Method'!$A$309:$A$314,0))+INDEX('Scoring Method'!$B$337:$B$341,MATCH(X28,'Scoring Method'!$A$337:$A$341,0))+INDEX('Scoring Method'!$B$324:$B$326,MATCH(P28,'Scoring Method'!$A$324:$A$326,0)),1) | BF28: =ROUND(INDEX('Scoring Method'!$B$268:$B$276,MATCH(AE28,'Scoring Method'!$A$268:$A$276,0))*BB28*BD28+INDEX('Scoring Method'!$B$280:$B$288,MATCH(AP28,'Scoring Method'!$A$280:$A$288,0))*BM28*BB28*BD28+INDEX('Scoring Method'!$B$292:$B$296,MATCH(AQ28,'Scoring Method'!$A$292:$A$296,0))*BD28+INDEX('Scoring Method'!$B$300:$B$305,MATCH(AO28,'Scoring Method'!$A$300:$A$305,0))*BM28*BB28+INDEX('Scoring Method'!$B$309:$B$314,MATCH(AX28,'Scoring Method'!$A$309:$A$314,0))+INDEX('Scoring Method'!$B$337:$B$341,MATCH(X28,'Scoring Method'!$A$337:$A$341,0))+INDEX('Scoring Method'!$B$324:$B$326,MATCH(P28,'Scoring Method'!$A$324:$A$326,0)),1) | BG28: Fits (~$3,896/mo) | BH28: DTC | BI28: Downtown Core | BL28: Bar permitted | BM28: =INDEX('Scoring Method'!$B$358:$B$363,MATCH(BL28,'Scoring Method'!$A$358:$A$363,0))
A29: 28 | B29: 058-40-00-004.02 | C29: 3865 WOLF RD | D29: PIERSON JACOB & LYNNE | E29: 11935 S HERDING AVE | F29: ALSIP | G29: IL | H29: MISCELLANEOUS IMPROVEMENT | I29: 16607 | J29: =I29/43560 | K29: 531.6 | L29: =I29/(K29^2) | M29: Near 14-18k/32-45k | N29: D | O29: Compact >=.055 | P29: Low | Q29: Out-of-state | R29: Individual | S29: 1 | T29: =INDEX('Scoring Method'!$B$6:$B$9,MATCH(M29,'Scoring Method'!$A$6:$A$9,0))+INDEX('Scoring Method'!$B$12:$B$16,MATCH(N29,'Scoring Method'!$A$12:$A$16,0))+INDEX('Scoring Method'!$B$19:$B$22,MATCH(O29,'Scoring Method'!$A$19:$A$22,0))+INDEX('Scoring Method'!$B$25:$B$27,MATCH(P29,'Scoring Method'!$A$25:$A$27,0)) | U29: =(INDEX('Scoring Method'!$B$30:$B$33,MATCH(Q29,'Scoring Method'!$A$30:$A$33,0))+INDEX('Scoring Method'!$B$36:$B$42,MATCH(R29,'Scoring Method'!$A$36:$A$42,0))+INDEX('Scoring Method'!$B$45:$B$47,MATCH(IF(S29=1,"1",IF(S29=2,"2","3+")),'Scoring Method'!$A$45:$A$47,0)))/90*100 | V29: =T29*U29/100 | W29: 905 | X29: X (minimal hazard) | Y29: 15525 | Z29: =W29/I29 | AA29: =MAX(0,(Y29-5000)/300) | AC29: 0.25 | AD29: CHECK | AE29: Too small <1.2k | AF29: =INDEX('Scoring Method'!$B$63:$B$71,MATCH(AE29,'Scoring Method'!$A$63:$A$71,0))+INDEX('Scoring Method'!$B$75:$B$79,MATCH("Ample >=15k",'Scoring Method'!$A$75:$A$79,0))+INDEX('Scoring Method'!$B$343:$B$347,MATCH(X29,'Scoring Method'!$A$343:$A$347,0))+INDEX('Scoring Method'!$B$25:$B$27,MATCH(P29,'Scoring Method'!$A$25:$A$27,0)) | AG29: =AF29*U29/100 | AH29: LINK-GIS + LoopNet | AI29: 38.98829 | AJ29: -84.49155 | AK29: 6.79 | AL29: 7.14 | AM29: 7.9 | AN29: 6.69 | AO29: Remote >3mi | AP29: Lot / minimal bldg | AQ29: Ample >=15k | AS29: =ROUND(INDEX('Scoring Method'!$B$63:$B$70,MATCH(AE29,'Scoring Method'!$A$63:$A$70,0))*0.625+INDEX('Scoring Method'!$B$105:$B$113,MATCH(AP29,'Scoring Method'!$A$105:$A$113,0))+INDEX('Scoring Method'!$B$74:$B$78,MATCH(AQ29,'Scoring Method'!$A$74:$A$78,0))*0.6667+INDEX('Scoring Method'!$B$96:$B$101,MATCH(AO29,'Scoring Method'!$A$96:$A$101,0))+INDEX('Scoring Method'!$B$343:$B$347,MATCH(X29,'Scoring Method'!$A$343:$A$347,0))*0.3333+INDEX('Scoring Method'!$B$25:$B$27,MATCH(P29,'Scoring Method'!$A$25:$A$27,0))*0.3333,1) | AT29: =AS29*U29/100 | AU29: South Covington | AV29: 88 | AW29: Sourced | AX29: Very safe 80+ | AY29: =ROUND(INDEX('Scoring Method'!$B$132:$B$140,MATCH(AE29,'Scoring Method'!$A$132:$A$140,0))+INDEX('Scoring Method'!$B$144:$B$152,MATCH(AP29,'Scoring Method'!$A$144:$A$152,0))+INDEX('Scoring Method'!$B$156:$B$160,MATCH(AQ29,'Scoring Method'!$A$156:$A$160,0))+INDEX('Scoring Method'!$B$164:$B$169,MATCH(AO29,'Scoring Method'!$A$164:$A$169,0))+INDEX('Scoring Method'!$B$173:$B$178,MATCH(AX29,'Scoring Method'!$A$173:$A$178,0))+INDEX('Scoring Method'!$B$349:$B$353,MATCH(X29,'Scoring Method'!$A$349:$A$353,0))+INDEX('Scoring Method'!$B$188:$B$190,MATCH(P29,'Scoring Method'!$A$188:$A$190,0)),1) | AZ29: =AY29*U29/100 | BA29: No chain signal | BB29: 1 | BC29: Right-sized 0.35-0.75 AC | BD29: 1 | BE29: =ROUND(INDEX('Scoring Method'!$B$268:$B$276,MATCH(AE29,'Scoring Method'!$A$268:$A$276,0))+INDEX('Scoring Method'!$B$280:$B$288,MATCH(AP29,'Scoring Method'!$A$280:$A$288,0))+INDEX('Scoring Method'!$B$292:$B$296,MATCH(AQ29,'Scoring Method'!$A$292:$A$296,0))+INDEX('Scoring Method'!$B$300:$B$305,MATCH(AO29,'Scoring Method'!$A$300:$A$305,0))+INDEX('Scoring Method'!$B$309:$B$314,MATCH(AX29,'Scoring Method'!$A$309:$A$314,0))+INDEX('Scoring Method'!$B$337:$B$341,MATCH(X29,'Scoring Method'!$A$337:$A$341,0))+INDEX('Scoring Method'!$B$324:$B$326,MATCH(P29,'Scoring Method'!$A$324:$A$326,0)),1) | BF29: =ROUND(INDEX('Scoring Method'!$B$268:$B$276,MATCH(AE29,'Scoring Method'!$A$268:$A$276,0))*BB29*BD29+INDEX('Scoring Method'!$B$280:$B$288,MATCH(AP29,'Scoring Method'!$A$280:$A$288,0))*BM29*BB29*BD29+INDEX('Scoring Method'!$B$292:$B$296,MATCH(AQ29,'Scoring Method'!$A$292:$A$296,0))*BD29+INDEX('Scoring Method'!$B$300:$B$305,MATCH(AO29,'Scoring Method'!$A$300:$A$305,0))*BM29*BB29+INDEX('Scoring Method'!$B$309:$B$314,MATCH(AX29,'Scoring Method'!$A$309:$A$314,0))+INDEX('Scoring Method'!$B$337:$B$341,MATCH(X29,'Scoring Method'!$A$337:$A$341,0))+INDEX('Scoring Method'!$B$324:$B$326,MATCH(P29,'Scoring Method'!$A$324:$A$326,0)),1) | BG29: Fits (~$830/mo) | BH29: SR | BI29: Suburban Residential | BL29: No path | BM29: =INDEX('Scoring Method'!$B$358:$B$363,MATCH(BL29,'Scoring Method'!$A$358:$A$363,0))
A30: 29 | B30: 056-11-09-002.00 | C30: 3024 MADISON AVE | D30: SCHEWE STEPHEN & DEMOSS LYNN | E30: 504 WOLFZORN CT | F30: FT WRIGHT | G30: KY | H30: RESTAURANT CAFE/BAR | I30: 14919 | J30: =I30/43560 | K30: 498.3 | L30: =I30/(K30^2) | M30: Near 14-18k/32-45k | N30: C | O30: Compact >=.055 | P30: Low | Q30: Out-of-city KY | R30: Individual | S30: 1 | T30: =INDEX('Scoring Method'!$B$6:$B$9,MATCH(M30,'Scoring Method'!$A$6:$A$9,0))+INDEX('Scoring Method'!$B$12:$B$16,MATCH(N30,'Scoring Method'!$A$12:$A$16,0))+INDEX('Scoring Method'!$B$19:$B$22,MATCH(O30,'Scoring Method'!$A$19:$A$22,0))+INDEX('Scoring Method'!$B$25:$B$27,MATCH(P30,'Scoring Method'!$A$25:$A$27,0)) | U30: =(INDEX('Scoring Method'!$B$30:$B$33,MATCH(Q30,'Scoring Method'!$A$30:$A$33,0))+INDEX('Scoring Method'!$B$36:$B$42,MATCH(R30,'Scoring Method'!$A$36:$A$42,0))+INDEX('Scoring Method'!$B$45:$B$47,MATCH(IF(S30=1,"1",IF(S30=2,"2","3+")),'Scoring Method'!$A$45:$A$47,0)))/90*100 | V30: =T30*U30/100 | W30: 616 | X30: X (minimal hazard) | Y30: 12650 | Z30: =W30/I30 | AA30: =MAX(0,(Y30-5000)/300) | AC30: 0.35 | AD30: ok | AE30: Too small <1.2k | AF30: =INDEX('Scoring Method'!$B$63:$B$71,MATCH(AE30,'Scoring Method'!$A$63:$A$71,0))+INDEX('Scoring Method'!$B$75:$B$79,MATCH("Good 8-15k",'Scoring Method'!$A$75:$A$79,0))+INDEX('Scoring Method'!$B$343:$B$347,MATCH(X30,'Scoring Method'!$A$343:$A$347,0))+INDEX('Scoring Method'!$B$25:$B$27,MATCH(P30,'Scoring Method'!$A$25:$A$27,0)) | AG30: =AF30*U30/100 | AH30: LINK-GIS + LoopNet | AI30: 39.05226 | AJ30: -84.51639 | AK30: 2.22 | AL30: 2.7 | AM30: 3.41 | AN30: 2.21 | AO30: Distant 2-3mi | AP30: Built-out kitchen | AQ30: Good 8-15k | AS30: =ROUND(INDEX('Scoring Method'!$B$63:$B$70,MATCH(AE30,'Scoring Method'!$A$63:$A$70,0))*0.625+INDEX('Scoring Method'!$B$105:$B$113,MATCH(AP30,'Scoring Method'!$A$105:$A$113,0))+INDEX('Scoring Method'!$B$74:$B$78,MATCH(AQ30,'Scoring Method'!$A$74:$A$78,0))*0.6667+INDEX('Scoring Method'!$B$96:$B$101,MATCH(AO30,'Scoring Method'!$A$96:$A$101,0))+INDEX('Scoring Method'!$B$343:$B$347,MATCH(X30,'Scoring Method'!$A$343:$A$347,0))*0.3333+INDEX('Scoring Method'!$B$25:$B$27,MATCH(P30,'Scoring Method'!$A$25:$A$27,0))*0.3333,1) | AT30: =AS30*U30/100 | AU30: Latonia Rosedale | AV30: 68 | AW30: Sourced | AX30: Moderate 60-69 | AY30: =ROUND(INDEX('Scoring Method'!$B$132:$B$140,MATCH(AE30,'Scoring Method'!$A$132:$A$140,0))+INDEX('Scoring Method'!$B$144:$B$152,MATCH(AP30,'Scoring Method'!$A$144:$A$152,0))+INDEX('Scoring Method'!$B$156:$B$160,MATCH(AQ30,'Scoring Method'!$A$156:$A$160,0))+INDEX('Scoring Method'!$B$164:$B$169,MATCH(AO30,'Scoring Method'!$A$164:$A$169,0))+INDEX('Scoring Method'!$B$173:$B$178,MATCH(AX30,'Scoring Method'!$A$173:$A$178,0))+INDEX('Scoring Method'!$B$349:$B$353,MATCH(X30,'Scoring Method'!$A$349:$A$353,0))+INDEX('Scoring Method'!$B$188:$B$190,MATCH(P30,'Scoring Method'!$A$188:$A$190,0)),1) | AZ30: =AY30*U30/100 | BA30: No chain signal | BB30: 1 | BC30: Small 0.25-0.35 AC | BD30: 0.9 | BE30: =ROUND(INDEX('Scoring Method'!$B$268:$B$276,MATCH(AE30,'Scoring Method'!$A$268:$A$276,0))+INDEX('Scoring Method'!$B$280:$B$288,MATCH(AP30,'Scoring Method'!$A$280:$A$288,0))+INDEX('Scoring Method'!$B$292:$B$296,MATCH(AQ30,'Scoring Method'!$A$292:$A$296,0))+INDEX('Scoring Method'!$B$300:$B$305,MATCH(AO30,'Scoring Method'!$A$300:$A$305,0))+INDEX('Scoring Method'!$B$309:$B$314,MATCH(AX30,'Scoring Method'!$A$309:$A$314,0))+INDEX('Scoring Method'!$B$337:$B$341,MATCH(X30,'Scoring Method'!$A$337:$A$341,0))+INDEX('Scoring Method'!$B$324:$B$326,MATCH(P30,'Scoring Method'!$A$324:$A$326,0)),1) | BF30: =ROUND(INDEX('Scoring Method'!$B$268:$B$276,MATCH(AE30,'Scoring Method'!$A$268:$A$276,0))*BB30*BD30+INDEX('Scoring Method'!$B$280:$B$288,MATCH(AP30,'Scoring Method'!$A$280:$A$288,0))*BM30*BB30*BD30+INDEX('Scoring Method'!$B$292:$B$296,MATCH(AQ30,'Scoring Method'!$A$292:$A$296,0))*BD30+INDEX('Scoring Method'!$B$300:$B$305,MATCH(AO30,'Scoring Method'!$A$300:$A$305,0))*BM30*BB30+INDEX('Scoring Method'!$B$309:$B$314,MATCH(AX30,'Scoring Method'!$A$309:$A$314,0))+INDEX('Scoring Method'!$B$337:$B$341,MATCH(X30,'Scoring Method'!$A$337:$A$341,0))+INDEX('Scoring Method'!$B$324:$B$326,MATCH(P30,'Scoring Method'!$A$324:$A$326,0)),1) | BG30: Fits (~$565/mo) | BH30: SU | BI30: Semi-Urban Residential | BL30: SU corner unverified | BM30: =INDEX('Scoring Method'!$B$358:$B$363,MATCH(BL30,'Scoring Method'!$A$358:$A$363,0))
A31: 30 | B31: 044-00-00-004.01 | C31: 1016 MARY LAIDLEY DR | D31: BARNETT HOLDINGS LLC | E31: 1012 MARY LAIDLEY DR | F31: COVINGTON | G31: KY | H31: SMALL SHOP | I31: 54313 | J31: =I31/43560 | K31: 935.6 | L31: =I31/(K31^2) | M31: Marginal 10-14k/45-60k | N31: A | O31: Compact >=.055 | P31: Low | Q31: Local absentee | R31: Passive vehicle | S31: 2 | T31: =INDEX('Scoring Method'!$B$6:$B$9,MATCH(M31,'Scoring Method'!$A$6:$A$9,0))+INDEX('Scoring Method'!$B$12:$B$16,MATCH(N31,'Scoring Method'!$A$12:$A$16,0))+INDEX('Scoring Method'!$B$19:$B$22,MATCH(O31,'Scoring Method'!$A$19:$A$22,0))+INDEX('Scoring Method'!$B$25:$B$27,MATCH(P31,'Scoring Method'!$A$25:$A$27,0)) | U31: =(INDEX('Scoring Method'!$B$30:$B$33,MATCH(Q31,'Scoring Method'!$A$30:$A$33,0))+INDEX('Scoring Method'!$B$36:$B$42,MATCH(R31,'Scoring Method'!$A$36:$A$42,0))+INDEX('Scoring Method'!$B$45:$B$47,MATCH(IF(S31=1,"1",IF(S31=2,"2","3+")),'Scoring Method'!$A$45:$A$47,0)))/90*100 | V31: =T31*U31/100 | W31: 9578 | X31: X (minimal hazard) | Y31: 43000 | Z31: =W31/I31 | AA31: =MAX(0,(Y31-5000)/300) | AC31: 1.26 | AD31: ok | AE31: Oversize 6-12k | AF31: =INDEX('Scoring Method'!$B$63:$B$71,MATCH(AE31,'Scoring Method'!$A$63:$A$71,0))+INDEX('Scoring Method'!$B$75:$B$79,MATCH("Ample >=15k",'Scoring Method'!$A$75:$A$79,0))+INDEX('Scoring Method'!$B$343:$B$347,MATCH(X31,'Scoring Method'!$A$343:$A$347,0))+INDEX('Scoring Method'!$B$25:$B$27,MATCH(P31,'Scoring Method'!$A$25:$A$27,0)) | AG31: =AF31*U31/100 | AH31: LINK-GIS + LoopNet | AI31: 39.00269 | AJ31: -84.53418 | AK31: 5.71 | AL31: 6.25 | AM31: 6.93 | AN31: 5.71 | AO31: Remote >3mi | AP31: Open span | AQ31: Ample >=15k | AS31: =ROUND(INDEX('Scoring Method'!$B$63:$B$70,MATCH(AE31,'Scoring Method'!$A$63:$A$70,0))*0.625+INDEX('Scoring Method'!$B$105:$B$113,MATCH(AP31,'Scoring Method'!$A$105:$A$113,0))+INDEX('Scoring Method'!$B$74:$B$78,MATCH(AQ31,'Scoring Method'!$A$74:$A$78,0))*0.6667+INDEX('Scoring Method'!$B$96:$B$101,MATCH(AO31,'Scoring Method'!$A$96:$A$101,0))+INDEX('Scoring Method'!$B$343:$B$347,MATCH(X31,'Scoring Method'!$A$343:$A$347,0))*0.3333+INDEX('Scoring Method'!$B$25:$B$27,MATCH(P31,'Scoring Method'!$A$25:$A$27,0))*0.3333,1) | AT31: =AS31*U31/100 | AU31: South Covington | AV31: 88 | AW31: Sourced | AX31: Very safe 80+ | AY31: =ROUND(INDEX('Scoring Method'!$B$132:$B$140,MATCH(AE31,'Scoring Method'!$A$132:$A$140,0))+INDEX('Scoring Method'!$B$144:$B$152,MATCH(AP31,'Scoring Method'!$A$144:$A$152,0))+INDEX('Scoring Method'!$B$156:$B$160,MATCH(AQ31,'Scoring Method'!$A$156:$A$160,0))+INDEX('Scoring Method'!$B$164:$B$169,MATCH(AO31,'Scoring Method'!$A$164:$A$169,0))+INDEX('Scoring Method'!$B$173:$B$178,MATCH(AX31,'Scoring Method'!$A$173:$A$178,0))+INDEX('Scoring Method'!$B$349:$B$353,MATCH(X31,'Scoring Method'!$A$349:$A$353,0))+INDEX('Scoring Method'!$B$188:$B$190,MATCH(P31,'Scoring Method'!$A$188:$A$190,0)),1) | AZ31: =AY31*U31/100 | BA31: No chain signal | BB31: 1 | BC31: Large 0.75-1.25 AC | BD31: 0.9 | BE31: =ROUND(INDEX('Scoring Method'!$B$268:$B$276,MATCH(AE31,'Scoring Method'!$A$268:$A$276,0))+INDEX('Scoring Method'!$B$280:$B$288,MATCH(AP31,'Scoring Method'!$A$280:$A$288,0))+INDEX('Scoring Method'!$B$292:$B$296,MATCH(AQ31,'Scoring Method'!$A$292:$A$296,0))+INDEX('Scoring Method'!$B$300:$B$305,MATCH(AO31,'Scoring Method'!$A$300:$A$305,0))+INDEX('Scoring Method'!$B$309:$B$314,MATCH(AX31,'Scoring Method'!$A$309:$A$314,0))+INDEX('Scoring Method'!$B$337:$B$341,MATCH(X31,'Scoring Method'!$A$337:$A$341,0))+INDEX('Scoring Method'!$B$324:$B$326,MATCH(P31,'Scoring Method'!$A$324:$A$326,0)),1) | BF31: =ROUND(INDEX('Scoring Method'!$B$268:$B$276,MATCH(AE31,'Scoring Method'!$A$268:$A$276,0))*BB31*BD31+INDEX('Scoring Method'!$B$280:$B$288,MATCH(AP31,'Scoring Method'!$A$280:$A$288,0))*BM31*BB31*BD31+INDEX('Scoring Method'!$B$292:$B$296,MATCH(AQ31,'Scoring Method'!$A$292:$A$296,0))*BD31+INDEX('Scoring Method'!$B$300:$B$305,MATCH(AO31,'Scoring Method'!$A$300:$A$305,0))*BM31*BB31+INDEX('Scoring Method'!$B$309:$B$314,MATCH(AX31,'Scoring Method'!$A$309:$A$314,0))+INDEX('Scoring Method'!$B$337:$B$341,MATCH(X31,'Scoring Method'!$A$337:$A$341,0))+INDEX('Scoring Method'!$B$324:$B$326,MATCH(P31,'Scoring Method'!$A$324:$A$326,0)),1) | BG31: Fits (~$8,780/mo) | BH31: SI | BI31: Suburban Industrial | BL31: Bar permitted | BM31: =INDEX('Scoring Method'!$B$358:$B$363,MATCH(BL31,'Scoring Method'!$A$358:$A$363,0))
A32: 31 | B32: 055-14-15-002.00 | C32: 15 E 17TH ST | D32: SHELL MGM COVINGTON LLC | E32: 2582 GRANDIN RD | F32: CINCINNATI | G32: OH | H32: PAVED LOT | I32: 25889 | J32: =I32/43560 | K32: 650.9 | L32: =I32/(K32^2) | M32: Ideal 18-32k | N32: D | O32: Compact >=.055 | P32: Low | Q32: Out-of-state | R32: Operating entity | S32: 2 | T32: =INDEX('Scoring Method'!$B$6:$B$9,MATCH(M32,'Scoring Method'!$A$6:$A$9,0))+INDEX('Scoring Method'!$B$12:$B$16,MATCH(N32,'Scoring Method'!$A$12:$A$16,0))+INDEX('Scoring Method'!$B$19:$B$22,MATCH(O32,'Scoring Method'!$A$19:$A$22,0))+INDEX('Scoring Method'!$B$25:$B$27,MATCH(P32,'Scoring Method'!$A$25:$A$27,0)) | U32: =(INDEX('Scoring Method'!$B$30:$B$33,MATCH(Q32,'Scoring Method'!$A$30:$A$33,0))+INDEX('Scoring Method'!$B$36:$B$42,MATCH(R32,'Scoring Method'!$A$36:$A$42,0))+INDEX('Scoring Method'!$B$45:$B$47,MATCH(IF(S32=1,"1",IF(S32=2,"2","3+")),'Scoring Method'!$A$45:$A$47,0)))/90*100 | V32: =T32*U32/100 | X32: X (minimal hazard) | Y32: 25650 | AC32: 0.59 | AD32: ok | AE32: No building | AF32: =INDEX('Scoring Method'!$B$63:$B$71,MATCH(AE32,'Scoring Method'!$A$63:$A$71,0))+INDEX('Scoring Method'!$B$75:$B$79,MATCH("Ample >=15k",'Scoring Method'!$A$75:$A$79,0))+INDEX('Scoring Method'!$B$343:$B$347,MATCH(X32,'Scoring Method'!$A$343:$A$347,0))+INDEX('Scoring Method'!$B$25:$B$27,MATCH(P32,'Scoring Method'!$A$25:$A$27,0)) | AG32: =AF32*U32/100 | AH32: LINK-GIS + LoopNet | AI32: 39.07029 | AJ32: -84.50589 | AK32: 1.17 | AL32: 1.43 | AM32: 2.18 | AN32: 0.99 | AO32: Fringe 0.75-1.25mi | AP32: Lot / minimal bldg | AQ32: Ample >=15k | AS32: =ROUND(INDEX('Scoring Method'!$B$63:$B$70,MATCH(AE32,'Scoring Method'!$A$63:$A$70,0))*0.625+INDEX('Scoring Method'!$B$105:$B$113,MATCH(AP32,'Scoring Method'!$A$105:$A$113,0))+INDEX('Scoring Method'!$B$74:$B$78,MATCH(AQ32,'Scoring Method'!$A$74:$A$78,0))*0.6667+INDEX('Scoring Method'!$B$96:$B$101,MATCH(AO32,'Scoring Method'!$A$96:$A$101,0))+INDEX('Scoring Method'!$B$343:$B$347,MATCH(X32,'Scoring Method'!$A$343:$A$347,0))*0.3333+INDEX('Scoring Method'!$B$25:$B$27,MATCH(P32,'Scoring Method'!$A$25:$A$27,0))*0.3333,1) | AT32: =AS32*U32/100 | AU32: Eastside | AV32: 28 | AW32: ESTIMATED | AX32: High <35 | AY32: =ROUND(INDEX('Scoring Method'!$B$132:$B$140,MATCH(AE32,'Scoring Method'!$A$132:$A$140,0))+INDEX('Scoring Method'!$B$144:$B$152,MATCH(AP32,'Scoring Method'!$A$144:$A$152,0))+INDEX('Scoring Method'!$B$156:$B$160,MATCH(AQ32,'Scoring Method'!$A$156:$A$160,0))+INDEX('Scoring Method'!$B$164:$B$169,MATCH(AO32,'Scoring Method'!$A$164:$A$169,0))+INDEX('Scoring Method'!$B$173:$B$178,MATCH(AX32,'Scoring Method'!$A$173:$A$178,0))+INDEX('Scoring Method'!$B$349:$B$353,MATCH(X32,'Scoring Method'!$A$349:$A$353,0))+INDEX('Scoring Method'!$B$188:$B$190,MATCH(P32,'Scoring Method'!$A$188:$A$190,0)),1) | AZ32: =AY32*U32/100 | BA32: No chain signal | BB32: 1 | BC32: Right-sized 0.35-0.75 AC | BD32: 1 | BE32: =ROUND(INDEX('Scoring Method'!$B$268:$B$276,MATCH(AE32,'Scoring Method'!$A$268:$A$276,0))+INDEX('Scoring Method'!$B$280:$B$288,MATCH(AP32,'Scoring Method'!$A$280:$A$288,0))+INDEX('Scoring Method'!$B$292:$B$296,MATCH(AQ32,'Scoring Method'!$A$292:$A$296,0))+INDEX('Scoring Method'!$B$300:$B$305,MATCH(AO32,'Scoring Method'!$A$300:$A$305,0))+INDEX('Scoring Method'!$B$309:$B$314,MATCH(AX32,'Scoring Method'!$A$309:$A$314,0))+INDEX('Scoring Method'!$B$337:$B$341,MATCH(X32,'Scoring Method'!$A$337:$A$341,0))+INDEX('Scoring Method'!$B$324:$B$326,MATCH(P32,'Scoring Method'!$A$324:$A$326,0)),1) | BF32: =ROUND(INDEX('Scoring Method'!$B$268:$B$276,MATCH(AE32,'Scoring Method'!$A$268:$A$276,0))*BB32*BD32+INDEX('Scoring Method'!$B$280:$B$288,MATCH(AP32,'Scoring Method'!$A$280:$A$288,0))*BM32*BB32*BD32+INDEX('Scoring Method'!$B$292:$B$296,MATCH(AQ32,'Scoring Method'!$A$292:$A$296,0))*BD32+INDEX('Scoring Method'!$B$300:$B$305,MATCH(AO32,'Scoring Method'!$A$300:$A$305,0))*BM32*BB32+INDEX('Scoring Method'!$B$309:$B$314,MATCH(AX32,'Scoring Method'!$A$309:$A$314,0))+INDEX('Scoring Method'!$B$337:$B$341,MATCH(X32,'Scoring Method'!$A$337:$A$341,0))+INDEX('Scoring Method'!$B$324:$B$326,MATCH(P32,'Scoring Method'!$A$324:$A$326,0)),1) | BH32: SU | BI32: Semi-Urban Residential | BL32: SU corner unverified | BM32: =INDEX('Scoring Method'!$B$358:$B$363,MATCH(BL32,'Scoring Method'!$A$358:$A$363,0))
A33: 32 | B33: 095-00-00-001.12 | C33: RUSSELL ST | D33: JRW HOLDINGS LLC | E33: 1850 AUGUSTINE ST STE C | F33: COVINGTON | G33: KY | H33: PAVED LOT | I33: 22563 | J33: =I33/43560 | K33: 663.8 | L33: =I33/(K33^2) | M33: Ideal 18-32k | N33: D | O33: Regular .045-.055 | P33: Low | Q33: Local absentee | R33: Passive vehicle | S33: 3 | T33: =INDEX('Scoring Method'!$B$6:$B$9,MATCH(M33,'Scoring Method'!$A$6:$A$9,0))+INDEX('Scoring Method'!$B$12:$B$16,MATCH(N33,'Scoring Method'!$A$12:$A$16,0))+INDEX('Scoring Method'!$B$19:$B$22,MATCH(O33,'Scoring Method'!$A$19:$A$22,0))+INDEX('Scoring Method'!$B$25:$B$27,MATCH(P33,'Scoring Method'!$A$25:$A$27,0)) | U33: =(INDEX('Scoring Method'!$B$30:$B$33,MATCH(Q33,'Scoring Method'!$A$30:$A$33,0))+INDEX('Scoring Method'!$B$36:$B$42,MATCH(R33,'Scoring Method'!$A$36:$A$42,0))+INDEX('Scoring Method'!$B$45:$B$47,MATCH(IF(S33=1,"1",IF(S33=2,"2","3+")),'Scoring Method'!$A$45:$A$47,0)))/90*100 | V33: =T33*U33/100 | X33: Unknown | AH33: LINK-GIS only | AI33: 39.06806 | AJ33: -84.50824 | AK33: 1.24 | AL33: 1.57 | AM33: 2.32 | AN33: 1.11 | AO33: Fringe 0.75-1.25mi | AP33: Lot / minimal bldg | AU33: Levassor Park | AV33: 42 | AW33: ESTIMATED | AX33: Elevated 35-44 | BA33: No chain signal | BB33: 1 | BC33: Right-sized 0.35-0.75 AC | BD33: 1 | BH33: Not joined | BL33: Not joined | BM33: 1
A34: 33 | B34: 042-30-00-040.00 | C34: 3288 MADISON PIKE | D34: SCHLIPF DANIEL | E34: 3197 HIGH RIDGE DR | F34: TAYLOR MILL | G34: KY | H34: OTHER RETAIL | I34: 25418 | J34: =I34/43560 | K34: 827.5 | L34: =I34/(K34^2) | M34: Ideal 18-32k | N34: C | O34: Elongated .035-.045 | P34: Low | Q34: Out-of-city KY | R34: Individual | S34: 1 | T34: =INDEX('Scoring Method'!$B$6:$B$9,MATCH(M34,'Scoring Method'!$A$6:$A$9,0))+INDEX('Scoring Method'!$B$12:$B$16,MATCH(N34,'Scoring Method'!$A$12:$A$16,0))+INDEX('Scoring Method'!$B$19:$B$22,MATCH(O34,'Scoring Method'!$A$19:$A$22,0))+INDEX('Scoring Method'!$B$25:$B$27,MATCH(P34,'Scoring Method'!$A$25:$A$27,0)) | U34: =(INDEX('Scoring Method'!$B$30:$B$33,MATCH(Q34,'Scoring Method'!$A$30:$A$33,0))+INDEX('Scoring Method'!$B$36:$B$42,MATCH(R34,'Scoring Method'!$A$36:$A$42,0))+INDEX('Scoring Method'!$B$45:$B$47,MATCH(IF(S34=1,"1",IF(S34=2,"2","3+")),'Scoring Method'!$A$45:$A$47,0)))/90*100 | V34: =T34*U34/100 | W34: 4520 | X34: AE (1% annual) | Y34: 18325 | Z34: =W34/I34 | AA34: =MAX(0,(Y34-5000)/300) | AC34: 0.58 | AD34: ok | AE34: Large 4-6k | AF34: =INDEX('Scoring Method'!$B$63:$B$71,MATCH(AE34,'Scoring Method'!$A$63:$A$71,0))+INDEX('Scoring Method'!$B$75:$B$79,MATCH("Ample >=15k",'Scoring Method'!$A$75:$A$79,0))+INDEX('Scoring Method'!$B$343:$B$347,MATCH(X34,'Scoring Method'!$A$343:$A$347,0))+INDEX('Scoring Method'!$B$25:$B$27,MATCH(P34,'Scoring Method'!$A$25:$A$27,0)) | AG34: =AF34*U34/100 | AH34: LINK-GIS + LoopNet | AI34: 39.04228 | AJ34: -84.52533 | AK34: 2.94 | AL34: 3.48 | AM34: 4.15 | AN34: 2.94 | AO34: Distant 2-3mi | AP34: Retail shell | AQ34: Ample >=15k | AS34: =ROUND(INDEX('Scoring Method'!$B$63:$B$70,MATCH(AE34,'Scoring Method'!$A$63:$A$70,0))*0.625+INDEX('Scoring Method'!$B$105:$B$113,MATCH(AP34,'Scoring Method'!$A$105:$A$113,0))+INDEX('Scoring Method'!$B$74:$B$78,MATCH(AQ34,'Scoring Method'!$A$74:$A$78,0))*0.6667+INDEX('Scoring Method'!$B$96:$B$101,MATCH(AO34,'Scoring Method'!$A$96:$A$101,0))+INDEX('Scoring Method'!$B$343:$B$347,MATCH(X34,'Scoring Method'!$A$343:$A$347,0))*0.3333+INDEX('Scoring Method'!$B$25:$B$27,MATCH(P34,'Scoring Method'!$A$25:$A$27,0))*0.3333,1) | AT34: =AS34*U34/100 | AU34: Rittes East / Winston Park | AV34: 82 | AW34: Sourced | AX34: Very safe 80+ | AY34: =ROUND(INDEX('Scoring Method'!$B$132:$B$140,MATCH(AE34,'Scoring Method'!$A$132:$A$140,0))+INDEX('Scoring Method'!$B$144:$B$152,MATCH(AP34,'Scoring Method'!$A$144:$A$152,0))+INDEX('Scoring Method'!$B$156:$B$160,MATCH(AQ34,'Scoring Method'!$A$156:$A$160,0))+INDEX('Scoring Method'!$B$164:$B$169,MATCH(AO34,'Scoring Method'!$A$164:$A$169,0))+INDEX('Scoring Method'!$B$173:$B$178,MATCH(AX34,'Scoring Method'!$A$173:$A$178,0))+INDEX('Scoring Method'!$B$349:$B$353,MATCH(X34,'Scoring Method'!$A$349:$A$353,0))+INDEX('Scoring Method'!$B$188:$B$190,MATCH(P34,'Scoring Method'!$A$188:$A$190,0)),1) | AZ34: =AY34*U34/100 | BA34: No chain signal | BB34: 1 | BC34: Right-sized 0.35-0.75 AC | BD34: 1 | BE34: =ROUND(INDEX('Scoring Method'!$B$268:$B$276,MATCH(AE34,'Scoring Method'!$A$268:$A$276,0))+INDEX('Scoring Method'!$B$280:$B$288,MATCH(AP34,'Scoring Method'!$A$280:$A$288,0))+INDEX('Scoring Method'!$B$292:$B$296,MATCH(AQ34,'Scoring Method'!$A$292:$A$296,0))+INDEX('Scoring Method'!$B$300:$B$305,MATCH(AO34,'Scoring Method'!$A$300:$A$305,0))+INDEX('Scoring Method'!$B$309:$B$314,MATCH(AX34,'Scoring Method'!$A$309:$A$314,0))+INDEX('Scoring Method'!$B$337:$B$341,MATCH(X34,'Scoring Method'!$A$337:$A$341,0))+INDEX('Scoring Method'!$B$324:$B$326,MATCH(P34,'Scoring Method'!$A$324:$A$326,0)),1) | BF34: =ROUND(INDEX('Scoring Method'!$B$268:$B$276,MATCH(AE34,'Scoring Method'!$A$268:$A$276,0))*BB34*BD34+INDEX('Scoring Method'!$B$280:$B$288,MATCH(AP34,'Scoring Method'!$A$280:$A$288,0))*BM34*BB34*BD34+INDEX('Scoring Method'!$B$292:$B$296,MATCH(AQ34,'Scoring Method'!$A$292:$A$296,0))*BD34+INDEX('Scoring Method'!$B$300:$B$305,MATCH(AO34,'Scoring Method'!$A$300:$A$305,0))*BM34*BB34+INDEX('Scoring Method'!$B$309:$B$314,MATCH(AX34,'Scoring Method'!$A$309:$A$314,0))+INDEX('Scoring Method'!$B$337:$B$341,MATCH(X34,'Scoring Method'!$A$337:$A$341,0))+INDEX('Scoring Method'!$B$324:$B$326,MATCH(P34,'Scoring Method'!$A$324:$A$326,0)),1) | BG34: Fits (~$4,143/mo) | BH34: AUC | BI34: Auto-Urban Commercial | BL34: Bar permitted | BM34: =INDEX('Scoring Method'!$B$358:$B$363,MATCH(BL34,'Scoring Method'!$A$358:$A$363,0))
A35: 34 | B35: 040-41-11-024.00 | C35: 605 WESTERN AVE | D35: CLIFFORD RIVERVIEW | E35: 3091 LITTLE DRY RUN RD | F35: CINCINNATI | G35: OH | H35: MISCELLANEOUS IMPROVEMENT | I35: 20087 | J35: =I35/43560 | K35: 697.1 | L35: =I35/(K35^2) | M35: Ideal 18-32k | N35: D | O35: Elongated .035-.045 | P35: Low | Q35: Out-of-state | R35: Individual | S35: 1 | T35: =INDEX('Scoring Method'!$B$6:$B$9,MATCH(M35,'Scoring Method'!$A$6:$A$9,0))+INDEX('Scoring Method'!$B$12:$B$16,MATCH(N35,'Scoring Method'!$A$12:$A$16,0))+INDEX('Scoring Method'!$B$19:$B$22,MATCH(O35,'Scoring Method'!$A$19:$A$22,0))+INDEX('Scoring Method'!$B$25:$B$27,MATCH(P35,'Scoring Method'!$A$25:$A$27,0)) | U35: =(INDEX('Scoring Method'!$B$30:$B$33,MATCH(Q35,'Scoring Method'!$A$30:$A$33,0))+INDEX('Scoring Method'!$B$36:$B$42,MATCH(R35,'Scoring Method'!$A$36:$A$42,0))+INDEX('Scoring Method'!$B$45:$B$47,MATCH(IF(S35=1,"1",IF(S35=2,"2","3+")),'Scoring Method'!$A$45:$A$47,0)))/90*100 | V35: =T35*U35/100 | W35: 812 | X35: X (minimal hazard) | Y35: 18550 | AA35: =MAX(0,(Y35-5000)/300) | AE35: Too small <1.2k | AF35: =INDEX('Scoring Method'!$B$63:$B$71,MATCH(AE35,'Scoring Method'!$A$63:$A$71,0))+INDEX('Scoring Method'!$B$75:$B$79,MATCH("Ample >=15k",'Scoring Method'!$A$75:$A$79,0))+INDEX('Scoring Method'!$B$343:$B$347,MATCH(X35,'Scoring Method'!$A$343:$A$347,0))+INDEX('Scoring Method'!$B$25:$B$27,MATCH(P35,'Scoring Method'!$A$25:$A$27,0)) | AG35: =AF35*U35/100 | AH35: LINK-GIS (no LoopNet record) | AI35: 39.08379 | AJ35: -84.52486 | AK35: 0.38 | AL35: 1.01 | AM35: 1.39 | AN35: 0.38 | AO35: Near 0.35-0.75mi | AP35: Lot / minimal bldg | AQ35: Ample >=15k | AS35: =ROUND(INDEX('Scoring Method'!$B$63:$B$70,MATCH(AE35,'Scoring Method'!$A$63:$A$70,0))*0.625+INDEX('Scoring Method'!$B$105:$B$113,MATCH(AP35,'Scoring Method'!$A$105:$A$113,0))+INDEX('Scoring Method'!$B$74:$B$78,MATCH(AQ35,'Scoring Method'!$A$74:$A$78,0))*0.6667+INDEX('Scoring Method'!$B$96:$B$101,MATCH(AO35,'Scoring Method'!$A$96:$A$101,0))+INDEX('Scoring Method'!$B$343:$B$347,MATCH(X35,'Scoring Method'!$A$343:$A$347,0))*0.3333+INDEX('Scoring Method'!$B$25:$B$27,MATCH(P35,'Scoring Method'!$A$25:$A$27,0))*0.3333,1) | AT35: =AS35*U35/100 | AU35: Kenton Hills | AV35: 85 | AW35: Sourced | AX35: Very safe 80+ | AY35: =ROUND(INDEX('Scoring Method'!$B$132:$B$140,MATCH(AE35,'Scoring Method'!$A$132:$A$140,0))+INDEX('Scoring Method'!$B$144:$B$152,MATCH(AP35,'Scoring Method'!$A$144:$A$152,0))+INDEX('Scoring Method'!$B$156:$B$160,MATCH(AQ35,'Scoring Method'!$A$156:$A$160,0))+INDEX('Scoring Method'!$B$164:$B$169,MATCH(AO35,'Scoring Method'!$A$164:$A$169,0))+INDEX('Scoring Method'!$B$173:$B$178,MATCH(AX35,'Scoring Method'!$A$173:$A$178,0))+INDEX('Scoring Method'!$B$349:$B$353,MATCH(X35,'Scoring Method'!$A$349:$A$353,0))+INDEX('Scoring Method'!$B$188:$B$190,MATCH(P35,'Scoring Method'!$A$188:$A$190,0)),1) | AZ35: =AY35*U35/100 | BA35: No chain signal | BB35: 1 | BC35: Right-sized 0.35-0.75 AC | BD35: 1 | BE35: =ROUND(INDEX('Scoring Method'!$B$268:$B$276,MATCH(AE35,'Scoring Method'!$A$268:$A$276,0))+INDEX('Scoring Method'!$B$280:$B$288,MATCH(AP35,'Scoring Method'!$A$280:$A$288,0))+INDEX('Scoring Method'!$B$292:$B$296,MATCH(AQ35,'Scoring Method'!$A$292:$A$296,0))+INDEX('Scoring Method'!$B$300:$B$305,MATCH(AO35,'Scoring Method'!$A$300:$A$305,0))+INDEX('Scoring Method'!$B$309:$B$314,MATCH(AX35,'Scoring Method'!$A$309:$A$314,0))+INDEX('Scoring Method'!$B$337:$B$341,MATCH(X35,'Scoring Method'!$A$337:$A$341,0))+INDEX('Scoring Method'!$B$324:$B$326,MATCH(P35,'Scoring Method'!$A$324:$A$326,0)),1) | BF35: =ROUND(INDEX('Scoring Method'!$B$268:$B$276,MATCH(AE35,'Scoring Method'!$A$268:$A$276,0))*BB35*BD35+INDEX('Scoring Method'!$B$280:$B$288,MATCH(AP35,'Scoring Method'!$A$280:$A$288,0))*BM35*BB35*BD35+INDEX('Scoring Method'!$B$292:$B$296,MATCH(AQ35,'Scoring Method'!$A$292:$A$296,0))*BD35+INDEX('Scoring Method'!$B$300:$B$305,MATCH(AO35,'Scoring Method'!$A$300:$A$305,0))*BM35*BB35+INDEX('Scoring Method'!$B$309:$B$314,MATCH(AX35,'Scoring Method'!$A$309:$A$314,0))+INDEX('Scoring Method'!$B$337:$B$341,MATCH(X35,'Scoring Method'!$A$337:$A$341,0))+INDEX('Scoring Method'!$B$324:$B$326,MATCH(P35,'Scoring Method'!$A$324:$A$326,0)),1) | BG35: Fits (~$744/mo) | BH35: SU | BI35: Semi-Urban Residential | BL35: SU corner unverified | BM35: =INDEX('Scoring Method'!$B$358:$B$363,MATCH(BL35,'Scoring Method'!$A$358:$A$363,0))
A36: 35 | B36: 054-24-04-002.00 | C36: 25 W 11TH ST | D36: BATSHOUN PROPERTIES LLC | E36: 20 W 11TH ST STE 100 | F36: COVINGTON | G36: KY | H36: PAVED LOT | I36: 21544 | J36: =I36/43560 | K36: 606.8 | L36: =I36/(K36^2) | M36: Ideal 18-32k | N36: D | O36: Compact >=.055 | P36: Low | Q36: Local absentee | R36: Passive vehicle | S36: 2 | T36: =INDEX('Scoring Method'!$B$6:$B$9,MATCH(M36,'Scoring Method'!$A$6:$A$9,0))+INDEX('Scoring Method'!$B$12:$B$16,MATCH(N36,'Scoring Method'!$A$12:$A$16,0))+INDEX('Scoring Method'!$B$19:$B$22,MATCH(O36,'Scoring Method'!$A$19:$A$22,0))+INDEX('Scoring Method'!$B$25:$B$27,MATCH(P36,'Scoring Method'!$A$25:$A$27,0)) | U36: =(INDEX('Scoring Method'!$B$30:$B$33,MATCH(Q36,'Scoring Method'!$A$30:$A$33,0))+INDEX('Scoring Method'!$B$36:$B$42,MATCH(R36,'Scoring Method'!$A$36:$A$42,0))+INDEX('Scoring Method'!$B$45:$B$47,MATCH(IF(S36=1,"1",IF(S36=2,"2","3+")),'Scoring Method'!$A$45:$A$47,0)))/90*100 | V36: =T36*U36/100 | X36: X (minimal hazard) | Y36: 21250 | AC36: 0.49 | AD36: ok | AE36: No building | AF36: =INDEX('Scoring Method'!$B$63:$B$71,MATCH(AE36,'Scoring Method'!$A$63:$A$71,0))+INDEX('Scoring Method'!$B$75:$B$79,MATCH("Ample >=15k",'Scoring Method'!$A$75:$A$79,0))+INDEX('Scoring Method'!$B$343:$B$347,MATCH(X36,'Scoring Method'!$A$343:$A$347,0))+INDEX('Scoring Method'!$B$25:$B$27,MATCH(P36,'Scoring Method'!$A$25:$A$27,0)) | AG36: =AF36*U36/100 | AH36: LINK-GIS + LoopNet | AI36: 39.07844 | AJ36: -84.50986 | AK36: 0.59 | AL36: 0.86 | AM36: 1.6 | AN36: 0.39 | AO36: Near 0.35-0.75mi | AP36: Lot / minimal bldg | AQ36: Ample >=15k | AS36: =ROUND(INDEX('Scoring Method'!$B$63:$B$70,MATCH(AE36,'Scoring Method'!$A$63:$A$70,0))*0.625+INDEX('Scoring Method'!$B$105:$B$113,MATCH(AP36,'Scoring Method'!$A$105:$A$113,0))+INDEX('Scoring Method'!$B$74:$B$78,MATCH(AQ36,'Scoring Method'!$A$74:$A$78,0))*0.6667+INDEX('Scoring Method'!$B$96:$B$101,MATCH(AO36,'Scoring Method'!$A$96:$A$101,0))+INDEX('Scoring Method'!$B$343:$B$347,MATCH(X36,'Scoring Method'!$A$343:$A$347,0))*0.3333+INDEX('Scoring Method'!$B$25:$B$27,MATCH(P36,'Scoring Method'!$A$25:$A$27,0))*0.3333,1) | AT36: =AS36*U36/100 | AU36: Eastside | AV36: 28 | AW36: ESTIMATED | AX36: High <35 | AY36: =ROUND(INDEX('Scoring Method'!$B$132:$B$140,MATCH(AE36,'Scoring Method'!$A$132:$A$140,0))+INDEX('Scoring Method'!$B$144:$B$152,MATCH(AP36,'Scoring Method'!$A$144:$A$152,0))+INDEX('Scoring Method'!$B$156:$B$160,MATCH(AQ36,'Scoring Method'!$A$156:$A$160,0))+INDEX('Scoring Method'!$B$164:$B$169,MATCH(AO36,'Scoring Method'!$A$164:$A$169,0))+INDEX('Scoring Method'!$B$173:$B$178,MATCH(AX36,'Scoring Method'!$A$173:$A$178,0))+INDEX('Scoring Method'!$B$349:$B$353,MATCH(X36,'Scoring Method'!$A$349:$A$353,0))+INDEX('Scoring Method'!$B$188:$B$190,MATCH(P36,'Scoring Method'!$A$188:$A$190,0)),1) | AZ36: =AY36*U36/100 | BA36: No chain signal | BB36: 1 | BC36: Right-sized 0.35-0.75 AC | BD36: 1 | BE36: =ROUND(INDEX('Scoring Method'!$B$268:$B$276,MATCH(AE36,'Scoring Method'!$A$268:$A$276,0))+INDEX('Scoring Method'!$B$280:$B$288,MATCH(AP36,'Scoring Method'!$A$280:$A$288,0))+INDEX('Scoring Method'!$B$292:$B$296,MATCH(AQ36,'Scoring Method'!$A$292:$A$296,0))+INDEX('Scoring Method'!$B$300:$B$305,MATCH(AO36,'Scoring Method'!$A$300:$A$305,0))+INDEX('Scoring Method'!$B$309:$B$314,MATCH(AX36,'Scoring Method'!$A$309:$A$314,0))+INDEX('Scoring Method'!$B$337:$B$341,MATCH(X36,'Scoring Method'!$A$337:$A$341,0))+INDEX('Scoring Method'!$B$324:$B$326,MATCH(P36,'Scoring Method'!$A$324:$A$326,0)),1) | BF36: =ROUND(INDEX('Scoring Method'!$B$268:$B$276,MATCH(AE36,'Scoring Method'!$A$268:$A$276,0))*BB36*BD36+INDEX('Scoring Method'!$B$280:$B$288,MATCH(AP36,'Scoring Method'!$A$280:$A$288,0))*BM36*BB36*BD36+INDEX('Scoring Method'!$B$292:$B$296,MATCH(AQ36,'Scoring Method'!$A$292:$A$296,0))*BD36+INDEX('Scoring Method'!$B$300:$B$305,MATCH(AO36,'Scoring Method'!$A$300:$A$305,0))*BM36*BB36+INDEX('Scoring Method'!$B$309:$B$314,MATCH(AX36,'Scoring Method'!$A$309:$A$314,0))+INDEX('Scoring Method'!$B$337:$B$341,MATCH(X36,'Scoring Method'!$A$337:$A$341,0))+INDEX('Scoring Method'!$B$324:$B$326,MATCH(P36,'Scoring Method'!$A$324:$A$326,0)),1) | BH36: DTC (TS) | BI36: Downtown Core | BK36: Yes | BL36: Bar permitted | BM36: =INDEX('Scoring Method'!$B$358:$B$363,MATCH(BL36,'Scoring Method'!$A$358:$A$363,0))
A37: 36 | B37: 044-00-01-001.00 | C37: 3954 DECKER CRANE LN | D37: VEATCH INDUSTRIAL PARK LLC | E37: PO BOX 73213 | F37: BELLEVUE | G37: KY | H37: WAREHOUSE 1-20000 SQ FT | I37: 41965 | J37: =I37/43560 | K37: 896.4 | L37: =I37/(K37^2) | M37: Near 14-18k/32-45k | N37: A | O37: Regular .045-.055 | P37: Low | Q37: Out-of-city KY | R37: Operating entity | S37: 2 | T37: =INDEX('Scoring Method'!$B$6:$B$9,MATCH(M37,'Scoring Method'!$A$6:$A$9,0))+INDEX('Scoring Method'!$B$12:$B$16,MATCH(N37,'Scoring Method'!$A$12:$A$16,0))+INDEX('Scoring Method'!$B$19:$B$22,MATCH(O37,'Scoring Method'!$A$19:$A$22,0))+INDEX('Scoring Method'!$B$25:$B$27,MATCH(P37,'Scoring Method'!$A$25:$A$27,0)) | U37: =(INDEX('Scoring Method'!$B$30:$B$33,MATCH(Q37,'Scoring Method'!$A$30:$A$33,0))+INDEX('Scoring Method'!$B$36:$B$42,MATCH(R37,'Scoring Method'!$A$36:$A$42,0))+INDEX('Scoring Method'!$B$45:$B$47,MATCH(IF(S37=1,"1",IF(S37=2,"2","3+")),'Scoring Method'!$A$45:$A$47,0)))/90*100 | V37: =T37*U37/100 | W37: 9250 | X37: X (minimal hazard) | Y37: 29975 | Z37: =W37/I37 | AA37: =MAX(0,(Y37-5000)/300) | AC37: 0.96 | AD37: ok | AE37: Oversize 6-12k | AF37: =INDEX('Scoring Method'!$B$63:$B$71,MATCH(AE37,'Scoring Method'!$A$63:$A$71,0))+INDEX('Scoring Method'!$B$75:$B$79,MATCH("Ample >=15k",'Scoring Method'!$A$75:$A$79,0))+INDEX('Scoring Method'!$B$343:$B$347,MATCH(X37,'Scoring Method'!$A$343:$A$347,0))+INDEX('Scoring Method'!$B$25:$B$27,MATCH(P37,'Scoring Method'!$A$25:$A$27,0)) | AG37: =AF37*U37/100 | AH37: LINK-GIS + LoopNet | AI37: 39.00347 | AJ37: -84.53375 | AK37: 5.66 | AL37: 6.19 | AM37: 6.87 | AN37: 5.66 | AO37: Remote >3mi | AP37: Open span | AQ37: Ample >=15k | AS37: =ROUND(INDEX('Scoring Method'!$B$63:$B$70,MATCH(AE37,'Scoring Method'!$A$63:$A$70,0))*0.625+INDEX('Scoring Method'!$B$105:$B$113,MATCH(AP37,'Scoring Method'!$A$105:$A$113,0))+INDEX('Scoring Method'!$B$74:$B$78,MATCH(AQ37,'Scoring Method'!$A$74:$A$78,0))*0.6667+INDEX('Scoring Method'!$B$96:$B$101,MATCH(AO37,'Scoring Method'!$A$96:$A$101,0))+INDEX('Scoring Method'!$B$343:$B$347,MATCH(X37,'Scoring Method'!$A$343:$A$347,0))*0.3333+INDEX('Scoring Method'!$B$25:$B$27,MATCH(P37,'Scoring Method'!$A$25:$A$27,0))*0.3333,1) | AT37: =AS37*U37/100 | AU37: South Covington | AV37: 88 | AW37: Sourced | AX37: Very safe 80+ | AY37: =ROUND(INDEX('Scoring Method'!$B$132:$B$140,MATCH(AE37,'Scoring Method'!$A$132:$A$140,0))+INDEX('Scoring Method'!$B$144:$B$152,MATCH(AP37,'Scoring Method'!$A$144:$A$152,0))+INDEX('Scoring Method'!$B$156:$B$160,MATCH(AQ37,'Scoring Method'!$A$156:$A$160,0))+INDEX('Scoring Method'!$B$164:$B$169,MATCH(AO37,'Scoring Method'!$A$164:$A$169,0))+INDEX('Scoring Method'!$B$173:$B$178,MATCH(AX37,'Scoring Method'!$A$173:$A$178,0))+INDEX('Scoring Method'!$B$349:$B$353,MATCH(X37,'Scoring Method'!$A$349:$A$353,0))+INDEX('Scoring Method'!$B$188:$B$190,MATCH(P37,'Scoring Method'!$A$188:$A$190,0)),1) | AZ37: =AY37*U37/100 | BA37: No chain signal | BB37: 1 | BC37: Large 0.75-1.25 AC | BD37: 0.9 | BE37: =ROUND(INDEX('Scoring Method'!$B$268:$B$276,MATCH(AE37,'Scoring Method'!$A$268:$A$276,0))+INDEX('Scoring Method'!$B$280:$B$288,MATCH(AP37,'Scoring Method'!$A$280:$A$288,0))+INDEX('Scoring Method'!$B$292:$B$296,MATCH(AQ37,'Scoring Method'!$A$292:$A$296,0))+INDEX('Scoring Method'!$B$300:$B$305,MATCH(AO37,'Scoring Method'!$A$300:$A$305,0))+INDEX('Scoring Method'!$B$309:$B$314,MATCH(AX37,'Scoring Method'!$A$309:$A$314,0))+INDEX('Scoring Method'!$B$337:$B$341,MATCH(X37,'Scoring Method'!$A$337:$A$341,0))+INDEX('Scoring Method'!$B$324:$B$326,MATCH(P37,'Scoring Method'!$A$324:$A$326,0)),1) | BF37: =ROUND(INDEX('Scoring Method'!$B$268:$B$276,MATCH(AE37,'Scoring Method'!$A$268:$A$276,0))*BB37*BD37+INDEX('Scoring Method'!$B$280:$B$288,MATCH(AP37,'Scoring Method'!$A$280:$A$288,0))*BM37*BB37*BD37+INDEX('Scoring Method'!$B$292:$B$296,MATCH(AQ37,'Scoring Method'!$A$292:$A$296,0))*BD37+INDEX('Scoring Method'!$B$300:$B$305,MATCH(AO37,'Scoring Method'!$A$300:$A$305,0))*BM37*BB37+INDEX('Scoring Method'!$B$309:$B$314,MATCH(AX37,'Scoring Method'!$A$309:$A$314,0))+INDEX('Scoring Method'!$B$337:$B$341,MATCH(X37,'Scoring Method'!$A$337:$A$341,0))+INDEX('Scoring Method'!$B$324:$B$326,MATCH(P37,'Scoring Method'!$A$324:$A$326,0)),1) | BG37: Fits (~$8,479/mo) | BH37: SI | BI37: Suburban Industrial | BL37: Bar permitted | BM37: =INDEX('Scoring Method'!$B$358:$B$363,MATCH(BL37,'Scoring Method'!$A$358:$A$363,0))
A38: 37 | B38: 055-32-03-003.00 | C38: 217 E 19TH ST | D38: BOONE MICHAEL P & DANIEL T | E38: 221 E 19TH ST | F38: COVINGTON | G38: KY | H38: SMALL SHOP | I38: 17240 | J38: =I38/43560 | K38: 564.3 | L38: =I38/(K38^2) | M38: Near 14-18k/32-45k | N38: A | O38: Regular .045-.055 | P38: Low | Q38: Local absentee | R38: Individual | S38: 1 | T38: =INDEX('Scoring Method'!$B$6:$B$9,MATCH(M38,'Scoring Method'!$A$6:$A$9,0))+INDEX('Scoring Method'!$B$12:$B$16,MATCH(N38,'Scoring Method'!$A$12:$A$16,0))+INDEX('Scoring Method'!$B$19:$B$22,MATCH(O38,'Scoring Method'!$A$19:$A$22,0))+INDEX('Scoring Method'!$B$25:$B$27,MATCH(P38,'Scoring Method'!$A$25:$A$27,0)) | U38: =(INDEX('Scoring Method'!$B$30:$B$33,MATCH(Q38,'Scoring Method'!$A$30:$A$33,0))+INDEX('Scoring Method'!$B$36:$B$42,MATCH(R38,'Scoring Method'!$A$36:$A$42,0))+INDEX('Scoring Method'!$B$45:$B$47,MATCH(IF(S38=1,"1",IF(S38=2,"2","3+")),'Scoring Method'!$A$45:$A$47,0)))/90*100 | V38: =T38*U38/100 | W38: 5991 | X38: X (minimal hazard) | Y38: 7225 | Z38: =W38/I38 | AA38: =MAX(0,(Y38-5000)/300) | AC38: 0.4 | AD38: ok | AE38: Large 4-6k | AF38: =INDEX('Scoring Method'!$B$63:$B$71,MATCH(AE38,'Scoring Method'!$A$63:$A$71,0))+INDEX('Scoring Method'!$B$75:$B$79,MATCH("Adequate 5-8k",'Scoring Method'!$A$75:$A$79,0))+INDEX('Scoring Method'!$B$343:$B$347,MATCH(X38,'Scoring Method'!$A$343:$A$347,0))+INDEX('Scoring Method'!$B$25:$B$27,MATCH(P38,'Scoring Method'!$A$25:$A$27,0)) | AG38: =AF38*U38/100 | AH38: LINK-GIS + LoopNet | AI38: 39.0683 | AJ38: -84.50228 | AK38: 1.39 | AL38: 1.59 | AM38: 2.36 | AN38: 1.18 | AO38: Fringe 0.75-1.25mi | AP38: Open span | AQ38: Adequate 5-8k | AS38: =ROUND(INDEX('Scoring Method'!$B$63:$B$70,MATCH(AE38,'Scoring Method'!$A$63:$A$70,0))*0.625+INDEX('Scoring Method'!$B$105:$B$113,MATCH(AP38,'Scoring Method'!$A$105:$A$113,0))+INDEX('Scoring Method'!$B$74:$B$78,MATCH(AQ38,'Scoring Method'!$A$74:$A$78,0))*0.6667+INDEX('Scoring Method'!$B$96:$B$101,MATCH(AO38,'Scoring Method'!$A$96:$A$101,0))+INDEX('Scoring Method'!$B$343:$B$347,MATCH(X38,'Scoring Method'!$A$343:$A$347,0))*0.3333+INDEX('Scoring Method'!$B$25:$B$27,MATCH(P38,'Scoring Method'!$A$25:$A$27,0))*0.3333,1) | AT38: =AS38*U38/100 | AU38: Levassor Park | AV38: 42 | AW38: ESTIMATED | AX38: Elevated 35-44 | AY38: =ROUND(INDEX('Scoring Method'!$B$132:$B$140,MATCH(AE38,'Scoring Method'!$A$132:$A$140,0))+INDEX('Scoring Method'!$B$144:$B$152,MATCH(AP38,'Scoring Method'!$A$144:$A$152,0))+INDEX('Scoring Method'!$B$156:$B$160,MATCH(AQ38,'Scoring Method'!$A$156:$A$160,0))+INDEX('Scoring Method'!$B$164:$B$169,MATCH(AO38,'Scoring Method'!$A$164:$A$169,0))+INDEX('Scoring Method'!$B$173:$B$178,MATCH(AX38,'Scoring Method'!$A$173:$A$178,0))+INDEX('Scoring Method'!$B$349:$B$353,MATCH(X38,'Scoring Method'!$A$349:$A$353,0))+INDEX('Scoring Method'!$B$188:$B$190,MATCH(P38,'Scoring Method'!$A$188:$A$190,0)),1) | AZ38: =AY38*U38/100 | BA38: No chain signal | BB38: 1 | BC38: Right-sized 0.35-0.75 AC | BD38: 1 | BE38: =ROUND(INDEX('Scoring Method'!$B$268:$B$276,MATCH(AE38,'Scoring Method'!$A$268:$A$276,0))+INDEX('Scoring Method'!$B$280:$B$288,MATCH(AP38,'Scoring Method'!$A$280:$A$288,0))+INDEX('Scoring Method'!$B$292:$B$296,MATCH(AQ38,'Scoring Method'!$A$292:$A$296,0))+INDEX('Scoring Method'!$B$300:$B$305,MATCH(AO38,'Scoring Method'!$A$300:$A$305,0))+INDEX('Scoring Method'!$B$309:$B$314,MATCH(AX38,'Scoring Method'!$A$309:$A$314,0))+INDEX('Scoring Method'!$B$337:$B$341,MATCH(X38,'Scoring Method'!$A$337:$A$341,0))+INDEX('Scoring Method'!$B$324:$B$326,MATCH(P38,'Scoring Method'!$A$324:$A$326,0)),1) | BF38: =ROUND(INDEX('Scoring Method'!$B$268:$B$276,MATCH(AE38,'Scoring Method'!$A$268:$A$276,0))*BB38*BD38+INDEX('Scoring Method'!$B$280:$B$288,MATCH(AP38,'Scoring Method'!$A$280:$A$288,0))*BM38*BB38*BD38+INDEX('Scoring Method'!$B$292:$B$296,MATCH(AQ38,'Scoring Method'!$A$292:$A$296,0))*BD38+INDEX('Scoring Method'!$B$300:$B$305,MATCH(AO38,'Scoring Method'!$A$300:$A$305,0))*BM38*BB38+INDEX('Scoring Method'!$B$309:$B$314,MATCH(AX38,'Scoring Method'!$A$309:$A$314,0))+INDEX('Scoring Method'!$B$337:$B$341,MATCH(X38,'Scoring Method'!$A$337:$A$341,0))+INDEX('Scoring Method'!$B$324:$B$326,MATCH(P38,'Scoring Method'!$A$324:$A$326,0)),1) | BG38: Fits (~$5,492/mo) | BH38: SU | BI38: Semi-Urban Residential | BL38: SU corner unverified | BM38: =INDEX('Scoring Method'!$B$358:$B$363,MATCH(BL38,'Scoring Method'!$A$358:$A$363,0))
A39: 38 | B39: 055-13-10-001.00 | C39: 1602 MADISON AVE | D39: COVINGTON PLAZA HOLDING LLC | E39: 855 MAN O WAR BLVD | F39: UNION | G39: KY | H39: OTHER RETAIL | I39: 21895 | J39: =I39/43560 | K39: 620.8 | L39: =I39/(K39^2) | M39: Ideal 18-32k | N39: C | O39: Compact >=.055 | P39: Low | Q39: Out-of-city KY | R39: Operating entity | S39: 2 | T39: =INDEX('Scoring Method'!$B$6:$B$9,MATCH(M39,'Scoring Method'!$A$6:$A$9,0))+INDEX('Scoring Method'!$B$12:$B$16,MATCH(N39,'Scoring Method'!$A$12:$A$16,0))+INDEX('Scoring Method'!$B$19:$B$22,MATCH(O39,'Scoring Method'!$A$19:$A$22,0))+INDEX('Scoring Method'!$B$25:$B$27,MATCH(P39,'Scoring Method'!$A$25:$A$27,0)) | U39: =(INDEX('Scoring Method'!$B$30:$B$33,MATCH(Q39,'Scoring Method'!$A$30:$A$33,0))+INDEX('Scoring Method'!$B$36:$B$42,MATCH(R39,'Scoring Method'!$A$36:$A$42,0))+INDEX('Scoring Method'!$B$45:$B$47,MATCH(IF(S39=1,"1",IF(S39=2,"2","3+")),'Scoring Method'!$A$45:$A$47,0)))/90*100 | V39: =T39*U39/100 | W39: 5092 | X39: X (minimal hazard) | Y39: 16525 | AA39: =MAX(0,(Y39-5000)/300) | AE39: Large 4-6k | AF39: =INDEX('Scoring Method'!$B$63:$B$71,MATCH(AE39,'Scoring Method'!$A$63:$A$71,0))+INDEX('Scoring Method'!$B$75:$B$79,MATCH("Ample >=15k",'Scoring Method'!$A$75:$A$79,0))+INDEX('Scoring Method'!$B$343:$B$347,MATCH(X39,'Scoring Method'!$A$343:$A$347,0))+INDEX('Scoring Method'!$B$25:$B$27,MATCH(P39,'Scoring Method'!$A$25:$A$27,0)) | AG39: =AF39*U39/100 | AH39: LINK-GIS + LoopNet (2026-08-02) | AI39: 39.07152 | AJ39: -84.50656 | AK39: 1.08 | AL39: 1.34 | AM39: 2.09 | AN39: 0.89 | AO39: Fringe 0.75-1.25mi | AP39: Retail shell | AQ39: Ample >=15k | AS39: =ROUND(INDEX('Scoring Method'!$B$63:$B$70,MATCH(AE39,'Scoring Method'!$A$63:$A$70,0))*0.625+INDEX('Scoring Method'!$B$105:$B$113,MATCH(AP39,'Scoring Method'!$A$105:$A$113,0))+INDEX('Scoring Method'!$B$74:$B$78,MATCH(AQ39,'Scoring Method'!$A$74:$A$78,0))*0.6667+INDEX('Scoring Method'!$B$96:$B$101,MATCH(AO39,'Scoring Method'!$A$96:$A$101,0))+INDEX('Scoring Method'!$B$343:$B$347,MATCH(X39,'Scoring Method'!$A$343:$A$347,0))*0.3333+INDEX('Scoring Method'!$B$25:$B$27,MATCH(P39,'Scoring Method'!$A$25:$A$27,0))*0.3333,1) | AT39: =AS39*U39/100 | AU39: Eastside | AV39: 28 | AW39: ESTIMATED | AX39: High <35 | AY39: =ROUND(INDEX('Scoring Method'!$B$132:$B$140,MATCH(AE39,'Scoring Method'!$A$132:$A$140,0))+INDEX('Scoring Method'!$B$144:$B$152,MATCH(AP39,'Scoring Method'!$A$144:$A$152,0))+INDEX('Scoring Method'!$B$156:$B$160,MATCH(AQ39,'Scoring Method'!$A$156:$A$160,0))+INDEX('Scoring Method'!$B$164:$B$169,MATCH(AO39,'Scoring Method'!$A$164:$A$169,0))+INDEX('Scoring Method'!$B$173:$B$178,MATCH(AX39,'Scoring Method'!$A$173:$A$178,0))+INDEX('Scoring Method'!$B$349:$B$353,MATCH(X39,'Scoring Method'!$A$349:$A$353,0))+INDEX('Scoring Method'!$B$188:$B$190,MATCH(P39,'Scoring Method'!$A$188:$A$190,0)),1) | AZ39: =AY39*U39/100 | BA39: No chain signal | BB39: 1 | BC39: Right-sized 0.35-0.75 AC | BD39: 1 | BE39: =ROUND(INDEX('Scoring Method'!$B$268:$B$276,MATCH(AE39,'Scoring Method'!$A$268:$A$276,0))+INDEX('Scoring Method'!$B$280:$B$288,MATCH(AP39,'Scoring Method'!$A$280:$A$288,0))+INDEX('Scoring Method'!$B$292:$B$296,MATCH(AQ39,'Scoring Method'!$A$292:$A$296,0))+INDEX('Scoring Method'!$B$300:$B$305,MATCH(AO39,'Scoring Method'!$A$300:$A$305,0))+INDEX('Scoring Method'!$B$309:$B$314,MATCH(AX39,'Scoring Method'!$A$309:$A$314,0))+INDEX('Scoring Method'!$B$337:$B$341,MATCH(X39,'Scoring Method'!$A$337:$A$341,0))+INDEX('Scoring Method'!$B$324:$B$326,MATCH(P39,'Scoring Method'!$A$324:$A$326,0)),1) | BF39: =ROUND(INDEX('Scoring Method'!$B$268:$B$276,MATCH(AE39,'Scoring Method'!$A$268:$A$276,0))*BB39*BD39+INDEX('Scoring Method'!$B$280:$B$288,MATCH(AP39,'Scoring Method'!$A$280:$A$288,0))*BM39*BB39*BD39+INDEX('Scoring Method'!$B$292:$B$296,MATCH(AQ39,'Scoring Method'!$A$292:$A$296,0))*BD39+INDEX('Scoring Method'!$B$300:$B$305,MATCH(AO39,'Scoring Method'!$A$300:$A$305,0))*BM39*BB39+INDEX('Scoring Method'!$B$309:$B$314,MATCH(AX39,'Scoring Method'!$A$309:$A$314,0))+INDEX('Scoring Method'!$B$337:$B$341,MATCH(X39,'Scoring Method'!$A$337:$A$341,0))+INDEX('Scoring Method'!$B$324:$B$326,MATCH(P39,'Scoring Method'!$A$324:$A$326,0)),1) | BG39: Fits (~$4,668/mo) | BH39: AUC | BI39: Auto-Urban Commercial | BL39: Bar permitted | BM39: =INDEX('Scoring Method'!$B$358:$B$363,MATCH(BL39,'Scoring Method'!$A$358:$A$363,0))
A40: 39 | B40: 041-33-08-030.00 | C40: 617 HINDE ST | D40: GABE HOLDINGS LLC | E40: 28 W 5TH ST | F40: COVINGTON | G40: KY | H40: SMALL SHOP | I40: 32600 | J40: =I40/43560 | K40: 727.2 | L40: =I40/(K40^2) | M40: Near 14-18k/32-45k | N40: A | O40: Compact >=.055 | P40: Low | Q40: Local absentee | R40: Passive vehicle | S40: 1 | T40: =INDEX('Scoring Method'!$B$6:$B$9,MATCH(M40,'Scoring Method'!$A$6:$A$9,0))+INDEX('Scoring Method'!$B$12:$B$16,MATCH(N40,'Scoring Method'!$A$12:$A$16,0))+INDEX('Scoring Method'!$B$19:$B$22,MATCH(O40,'Scoring Method'!$A$19:$A$22,0))+INDEX('Scoring Method'!$B$25:$B$27,MATCH(P40,'Scoring Method'!$A$25:$A$27,0)) | U40: =(INDEX('Scoring Method'!$B$30:$B$33,MATCH(Q40,'Scoring Method'!$A$30:$A$33,0))+INDEX('Scoring Method'!$B$36:$B$42,MATCH(R40,'Scoring Method'!$A$36:$A$42,0))+INDEX('Scoring Method'!$B$45:$B$47,MATCH(IF(S40=1,"1",IF(S40=2,"2","3+")),'Scoring Method'!$A$45:$A$47,0)))/90*100 | V40: =T40*U40/100 | X40: X (minimal hazard) | Y40: 30400 | AC40: 0.75 | AD40: ok | AE40: No building | AF40: =INDEX('Scoring Method'!$B$63:$B$71,MATCH(AE40,'Scoring Method'!$A$63:$A$71,0))+INDEX('Scoring Method'!$B$75:$B$79,MATCH("Ample >=15k",'Scoring Method'!$A$75:$A$79,0))+INDEX('Scoring Method'!$B$343:$B$347,MATCH(X40,'Scoring Method'!$A$343:$A$347,0))+INDEX('Scoring Method'!$B$25:$B$27,MATCH(P40,'Scoring Method'!$A$25:$A$27,0)) | AG40: =AF40*U40/100 | AH40: LINK-GIS + LoopNet | AI40: 39.07412 | AJ40: -84.52019 | AK40: 0.72 | AL40: 1.32 | AM40: 1.94 | AN40: 0.72 | AO40: Near 0.35-0.75mi | AP40: Open span | AQ40: Ample >=15k | AS40: =ROUND(INDEX('Scoring Method'!$B$63:$B$70,MATCH(AE40,'Scoring Method'!$A$63:$A$70,0))*0.625+INDEX('Scoring Method'!$B$105:$B$113,MATCH(AP40,'Scoring Method'!$A$105:$A$113,0))+INDEX('Scoring Method'!$B$74:$B$78,MATCH(AQ40,'Scoring Method'!$A$74:$A$78,0))*0.6667+INDEX('Scoring Method'!$B$96:$B$101,MATCH(AO40,'Scoring Method'!$A$96:$A$101,0))+INDEX('Scoring Method'!$B$343:$B$347,MATCH(X40,'Scoring Method'!$A$343:$A$347,0))*0.3333+INDEX('Scoring Method'!$B$25:$B$27,MATCH(P40,'Scoring Method'!$A$25:$A$27,0))*0.3333,1) | AT40: =AS40*U40/100 | AU40: Lewisburg | AV40: 65 | AW40: Sourced | AX40: Moderate 60-69 | AY40: =ROUND(INDEX('Scoring Method'!$B$132:$B$140,MATCH(AE40,'Scoring Method'!$A$132:$A$140,0))+INDEX('Scoring Method'!$B$144:$B$152,MATCH(AP40,'Scoring Method'!$A$144:$A$152,0))+INDEX('Scoring Method'!$B$156:$B$160,MATCH(AQ40,'Scoring Method'!$A$156:$A$160,0))+INDEX('Scoring Method'!$B$164:$B$169,MATCH(AO40,'Scoring Method'!$A$164:$A$169,0))+INDEX('Scoring Method'!$B$173:$B$178,MATCH(AX40,'Scoring Method'!$A$173:$A$178,0))+INDEX('Scoring Method'!$B$349:$B$353,MATCH(X40,'Scoring Method'!$A$349:$A$353,0))+INDEX('Scoring Method'!$B$188:$B$190,MATCH(P40,'Scoring Method'!$A$188:$A$190,0)),1) | AZ40: =AY40*U40/100 | BA40: No chain signal | BB40: 1 | BC40: Right-sized 0.35-0.75 AC | BD40: 1 | BE40: =ROUND(INDEX('Scoring Method'!$B$268:$B$276,MATCH(AE40,'Scoring Method'!$A$268:$A$276,0))+INDEX('Scoring Method'!$B$280:$B$288,MATCH(AP40,'Scoring Method'!$A$280:$A$288,0))+INDEX('Scoring Method'!$B$292:$B$296,MATCH(AQ40,'Scoring Method'!$A$292:$A$296,0))+INDEX('Scoring Method'!$B$300:$B$305,MATCH(AO40,'Scoring Method'!$A$300:$A$305,0))+INDEX('Scoring Method'!$B$309:$B$314,MATCH(AX40,'Scoring Method'!$A$309:$A$314,0))+INDEX('Scoring Method'!$B$337:$B$341,MATCH(X40,'Scoring Method'!$A$337:$A$341,0))+INDEX('Scoring Method'!$B$324:$B$326,MATCH(P40,'Scoring Method'!$A$324:$A$326,0)),1) | BF40: =ROUND(INDEX('Scoring Method'!$B$268:$B$276,MATCH(AE40,'Scoring Method'!$A$268:$A$276,0))*BB40*BD40+INDEX('Scoring Method'!$B$280:$B$288,MATCH(AP40,'Scoring Method'!$A$280:$A$288,0))*BM40*BB40*BD40+INDEX('Scoring Method'!$B$292:$B$296,MATCH(AQ40,'Scoring Method'!$A$292:$A$296,0))*BD40+INDEX('Scoring Method'!$B$300:$B$305,MATCH(AO40,'Scoring Method'!$A$300:$A$305,0))*BM40*BB40+INDEX('Scoring Method'!$B$309:$B$314,MATCH(AX40,'Scoring Method'!$A$309:$A$314,0))+INDEX('Scoring Method'!$B$337:$B$341,MATCH(X40,'Scoring Method'!$A$337:$A$341,0))+INDEX('Scoring Method'!$B$324:$B$326,MATCH(P40,'Scoring Method'!$A$324:$A$326,0)),1) | BH40: SU | BI40: Semi-Urban Residential | BL40: SU corner unverified | BM40: =INDEX('Scoring Method'!$B$358:$B$363,MATCH(BL40,'Scoring Method'!$A$358:$A$363,0))
A41: 40 | B41: 055-31-16-006.00 | C41: 417 E 17TH ST | D41: WIGGINS DANNY T & VICKI J | E41: 1308 ASHFORD PL | F41: FLORENCE | G41: KY | H41: SMALL SHOP | I41: 9238 | J41: =I41/43560 | K41: 385.4 | L41: =I41/(K41^2) | M41: Poor <10k/>60k | N41: A | O41: Compact >=.055 | P41: Low | Q41: Out-of-city KY | R41: Individual | S41: 1 | T41: =INDEX('Scoring Method'!$B$6:$B$9,MATCH(M41,'Scoring Method'!$A$6:$A$9,0))+INDEX('Scoring Method'!$B$12:$B$16,MATCH(N41,'Scoring Method'!$A$12:$A$16,0))+INDEX('Scoring Method'!$B$19:$B$22,MATCH(O41,'Scoring Method'!$A$19:$A$22,0))+INDEX('Scoring Method'!$B$25:$B$27,MATCH(P41,'Scoring Method'!$A$25:$A$27,0)) | U41: =(INDEX('Scoring Method'!$B$30:$B$33,MATCH(Q41,'Scoring Method'!$A$30:$A$33,0))+INDEX('Scoring Method'!$B$36:$B$42,MATCH(R41,'Scoring Method'!$A$36:$A$42,0))+INDEX('Scoring Method'!$B$45:$B$47,MATCH(IF(S41=1,"1",IF(S41=2,"2","3+")),'Scoring Method'!$A$45:$A$47,0)))/90*100 | V41: =T41*U41/100 | W41: 5677 | X41: X (minimal hazard) | Y41: 3550 | Z41: =W41/I41 | AA41: =MAX(0,(Y41-5000)/300) | AC41: 0.2 | AD41: ok | AE41: Large 4-6k | AF41: =INDEX('Scoring Method'!$B$63:$B$71,MATCH(AE41,'Scoring Method'!$A$63:$A$71,0))+INDEX('Scoring Method'!$B$75:$B$79,MATCH("Tight 2-5k",'Scoring Method'!$A$75:$A$79,0))+INDEX('Scoring Method'!$B$343:$B$347,MATCH(X41,'Scoring Method'!$A$343:$A$347,0))+INDEX('Scoring Method'!$B$25:$B$27,MATCH(P41,'Scoring Method'!$A$25:$A$27,0)) | AG41: =AF41*U41/100 | AH41: LINK-GIS + LoopNet | AI41: 39.07126 | AJ41: -84.49888 | AK41: 1.36 | AL41: 1.45 | AM41: 2.21 | AN41: 1.09 | AO41: Fringe 0.75-1.25mi | AP41: Open span | AQ41: Tight 2-5k | AS41: =ROUND(INDEX('Scoring Method'!$B$63:$B$70,MATCH(AE41,'Scoring Method'!$A$63:$A$70,0))*0.625+INDEX('Scoring Method'!$B$105:$B$113,MATCH(AP41,'Scoring Method'!$A$105:$A$113,0))+INDEX('Scoring Method'!$B$74:$B$78,MATCH(AQ41,'Scoring Method'!$A$74:$A$78,0))*0.6667+INDEX('Scoring Method'!$B$96:$B$101,MATCH(AO41,'Scoring Method'!$A$96:$A$101,0))+INDEX('Scoring Method'!$B$343:$B$347,MATCH(X41,'Scoring Method'!$A$343:$A$347,0))*0.3333+INDEX('Scoring Method'!$B$25:$B$27,MATCH(P41,'Scoring Method'!$A$25:$A$27,0))*0.3333,1) | AT41: =AS41*U41/100 | AU41: Austinburg | AV41: 32 | AW41: ESTIMATED | AX41: High <35 | AY41: =ROUND(INDEX('Scoring Method'!$B$132:$B$140,MATCH(AE41,'Scoring Method'!$A$132:$A$140,0))+INDEX('Scoring Method'!$B$144:$B$152,MATCH(AP41,'Scoring Method'!$A$144:$A$152,0))+INDEX('Scoring Method'!$B$156:$B$160,MATCH(AQ41,'Scoring Method'!$A$156:$A$160,0))+INDEX('Scoring Method'!$B$164:$B$169,MATCH(AO41,'Scoring Method'!$A$164:$A$169,0))+INDEX('Scoring Method'!$B$173:$B$178,MATCH(AX41,'Scoring Method'!$A$173:$A$178,0))+INDEX('Scoring Method'!$B$349:$B$353,MATCH(X41,'Scoring Method'!$A$349:$A$353,0))+INDEX('Scoring Method'!$B$188:$B$190,MATCH(P41,'Scoring Method'!$A$188:$A$190,0)),1) | AZ41: =AY41*U41/100 | BA41: No chain signal | BB41: 1 | BC41: Extra small 0.15-0.25 AC | BD41: 0.8 | BE41: =ROUND(INDEX('Scoring Method'!$B$268:$B$276,MATCH(AE41,'Scoring Method'!$A$268:$A$276,0))+INDEX('Scoring Method'!$B$280:$B$288,MATCH(AP41,'Scoring Method'!$A$280:$A$288,0))+INDEX('Scoring Method'!$B$292:$B$296,MATCH(AQ41,'Scoring Method'!$A$292:$A$296,0))+INDEX('Scoring Method'!$B$300:$B$305,MATCH(AO41,'Scoring Method'!$A$300:$A$305,0))+INDEX('Scoring Method'!$B$309:$B$314,MATCH(AX41,'Scoring Method'!$A$309:$A$314,0))+INDEX('Scoring Method'!$B$337:$B$341,MATCH(X41,'Scoring Method'!$A$337:$A$341,0))+INDEX('Scoring Method'!$B$324:$B$326,MATCH(P41,'Scoring Method'!$A$324:$A$326,0)),1) | BF41: =ROUND(INDEX('Scoring Method'!$B$268:$B$276,MATCH(AE41,'Scoring Method'!$A$268:$A$276,0))*BB41*BD41+INDEX('Scoring Method'!$B$280:$B$288,MATCH(AP41,'Scoring Method'!$A$280:$A$288,0))*BM41*BB41*BD41+INDEX('Scoring Method'!$B$292:$B$296,MATCH(AQ41,'Scoring Method'!$A$292:$A$296,0))*BD41+INDEX('Scoring Method'!$B$300:$B$305,MATCH(AO41,'Scoring Method'!$A$300:$A$305,0))*BM41*BB41+INDEX('Scoring Method'!$B$309:$B$314,MATCH(AX41,'Scoring Method'!$A$309:$A$314,0))+INDEX('Scoring Method'!$B$337:$B$341,MATCH(X41,'Scoring Method'!$A$337:$A$341,0))+INDEX('Scoring Method'!$B$324:$B$326,MATCH(P41,'Scoring Method'!$A$324:$A$326,0)),1) | BG41: Fits (~$5,204/mo) | BH41: CMU | BI41: Commercial Mixed Use | BL41: Bar permitted | BM41: =INDEX('Scoring Method'!$B$358:$B$363,MATCH(BL41,'Scoring Method'!$A$358:$A$363,0))
A42: 41 | B42: 055-23-13-001.00 | C42: 2401 MADISON AVE | D42: KENA PROPERTIES LLC | E42: 303 RENN CT | F42: LOUISVILLE | G42: KY | H42: OTHER RETAIL | I42: 32987 | J42: =I42/43560 | K42: 739 | L42: =I42/(K42^2) | M42: Near 14-18k/32-45k | N42: C | O42: Compact >=.055 | P42: Low | Q42: Out-of-city KY | R42: Passive vehicle | S42: 1 | T42: =INDEX('Scoring Method'!$B$6:$B$9,MATCH(M42,'Scoring Method'!$A$6:$A$9,0))+INDEX('Scoring Method'!$B$12:$B$16,MATCH(N42,'Scoring Method'!$A$12:$A$16,0))+INDEX('Scoring Method'!$B$19:$B$22,MATCH(O42,'Scoring Method'!$A$19:$A$22,0))+INDEX('Scoring Method'!$B$25:$B$27,MATCH(P42,'Scoring Method'!$A$25:$A$27,0)) | U42: =(INDEX('Scoring Method'!$B$30:$B$33,MATCH(Q42,'Scoring Method'!$A$30:$A$33,0))+INDEX('Scoring Method'!$B$36:$B$42,MATCH(R42,'Scoring Method'!$A$36:$A$42,0))+INDEX('Scoring Method'!$B$45:$B$47,MATCH(IF(S42=1,"1",IF(S42=2,"2","3+")),'Scoring Method'!$A$45:$A$47,0)))/90*100 | V42: =T42*U42/100 | W42: 7000 | X42: X (minimal hazard) | Y42: 23025 | Z42: =W42/I42 | AA42: =MAX(0,(Y42-5000)/300) | AC42: 0.8 | AD42: ok | AE42: Oversize 6-12k | AF42: =INDEX('Scoring Method'!$B$63:$B$71,MATCH(AE42,'Scoring Method'!$A$63:$A$71,0))+INDEX('Scoring Method'!$B$75:$B$79,MATCH("Ample >=15k",'Scoring Method'!$A$75:$A$79,0))+INDEX('Scoring Method'!$B$343:$B$347,MATCH(X42,'Scoring Method'!$A$343:$A$347,0))+INDEX('Scoring Method'!$B$25:$B$27,MATCH(P42,'Scoring Method'!$A$25:$A$27,0)) | AG42: =AF42*U42/100 | AH42: LINK-GIS + LoopNet | AI42: 39.06256 | AJ42: -84.50522 | AK42: 1.65 | AL42: 1.96 | AM42: 2.72 | AN42: 1.51 | AO42: Outer 1.25-2mi | AP42: Retail shell | AQ42: Ample >=15k | AS42: =ROUND(INDEX('Scoring Method'!$B$63:$B$70,MATCH(AE42,'Scoring Method'!$A$63:$A$70,0))*0.625+INDEX('Scoring Method'!$B$105:$B$113,MATCH(AP42,'Scoring Method'!$A$105:$A$113,0))+INDEX('Scoring Method'!$B$74:$B$78,MATCH(AQ42,'Scoring Method'!$A$74:$A$78,0))*0.6667+INDEX('Scoring Method'!$B$96:$B$101,MATCH(AO42,'Scoring Method'!$A$96:$A$101,0))+INDEX('Scoring Method'!$B$343:$B$347,MATCH(X42,'Scoring Method'!$A$343:$A$347,0))*0.3333+INDEX('Scoring Method'!$B$25:$B$27,MATCH(P42,'Scoring Method'!$A$25:$A$27,0))*0.3333,1) | AT42: =AS42*U42/100 | AU42: Levassor Park | AV42: 42 | AW42: ESTIMATED | AX42: Elevated 35-44 | AY42: =ROUND(INDEX('Scoring Method'!$B$132:$B$140,MATCH(AE42,'Scoring Method'!$A$132:$A$140,0))+INDEX('Scoring Method'!$B$144:$B$152,MATCH(AP42,'Scoring Method'!$A$144:$A$152,0))+INDEX('Scoring Method'!$B$156:$B$160,MATCH(AQ42,'Scoring Method'!$A$156:$A$160,0))+INDEX('Scoring Method'!$B$164:$B$169,MATCH(AO42,'Scoring Method'!$A$164:$A$169,0))+INDEX('Scoring Method'!$B$173:$B$178,MATCH(AX42,'Scoring Method'!$A$173:$A$178,0))+INDEX('Scoring Method'!$B$349:$B$353,MATCH(X42,'Scoring Method'!$A$349:$A$353,0))+INDEX('Scoring Method'!$B$188:$B$190,MATCH(P42,'Scoring Method'!$A$188:$A$190,0)),1) | AZ42: =AY42*U42/100 | BA42: No chain signal | BB42: 1 | BC42: Large 0.75-1.25 AC | BD42: 0.9 | BE42: =ROUND(INDEX('Scoring Method'!$B$268:$B$276,MATCH(AE42,'Scoring Method'!$A$268:$A$276,0))+INDEX('Scoring Method'!$B$280:$B$288,MATCH(AP42,'Scoring Method'!$A$280:$A$288,0))+INDEX('Scoring Method'!$B$292:$B$296,MATCH(AQ42,'Scoring Method'!$A$292:$A$296,0))+INDEX('Scoring Method'!$B$300:$B$305,MATCH(AO42,'Scoring Method'!$A$300:$A$305,0))+INDEX('Scoring Method'!$B$309:$B$314,MATCH(AX42,'Scoring Method'!$A$309:$A$314,0))+INDEX('Scoring Method'!$B$337:$B$341,MATCH(X42,'Scoring Method'!$A$337:$A$341,0))+INDEX('Scoring Method'!$B$324:$B$326,MATCH(P42,'Scoring Method'!$A$324:$A$326,0)),1) | BF42: =ROUND(INDEX('Scoring Method'!$B$268:$B$276,MATCH(AE42,'Scoring Method'!$A$268:$A$276,0))*BB42*BD42+INDEX('Scoring Method'!$B$280:$B$288,MATCH(AP42,'Scoring Method'!$A$280:$A$288,0))*BM42*BB42*BD42+INDEX('Scoring Method'!$B$292:$B$296,MATCH(AQ42,'Scoring Method'!$A$292:$A$296,0))*BD42+INDEX('Scoring Method'!$B$300:$B$305,MATCH(AO42,'Scoring Method'!$A$300:$A$305,0))*BM42*BB42+INDEX('Scoring Method'!$B$309:$B$314,MATCH(AX42,'Scoring Method'!$A$309:$A$314,0))+INDEX('Scoring Method'!$B$337:$B$341,MATCH(X42,'Scoring Method'!$A$337:$A$341,0))+INDEX('Scoring Method'!$B$324:$B$326,MATCH(P42,'Scoring Method'!$A$324:$A$326,0)),1) | BG42: Fits (~$6,417/mo) | BH42: AUC | BI42: Auto-Urban Commercial | BL42: Bar permitted | BM42: =INDEX('Scoring Method'!$B$358:$B$363,MATCH(BL42,'Scoring Method'!$A$358:$A$363,0))
A43: 42 | B43: 040-43-07-001.00 | C43: 410 PHILADELPHIA ST | D43: SINKULA INVESTMENTS LTD CO | E43: 3005 DIXIE HWY STE 150 | F43: EDGEWOOD | G43: KY | H43: FAST FOOD-DRIVE THRU REST | I43: 34491 | J43: =I43/43560 | K43: 746 | L43: =I43/(K43^2) | M43: Near 14-18k/32-45k | N43: C | O43: Compact >=.055 | P43: Low | Q43: Out-of-city KY | R43: Passive vehicle | S43: 1 | T43: =INDEX('Scoring Method'!$B$6:$B$9,MATCH(M43,'Scoring Method'!$A$6:$A$9,0))+INDEX('Scoring Method'!$B$12:$B$16,MATCH(N43,'Scoring Method'!$A$12:$A$16,0))+INDEX('Scoring Method'!$B$19:$B$22,MATCH(O43,'Scoring Method'!$A$19:$A$22,0))+INDEX('Scoring Method'!$B$25:$B$27,MATCH(P43,'Scoring Method'!$A$25:$A$27,0)) | U43: =(INDEX('Scoring Method'!$B$30:$B$33,MATCH(Q43,'Scoring Method'!$A$30:$A$33,0))+INDEX('Scoring Method'!$B$36:$B$42,MATCH(R43,'Scoring Method'!$A$36:$A$42,0))+INDEX('Scoring Method'!$B$45:$B$47,MATCH(IF(S43=1,"1",IF(S43=2,"2","3+")),'Scoring Method'!$A$45:$A$47,0)))/90*100 | V43: =T43*U43/100 | W43: 2560 | X43: X (minimal hazard) | Y43: 30000 | Z43: =W43/I43 | AA43: =MAX(0,(Y43-5000)/300) | AC43: 0.79 | AD43: ok | AE43: Above 2.5-4k | AF43: =INDEX('Scoring Method'!$B$63:$B$71,MATCH(AE43,'Scoring Method'!$A$63:$A$71,0))+INDEX('Scoring Method'!$B$75:$B$79,MATCH("Ample >=15k",'Scoring Method'!$A$75:$A$79,0))+INDEX('Scoring Method'!$B$343:$B$347,MATCH(X43,'Scoring Method'!$A$343:$A$347,0))+INDEX('Scoring Method'!$B$25:$B$27,MATCH(P43,'Scoring Method'!$A$25:$A$27,0)) | AG43: =AF43*U43/100 | AH43: LINK-GIS + LoopNet | AI43: 39.08611 | AJ43: -84.51947 | AK43: 0.15 | AL43: 0.68 | AM43: 1.13 | AN43: 0.15 | AO43: Core <=0.35mi | AP43: Built-out kitchen | AQ43: Ample >=15k | AS43: =ROUND(INDEX('Scoring Method'!$B$63:$B$70,MATCH(AE43,'Scoring Method'!$A$63:$A$70,0))*0.625+INDEX('Scoring Method'!$B$105:$B$113,MATCH(AP43,'Scoring Method'!$A$105:$A$113,0))+INDEX('Scoring Method'!$B$74:$B$78,MATCH(AQ43,'Scoring Method'!$A$74:$A$78,0))*0.6667+INDEX('Scoring Method'!$B$96:$B$101,MATCH(AO43,'Scoring Method'!$A$96:$A$101,0))+INDEX('Scoring Method'!$B$343:$B$347,MATCH(X43,'Scoring Method'!$A$343:$A$347,0))*0.3333+INDEX('Scoring Method'!$B$25:$B$27,MATCH(P43,'Scoring Method'!$A$25:$A$27,0))*0.3333,1) | AT43: =AS43*U43/100 | AU43: Botany Hills / Riverfront West | AV43: 45 | AW43: ESTIMATED | AX43: Mixed 45-59 | AY43: =ROUND(INDEX('Scoring Method'!$B$132:$B$140,MATCH(AE43,'Scoring Method'!$A$132:$A$140,0))+INDEX('Scoring Method'!$B$144:$B$152,MATCH(AP43,'Scoring Method'!$A$144:$A$152,0))+INDEX('Scoring Method'!$B$156:$B$160,MATCH(AQ43,'Scoring Method'!$A$156:$A$160,0))+INDEX('Scoring Method'!$B$164:$B$169,MATCH(AO43,'Scoring Method'!$A$164:$A$169,0))+INDEX('Scoring Method'!$B$173:$B$178,MATCH(AX43,'Scoring Method'!$A$173:$A$178,0))+INDEX('Scoring Method'!$B$349:$B$353,MATCH(X43,'Scoring Method'!$A$349:$A$353,0))+INDEX('Scoring Method'!$B$188:$B$190,MATCH(P43,'Scoring Method'!$A$188:$A$190,0)),1) | AZ43: =AY43*U43/100 | BA43: Chain format + investor | BB43: 0.45 | BC43: Large 0.75-1.25 AC | BD43: 0.9 | BE43: =ROUND(INDEX('Scoring Method'!$B$268:$B$276,MATCH(AE43,'Scoring Method'!$A$268:$A$276,0))+INDEX('Scoring Method'!$B$280:$B$288,MATCH(AP43,'Scoring Method'!$A$280:$A$288,0))+INDEX('Scoring Method'!$B$292:$B$296,MATCH(AQ43,'Scoring Method'!$A$292:$A$296,0))+INDEX('Scoring Method'!$B$300:$B$305,MATCH(AO43,'Scoring Method'!$A$300:$A$305,0))+INDEX('Scoring Method'!$B$309:$B$314,MATCH(AX43,'Scoring Method'!$A$309:$A$314,0))+INDEX('Scoring Method'!$B$337:$B$341,MATCH(X43,'Scoring Method'!$A$337:$A$341,0))+INDEX('Scoring Method'!$B$324:$B$326,MATCH(P43,'Scoring Method'!$A$324:$A$326,0)),1) | BF43: =ROUND(INDEX('Scoring Method'!$B$268:$B$276,MATCH(AE43,'Scoring Method'!$A$268:$A$276,0))*BB43*BD43+INDEX('Scoring Method'!$B$280:$B$288,MATCH(AP43,'Scoring Method'!$A$280:$A$288,0))*BM43*BB43*BD43+INDEX('Scoring Method'!$B$292:$B$296,MATCH(AQ43,'Scoring Method'!$A$292:$A$296,0))*BD43+INDEX('Scoring Method'!$B$300:$B$305,MATCH(AO43,'Scoring Method'!$A$300:$A$305,0))*BM43*BB43+INDEX('Scoring Method'!$B$309:$B$314,MATCH(AX43,'Scoring Method'!$A$309:$A$314,0))+INDEX('Scoring Method'!$B$337:$B$341,MATCH(X43,'Scoring Method'!$A$337:$A$341,0))+INDEX('Scoring Method'!$B$324:$B$326,MATCH(P43,'Scoring Method'!$A$324:$A$326,0)),1) | BG43: Fits (~$2,347/mo) | BH43: AUC | BI43: Auto-Urban Commercial | BL43: Bar permitted | BM43: =INDEX('Scoring Method'!$B$358:$B$363,MATCH(BL43,'Scoring Method'!$A$358:$A$363,0))
A44: 43 | B44: 054-22-40-002.00 | C44: 1204 RUSSELL ST | D44: KIRN RONALD C & MELISSA | E44: 408 OLIVIA LN | F44: FT WRIGHT | G44: KY | H44: AUTO SERVICE/REPAIR | I44: 10393 | J44: =I44/43560 | K44: 495.8 | L44: =I44/(K44^2) | M44: Marginal 10-14k/45-60k | N44: A | O44: Elongated .035-.045 | P44: Moderate | Q44: Out-of-city KY | R44: Individual | S44: 2 | T44: =INDEX('Scoring Method'!$B$6:$B$9,MATCH(M44,'Scoring Method'!$A$6:$A$9,0))+INDEX('Scoring Method'!$B$12:$B$16,MATCH(N44,'Scoring Method'!$A$12:$A$16,0))+INDEX('Scoring Method'!$B$19:$B$22,MATCH(O44,'Scoring Method'!$A$19:$A$22,0))+INDEX('Scoring Method'!$B$25:$B$27,MATCH(P44,'Scoring Method'!$A$25:$A$27,0)) | U44: =(INDEX('Scoring Method'!$B$30:$B$33,MATCH(Q44,'Scoring Method'!$A$30:$A$33,0))+INDEX('Scoring Method'!$B$36:$B$42,MATCH(R44,'Scoring Method'!$A$36:$A$42,0))+INDEX('Scoring Method'!$B$45:$B$47,MATCH(IF(S44=1,"1",IF(S44=2,"2","3+")),'Scoring Method'!$A$45:$A$47,0)))/90*100 | V44: =T44*U44/100 | W44: 9650 | X44: X (minimal hazard) | Y44: 1050 | Z44: =W44/I44 | AA44: =MAX(0,(Y44-5000)/300) | AC44: 0.12 | AD44: CHECK | AE44: Oversize 6-12k | AF44: =INDEX('Scoring Method'!$B$63:$B$71,MATCH(AE44,'Scoring Method'!$A$63:$A$71,0))+INDEX('Scoring Method'!$B$75:$B$79,MATCH("Insufficient <2k",'Scoring Method'!$A$75:$A$79,0))+INDEX('Scoring Method'!$B$343:$B$347,MATCH(X44,'Scoring Method'!$A$343:$A$347,0))+INDEX('Scoring Method'!$B$25:$B$27,MATCH(P44,'Scoring Method'!$A$25:$A$27,0)) | AG44: =AF44*U44/100 | AH44: LINK-GIS + LoopNet | AI44: 39.07697 | AJ44: -84.51123 | AK44: 0.62 | AL44: 0.97 | AM44: 1.7 | AN44: 0.48 | AO44: Near 0.35-0.75mi | AP44: Open span | AQ44: Insufficient <2k | AS44: =ROUND(INDEX('Scoring Method'!$B$63:$B$70,MATCH(AE44,'Scoring Method'!$A$63:$A$70,0))*0.625+INDEX('Scoring Method'!$B$105:$B$113,MATCH(AP44,'Scoring Method'!$A$105:$A$113,0))+INDEX('Scoring Method'!$B$74:$B$78,MATCH(AQ44,'Scoring Method'!$A$74:$A$78,0))*0.6667+INDEX('Scoring Method'!$B$96:$B$101,MATCH(AO44,'Scoring Method'!$A$96:$A$101,0))+INDEX('Scoring Method'!$B$343:$B$347,MATCH(X44,'Scoring Method'!$A$343:$A$347,0))*0.3333+INDEX('Scoring Method'!$B$25:$B$27,MATCH(P44,'Scoring Method'!$A$25:$A$27,0))*0.3333,1) | AT44: =AS44*U44/100 | AU44: Old Seminary Square | AV44: 35 | AW44: ESTIMATED | AX44: Elevated 35-44 | AY44: =ROUND(INDEX('Scoring Method'!$B$132:$B$140,MATCH(AE44,'Scoring Method'!$A$132:$A$140,0))+INDEX('Scoring Method'!$B$144:$B$152,MATCH(AP44,'Scoring Method'!$A$144:$A$152,0))+INDEX('Scoring Method'!$B$156:$B$160,MATCH(AQ44,'Scoring Method'!$A$156:$A$160,0))+INDEX('Scoring Method'!$B$164:$B$169,MATCH(AO44,'Scoring Method'!$A$164:$A$169,0))+INDEX('Scoring Method'!$B$173:$B$178,MATCH(AX44,'Scoring Method'!$A$173:$A$178,0))+INDEX('Scoring Method'!$B$349:$B$353,MATCH(X44,'Scoring Method'!$A$349:$A$353,0))+INDEX('Scoring Method'!$B$188:$B$190,MATCH(P44,'Scoring Method'!$A$188:$A$190,0)),1) | AZ44: =AY44*U44/100 | BA44: No chain signal | BB44: 1 | BC44: Extra small 0.15-0.25 AC | BD44: 0.8 | BE44: =ROUND(INDEX('Scoring Method'!$B$268:$B$276,MATCH(AE44,'Scoring Method'!$A$268:$A$276,0))+INDEX('Scoring Method'!$B$280:$B$288,MATCH(AP44,'Scoring Method'!$A$280:$A$288,0))+INDEX('Scoring Method'!$B$292:$B$296,MATCH(AQ44,'Scoring Method'!$A$292:$A$296,0))+INDEX('Scoring Method'!$B$300:$B$305,MATCH(AO44,'Scoring Method'!$A$300:$A$305,0))+INDEX('Scoring Method'!$B$309:$B$314,MATCH(AX44,'Scoring Method'!$A$309:$A$314,0))+INDEX('Scoring Method'!$B$337:$B$341,MATCH(X44,'Scoring Method'!$A$337:$A$341,0))+INDEX('Scoring Method'!$B$324:$B$326,MATCH(P44,'Scoring Method'!$A$324:$A$326,0)),1) | BF44: =ROUND(INDEX('Scoring Method'!$B$268:$B$276,MATCH(AE44,'Scoring Method'!$A$268:$A$276,0))*BB44*BD44+INDEX('Scoring Method'!$B$280:$B$288,MATCH(AP44,'Scoring Method'!$A$280:$A$288,0))*BM44*BB44*BD44+INDEX('Scoring Method'!$B$292:$B$296,MATCH(AQ44,'Scoring Method'!$A$292:$A$296,0))*BD44+INDEX('Scoring Method'!$B$300:$B$305,MATCH(AO44,'Scoring Method'!$A$300:$A$305,0))*BM44*BB44+INDEX('Scoring Method'!$B$309:$B$314,MATCH(AX44,'Scoring Method'!$A$309:$A$314,0))+INDEX('Scoring Method'!$B$337:$B$341,MATCH(X44,'Scoring Method'!$A$337:$A$341,0))+INDEX('Scoring Method'!$B$324:$B$326,MATCH(P44,'Scoring Method'!$A$324:$A$326,0)),1) | BG44: Fits (~$8,846/mo) | BH44: TUMU (TS) | BI44: Traditional Urban Mixed Use | BK44: Yes | BL44: Bar permitted | BM44: =INDEX('Scoring Method'!$B$358:$B$363,MATCH(BL44,'Scoring Method'!$A$358:$A$363,0))
A45: 44 | B45: 056-20-00-059.04 | C45: 1 W 43RD ST | D45: J & S LATONIA CENTRE KY LLC | E45: PO BOX 24550 | F45: COLUMBUS | G45: OH | H45: PAVED LOT | I45: 43556 | J45: =I45/43560 | K45: 835.6 | L45: =I45/(K45^2) | M45: Near 14-18k/32-45k | N45: D | O45: Compact >=.055 | P45: Low | Q45: Out-of-state | R45: Operating entity | S45: 4 | T45: =INDEX('Scoring Method'!$B$6:$B$9,MATCH(M45,'Scoring Method'!$A$6:$A$9,0))+INDEX('Scoring Method'!$B$12:$B$16,MATCH(N45,'Scoring Method'!$A$12:$A$16,0))+INDEX('Scoring Method'!$B$19:$B$22,MATCH(O45,'Scoring Method'!$A$19:$A$22,0))+INDEX('Scoring Method'!$B$25:$B$27,MATCH(P45,'Scoring Method'!$A$25:$A$27,0)) | U45: =(INDEX('Scoring Method'!$B$30:$B$33,MATCH(Q45,'Scoring Method'!$A$30:$A$33,0))+INDEX('Scoring Method'!$B$36:$B$42,MATCH(R45,'Scoring Method'!$A$36:$A$42,0))+INDEX('Scoring Method'!$B$45:$B$47,MATCH(IF(S45=1,"1",IF(S45=2,"2","3+")),'Scoring Method'!$A$45:$A$47,0)))/90*100 | V45: =T45*U45/100 | W45: 31 | X45: X (minimal hazard) | Y45: 43275 | AA45: =MAX(0,(Y45-5000)/300) | AE45: Too small <1.2k | AF45: =INDEX('Scoring Method'!$B$63:$B$71,MATCH(AE45,'Scoring Method'!$A$63:$A$71,0))+INDEX('Scoring Method'!$B$75:$B$79,MATCH("Ample >=15k",'Scoring Method'!$A$75:$A$79,0))+INDEX('Scoring Method'!$B$343:$B$347,MATCH(X45,'Scoring Method'!$A$343:$A$347,0))+INDEX('Scoring Method'!$B$25:$B$27,MATCH(P45,'Scoring Method'!$A$25:$A$27,0)) | AG45: =AF45*U45/100 | AH45: LINK-GIS only | AI45: 39.0413 | AJ45: -84.50776 | AK45: 3.03 | AL45: 3.42 | AM45: 4.17 | AN45: 2.95 | AO45: Distant 2-3mi | AP45: Lot / minimal bldg | AQ45: Ample >=15k | AS45: =ROUND(INDEX('Scoring Method'!$B$63:$B$70,MATCH(AE45,'Scoring Method'!$A$63:$A$70,0))*0.625+INDEX('Scoring Method'!$B$105:$B$113,MATCH(AP45,'Scoring Method'!$A$105:$A$113,0))+INDEX('Scoring Method'!$B$74:$B$78,MATCH(AQ45,'Scoring Method'!$A$74:$A$78,0))*0.6667+INDEX('Scoring Method'!$B$96:$B$101,MATCH(AO45,'Scoring Method'!$A$96:$A$101,0))+INDEX('Scoring Method'!$B$343:$B$347,MATCH(X45,'Scoring Method'!$A$343:$A$347,0))*0.3333+INDEX('Scoring Method'!$B$25:$B$27,MATCH(P45,'Scoring Method'!$A$25:$A$27,0))*0.3333,1) | AT45: =AS45*U45/100 | AU45: Rittes East / Winston Park | AV45: 82 | AW45: Sourced | AX45: Very safe 80+ | AY45: =ROUND(INDEX('Scoring Method'!$B$132:$B$140,MATCH(AE45,'Scoring Method'!$A$132:$A$140,0))+INDEX('Scoring Method'!$B$144:$B$152,MATCH(AP45,'Scoring Method'!$A$144:$A$152,0))+INDEX('Scoring Method'!$B$156:$B$160,MATCH(AQ45,'Scoring Method'!$A$156:$A$160,0))+INDEX('Scoring Method'!$B$164:$B$169,MATCH(AO45,'Scoring Method'!$A$164:$A$169,0))+INDEX('Scoring Method'!$B$173:$B$178,MATCH(AX45,'Scoring Method'!$A$173:$A$178,0))+INDEX('Scoring Method'!$B$349:$B$353,MATCH(X45,'Scoring Method'!$A$349:$A$353,0))+INDEX('Scoring Method'!$B$188:$B$190,MATCH(P45,'Scoring Method'!$A$188:$A$190,0)),1) | AZ45: =AY45*U45/100 | BA45: No chain signal | BB45: 1 | BC45: Large 0.75-1.25 AC | BD45: 0.9 | BE45: =ROUND(INDEX('Scoring Method'!$B$268:$B$276,MATCH(AE45,'Scoring Method'!$A$268:$A$276,0))+INDEX('Scoring Method'!$B$280:$B$288,MATCH(AP45,'Scoring Method'!$A$280:$A$288,0))+INDEX('Scoring Method'!$B$292:$B$296,MATCH(AQ45,'Scoring Method'!$A$292:$A$296,0))+INDEX('Scoring Method'!$B$300:$B$305,MATCH(AO45,'Scoring Method'!$A$300:$A$305,0))+INDEX('Scoring Method'!$B$309:$B$314,MATCH(AX45,'Scoring Method'!$A$309:$A$314,0))+INDEX('Scoring Method'!$B$337:$B$341,MATCH(X45,'Scoring Method'!$A$337:$A$341,0))+INDEX('Scoring Method'!$B$324:$B$326,MATCH(P45,'Scoring Method'!$A$324:$A$326,0)),1) | BF45: =ROUND(INDEX('Scoring Method'!$B$268:$B$276,MATCH(AE45,'Scoring Method'!$A$268:$A$276,0))*BB45*BD45+INDEX('Scoring Method'!$B$280:$B$288,MATCH(AP45,'Scoring Method'!$A$280:$A$288,0))*BM45*BB45*BD45+INDEX('Scoring Method'!$B$292:$B$296,MATCH(AQ45,'Scoring Method'!$A$292:$A$296,0))*BD45+INDEX('Scoring Method'!$B$300:$B$305,MATCH(AO45,'Scoring Method'!$A$300:$A$305,0))*BM45*BB45+INDEX('Scoring Method'!$B$309:$B$314,MATCH(AX45,'Scoring Method'!$A$309:$A$314,0))+INDEX('Scoring Method'!$B$337:$B$341,MATCH(X45,'Scoring Method'!$A$337:$A$341,0))+INDEX('Scoring Method'!$B$324:$B$326,MATCH(P45,'Scoring Method'!$A$324:$A$326,0)),1) | BG45: Fits (~$28/mo) | BH45: AUC | BI45: Auto-Urban Commercial | BL45: Bar permitted | BM45: =INDEX('Scoring Method'!$B$358:$B$363,MATCH(BL45,'Scoring Method'!$A$358:$A$363,0))
A46: 45 | B46: 055-14-11-007.00 | C46: 1833 MADISON AVE | D46: BANK OF KENTUCKY | E46: PROPERTY TAX COMPLIANCE | F46: WINSTON SALEM | G46: NC | H46: FULL SERVICE BANK | I46: 17615 | J46: =I46/43560 | K46: 558 | L46: =I46/(K46^2) | M46: Near 14-18k/32-45k | N46: E | O46: Compact >=.055 | P46: Low | Q46: Out-of-state | R46: Individual | S46: 1 | T46: =INDEX('Scoring Method'!$B$6:$B$9,MATCH(M46,'Scoring Method'!$A$6:$A$9,0))+INDEX('Scoring Method'!$B$12:$B$16,MATCH(N46,'Scoring Method'!$A$12:$A$16,0))+INDEX('Scoring Method'!$B$19:$B$22,MATCH(O46,'Scoring Method'!$A$19:$A$22,0))+INDEX('Scoring Method'!$B$25:$B$27,MATCH(P46,'Scoring Method'!$A$25:$A$27,0)) | U46: =(INDEX('Scoring Method'!$B$30:$B$33,MATCH(Q46,'Scoring Method'!$A$30:$A$33,0))+INDEX('Scoring Method'!$B$36:$B$42,MATCH(R46,'Scoring Method'!$A$36:$A$42,0))+INDEX('Scoring Method'!$B$45:$B$47,MATCH(IF(S46=1,"1",IF(S46=2,"2","3+")),'Scoring Method'!$A$45:$A$47,0)))/90*100 | V46: =T46*U46/100 | W46: 2900 | X46: X (minimal hazard) | Y46: 11525 | AA46: =MAX(0,(Y46-5000)/300) | AE46: Above 2.5-4k | AF46: =INDEX('Scoring Method'!$B$63:$B$71,MATCH(AE46,'Scoring Method'!$A$63:$A$71,0))+INDEX('Scoring Method'!$B$75:$B$79,MATCH("Good 8-15k",'Scoring Method'!$A$75:$A$79,0))+INDEX('Scoring Method'!$B$343:$B$347,MATCH(X46,'Scoring Method'!$A$343:$A$347,0))+INDEX('Scoring Method'!$B$25:$B$27,MATCH(P46,'Scoring Method'!$A$25:$A$27,0)) | AG46: =AF46*U46/100 | AH46: LINK-GIS + LoopNet (2026-08-03) | AI46: 39.06812 | AJ46: -84.5066 | AK46: 1.28 | AL46: 1.57 | AM46: 2.33 | AN46: 1.12 | AO46: Fringe 0.75-1.25mi | AP46: Office/institutional | AQ46: Good 8-15k | AS46: =ROUND(INDEX('Scoring Method'!$B$63:$B$70,MATCH(AE46,'Scoring Method'!$A$63:$A$70,0))*0.625+INDEX('Scoring Method'!$B$105:$B$113,MATCH(AP46,'Scoring Method'!$A$105:$A$113,0))+INDEX('Scoring Method'!$B$74:$B$78,MATCH(AQ46,'Scoring Method'!$A$74:$A$78,0))*0.6667+INDEX('Scoring Method'!$B$96:$B$101,MATCH(AO46,'Scoring Method'!$A$96:$A$101,0))+INDEX('Scoring Method'!$B$343:$B$347,MATCH(X46,'Scoring Method'!$A$343:$A$347,0))*0.3333+INDEX('Scoring Method'!$B$25:$B$27,MATCH(P46,'Scoring Method'!$A$25:$A$27,0))*0.3333,1) | AT46: =AS46*U46/100 | AU46: Levassor Park | AV46: 42 | AW46: ESTIMATED | AX46: Elevated 35-44 | AY46: =ROUND(INDEX('Scoring Method'!$B$132:$B$140,MATCH(AE46,'Scoring Method'!$A$132:$A$140,0))+INDEX('Scoring Method'!$B$144:$B$152,MATCH(AP46,'Scoring Method'!$A$144:$A$152,0))+INDEX('Scoring Method'!$B$156:$B$160,MATCH(AQ46,'Scoring Method'!$A$156:$A$160,0))+INDEX('Scoring Method'!$B$164:$B$169,MATCH(AO46,'Scoring Method'!$A$164:$A$169,0))+INDEX('Scoring Method'!$B$173:$B$178,MATCH(AX46,'Scoring Method'!$A$173:$A$178,0))+INDEX('Scoring Method'!$B$349:$B$353,MATCH(X46,'Scoring Method'!$A$349:$A$353,0))+INDEX('Scoring Method'!$B$188:$B$190,MATCH(P46,'Scoring Method'!$A$188:$A$190,0)),1) | AZ46: =AY46*U46/100 | BA46: Brand-owned / net lease | BB46: 0.3 | BC46: Right-sized 0.35-0.75 AC | BD46: 1 | BE46: =ROUND(INDEX('Scoring Method'!$B$268:$B$276,MATCH(AE46,'Scoring Method'!$A$268:$A$276,0))+INDEX('Scoring Method'!$B$280:$B$288,MATCH(AP46,'Scoring Method'!$A$280:$A$288,0))+INDEX('Scoring Method'!$B$292:$B$296,MATCH(AQ46,'Scoring Method'!$A$292:$A$296,0))+INDEX('Scoring Method'!$B$300:$B$305,MATCH(AO46,'Scoring Method'!$A$300:$A$305,0))+INDEX('Scoring Method'!$B$309:$B$314,MATCH(AX46,'Scoring Method'!$A$309:$A$314,0))+INDEX('Scoring Method'!$B$337:$B$341,MATCH(X46,'Scoring Method'!$A$337:$A$341,0))+INDEX('Scoring Method'!$B$324:$B$326,MATCH(P46,'Scoring Method'!$A$324:$A$326,0)),1) | BF46: =ROUND(INDEX('Scoring Method'!$B$268:$B$276,MATCH(AE46,'Scoring Method'!$A$268:$A$276,0))*BB46*BD46+INDEX('Scoring Method'!$B$280:$B$288,MATCH(AP46,'Scoring Method'!$A$280:$A$288,0))*BM46*BB46*BD46+INDEX('Scoring Method'!$B$292:$B$296,MATCH(AQ46,'Scoring Method'!$A$292:$A$296,0))*BD46+INDEX('Scoring Method'!$B$300:$B$305,MATCH(AO46,'Scoring Method'!$A$300:$A$305,0))*BM46*BB46+INDEX('Scoring Method'!$B$309:$B$314,MATCH(AX46,'Scoring Method'!$A$309:$A$314,0))+INDEX('Scoring Method'!$B$337:$B$341,MATCH(X46,'Scoring Method'!$A$337:$A$341,0))+INDEX('Scoring Method'!$B$324:$B$326,MATCH(P46,'Scoring Method'!$A$324:$A$326,0)),1) | BG46: Fits (~$2,658/mo) | BH46: AUC | BI46: Auto-Urban Commercial | BL46: Bar permitted | BM46: =INDEX('Scoring Method'!$B$358:$B$363,MATCH(BL46,'Scoring Method'!$A$358:$A$363,0))
